Workbook
Name FirstX: 'Propriedades geométricas VIGA'!$B$6
Name FirstX: 'Propriedades geométricas LAJE'!$B$6
Name testex: 'ELU i'!$T$85:$T$99
Name testey: 'ELU i'!$U$85:$U$99
Name X: OFFSET(FirstX,0,0,COUNT('Propriedades geométricas VIGA'!$B$1:$B$65531))
Name X: OFFSET('Propriedades geométricas LAJE'!FirstX,0,0,COUNT('Propriedades geométricas LAJE'!$B$1:$B$65531))
Name XX: 'ELU i'!$T$4:$T$18
Name XXX: 'ELU i'!$T$27:$T$41
Name XXXX: 'ELU i'!$T$52:$T$66
Name Y: OFFSET(X,0,1)
Name Y: OFFSET('Propriedades geométricas LAJE'!X,0,1)
Name YY: 'ELU i'!$U$4:$U$18
Name YYY: 'ELU i'!$U$27:$U$41
Name YYYY: 'ELU i'!$U$52:$U$66

Sheet Geometria
K1: Homogeneizar seção? | L1: FALSE | M1: Deformações t=1 | O1: =N1284 -> -1.1762592 | P1: =IF(M19="1 - Retângular","","Estádios Viga 'i'") | Q1: =IF(M19="1 - Retângular","",'ELU i'!G145)
M2: Deformações diferidas - t=inf | O2: =N1281 -> 0.73209376 | P2: Fissuração T=1 | Q2: =IF(L1209>L1214,"Ok","Estádio II") -> Ok
M3: Taxa | O3: =Taxas!L56 -> 290.7128 | P3: Fissuração T,inf | Q3: =IF(L1220>L1222,"Ok","Estádio II") -> Estádio II
K4: =IF(M19="1 - Retângular","Estádios viga retângular","") -> Estádios viga retângular | M4: As'p | N4: =Taxas!H50 -> 3 | O4: 16 | P4: As',adicional | Q4: 0 | R4: x
K5: =IF(M19="1 - Retângular",IF(M19="2 - i",M1083,IF(M19="3 - Transição",M1083,(_xlfn.CONCAT((IF(M18="1 - Sim",(IF(K1087="Seção 'T' Verdadeira",O1122,L1078)),L1078))," - ",M1075)))),"") -> Domínio 3 - Armadura simples | M5: As,p | N5: =Taxas!H57 -> 12 | O5: 16 | P5: As',adicional | Q5: 0 | R5: x
K6: ='Fissuração - wk por Seção'!N107
K7: 1 . Dados de entrada
K9: Cargas atuantes | T9: tamanhos estribos (U14 = aba Cisalhamento e Apoios, item 3b) | X9: Peso lajes
K10: Sobrecarga da laje = q0 | L10: 2500 | M10: kgf/m² | Q10: Linha neutra - Viga "i" | T10: T | U10: =(L26-2*R76)+18+(L37-2*R76)+(L38+L26-2*R76)+L38+(L37-2*R76)+18+(L27-L38)+(L26-2*R76)+(L27+L42-2*R76)+(L26-2*R76)+(L27+L42-2*R76) -> 388 | X10: 20 | Y10: 320
K11: Laje = g1 | L11: 355 | M11: kgf/m² | Q11: =IF(Q614="Ok","Ok","OBS: Valor da linha neutra é MAIOR que hf1 - armadura ativa necessita verificação") -> Ok | T11: R/A | U11: =(L27-2*R76)+(L26-2*R76)+(L27+L42-2*R76)+(L39-2*R76)+L42+(L26-(L39-2*R76)-2*R76) -> 206 | X11: 25 | Y11: 355
F12: Tabela 11.2 – Valores do coeficiente γf2 | K12: Revestimento = g2 | L12: 100 | M12: kgf/m² | T12: R | U12: =(L27-2*R76)*2+(L26-2*R76)*2 -> 156 | X12: 30 | Y12: 430
F13: Ações | G13: γf2 | K13: Alvenaria = g3 | L13: =L15/100*L16*L17/100 -> 0 | M13: kgf/m | T13: "i" | U13: =7+(L61-2*R76)+((L60-L61)/2)+L63+(L61-2*R76)+L63+(L63-2*R76)+((L60-L61)/2)+(L70-2*R76)+((L62-L61)/2-R76)+((L62-L61)/2)+(L67-2*R76)+15+((L62-L61)/2)-R76+15+(((L62-L61)/2)-R76+((L62-L61)/2))+(L70-2*R76)+(((L62-L61)/2)-R76+((L62-L61)/2))+7 -> 361
G14: Ψ0 | H14: Ψ1 | I14: Ψ2 | K14: Alvenaria | Q14: As' | U14: ='Cisalhamento e Apoios'!$J$76/100 -> 3.64 | V14: m
F15: Cargas de utilização de edificações | K15: e,alv | L15: 0 | M15: cm | Q15: =Taxas!L60 -> 0
F16: Locais em que não há predominância de pesos de equipamentos que permanecem fixos por longos períodos de tempo, nem de elevadas concentrações de pessoas b | G16: 0.5 | H16: 0.4 | I16: 0.3 | K16: y,alv | L16: 1350 | M16: kgf/m² | V16: ='Propriedades geométricas VIGA'!B7 -> 0 | W16: ='Propriedades geométricas VIGA'!C7 -> 0
K17: h,alv | L17: =350-50 -> 300 | M17: cm | V17: ='Propriedades geométricas VIGA'!B8 -> -15 | W17: ='Propriedades geométricas VIGA'!C8 -> 0
K18: Considerar solidarização | M18: 1 - Sim | Q18: As | V18: ='Propriedades geométricas VIGA'!B9 -> -15 | W18: ='Propriedades geométricas VIGA'!C9 -> 40
K19: Seção | M19: 1 - Retângular | Q19: =Taxas!L64 -> 8Ø15.2mm | V19: ='Propriedades geométricas VIGA'!B10 -> -15 | W19: ='Propriedades geométricas VIGA'!C10 -> 45
F20: Locais em que há predominância de pesos de equipamentos que permanecem fixos por longos períodos de tempo, ou de elevada concentração de pessoas c | G20: 0.7 | H20: 0.6 | I20: 0.4 | M20: 3 - R/A | V20: ='Propriedades geométricas VIGA'!B11 -> -15 | W20: ='Propriedades geométricas VIGA'!C11 -> 60
K21: L,balanço,esq | L21: 0 | N21: Comprimento do balanço esquerdo. | V21: ='Propriedades geométricas VIGA'!B12 -> 15 | W21: ='Propriedades geométricas VIGA'!C12 -> 60
K22: L,balanço,dir | L22: 0 | N22: Comprimento do balanço dirito. | V22: ='Propriedades geométricas VIGA'!B13 -> 15 | W22: ='Propriedades geométricas VIGA'!C13 -> 45
F23: Biblioteca, arquivos, oficinas e garagens | G23: 0.8 | H23: 0.7 | I23: 0.6 | K23: Geometria da viga retângular | Q23: Armadura Passiva - ELU | V23: ='Propriedades geométricas VIGA'!B14 -> 15 | W23: ='Propriedades geométricas VIGA'!C14 -> 40
L24: Simples | M24: Composta | Q24: =K1150 -> Necessita armadura passiva ELU | V24: ='Propriedades geométricas VIGA'!B15 -> 15 | W24: ='Propriedades geométricas VIGA'!C15 -> 0
F25: Vento | K25: L,útil | L25: 815 | N25: Comprimento total da viga. | V25: ='Propriedades geométricas VIGA'!B16 -> 0 | W25: ='Propriedades geométricas VIGA'!C16 -> 0
F26: Pressão dinâmica do vento nas estruturas em geral | G26: 0.6 | H26: 0.3 | I26: 0 | K26: bw | L26: 30 | N26: Largura da viga. | V26: ='Propriedades geométricas VIGA'!B17 -> 0 | W26: ='Propriedades geométricas VIGA'!C17 -> 0
K27: h | L27: 60 | N27: Altura da viga. | V27: ='Propriedades geométricas VIGA'!B18 -> 0 | W27: ='Propriedades geométricas VIGA'!C18 -> 0
F28: Temperatura | K28: l,console | L28: 30 | N28: Comprimento do console. | V28: ='Propriedades geométricas VIGA'!B19 -> 0 | W28: ='Propriedades geométricas VIGA'!C19 -> 0
F29: Variações uniformes de temperatura em relação à média anual local | G29: 0.6 | H29: 0.5 | I29: 0.3 | K29: L,útil | L29: =L25-L28 -> 785 | N29: Comprimento útil da viga. | V29: ='Propriedades geométricas VIGA'!B20 -> 0 | W29: ='Propriedades geométricas VIGA'!C20 -> 0
K30: y'.1 | L30: =IF(L1=TRUE(),Homogeneização!L55,'Propriedades geométricas VIGA'!M7) -> 30 | M30: =IF(L1=TRUE(),IF(M18="1 - Sim",Homogeneização!R55,Homogeneização!L55),IF(M18="1 - Sim",'Propriedades geométricas LAJE'!M7,L30)) -> 51.362431 | N30: Centro de gravidade até a borda inferiror. | V30: ='Propriedades geométricas VIGA'!B21 -> 0 | W30: ='Propriedades geométricas VIGA'!C21 -> 0
K31: y'.2 | L31: =IF(L1=TRUE(),Homogeneização!L54,'Propriedades geométricas VIGA'!M8) -> 30 | M31: =IF(L1=TRUE(),IF(M18="1 - Sim",Homogeneização!R54,Homogeneização!L54),IF(M18="1 - Sim",'Propriedades geométricas LAJE'!M8,L31)) -> 38.637569 | N31: Centro de gravidade até a borda superior. | V31: ='Propriedades geométricas VIGA'!B22 -> 0 | W31: ='Propriedades geométricas VIGA'!C22 -> 0
K32: d | L32: =L27-5 -> 55 | N32: Altura útil ESTIMADA. | V32: ='Propriedades geométricas VIGA'!B23 -> 0 | W32: ='Propriedades geométricas VIGA'!C23 -> 0
E33: Tabela 17.2 – Valores máximos de diâmetro e espaçamento, com barras de alta aderência | K33: d' | L33: =L27-L32 -> 5 | N33: Distância do C.G. de Ast até a fibra mais tracionada. | V33: ='Propriedades geométricas VIGA'!B24 -> 0 | W33: ='Propriedades geométricas VIGA'!C24 -> 0
E34: Tensão na barra σsi ou Δσpi MPa | F34: S/ armaduras ativas | H34: C/ armaduras ativas | K34: Consolo | L34: Chanfro | N34: Tipo do consolo. | V34: ='Propriedades geométricas VIGA'!B25 -> 0 | W34: ='Propriedades geométricas VIGA'!C25 -> 0
F35: ϕmáx (mm) | G35: s máx (cm) | H35: ϕmáx (mm) | I35: s máx (cm) | K35: Geometria da aba
E36: 160 | F36: 32 | G36: 30 | H36: 25 | I36: 20 | K36: Laba "T" | L36: 15 | M36: =IF(AND($M$19="1 - Retângular",$M$20="2 - T"),L36,0) -> 0 | N36: Comprimento da aba da seção "T". M36 = aba efetiva usada nos cálculos/desenho (só vale se M20 = "2 - T"; em "1 - R" e "3 - R/A" vale 0).
E37: 200 | F37: 25 | G37: 25 | H37: 16 | I37: 15 | K37: h-aba | L37: 15 | N37: altura menor da aba da viga seção "T".
E38: 240 | F38: 20 | G38: 20 | H38: 12.5 | I38: 10 | K38: h+aba | L38: 20 | N38: altura maior da aba da viga seção "T".
E39: 280 | F39: 16 | G39: 15 | H39: 8 | I39: 5 | K39: Laba R/A | L39: 10 | M39: =((L39*(L42+M46))/100^2)*L25/100 -> 0.26895 | N39: Largura da aba para casos de vigas retangulares com aba. | V39: ='Propriedades geométricas LAJE'!B7 -> 0 | W39: ='Propriedades geométricas LAJE'!C7 -> 0
E40: 320 | F40: 12.5 | G40: 10 | H40: 6 | I40: - | K40: Geometria da mesa colaborante | V40: ='Propriedades geométricas LAJE'!B8 -> -15 | W40: ='Propriedades geométricas LAJE'!C8 -> 0
E41: 360 | F41: 10 | G41: 5 | H41: - | I41: - | K41: Llaje | L41: =455.5+652 -> 1107.5 | N41: Comprimento da laje. | V41: ='Propriedades geométricas LAJE'!B9 -> -15 | W41: ='Propriedades geométricas LAJE'!C9 -> 40
E42: 400 | F42: 8 | G42: - | H42: - | I42: - | K42: Hlaje | L42: =VLOOKUP(L11,AUXÍLIO!I4:J6,2) -> 25 | M42: =IF(M18="1 - Sim",L42,0) -> 25 | N42: Altura da laje. | V42: ='Propriedades geométricas LAJE'!B10 -> -15 | W42: ='Propriedades geométricas LAJE'!C10 -> 45
K43: Lmc | L43: =AUXÍLIO!I20 -> 187 | M43: =IF(M18="1 - Sim",L43*L93,0) -> 144.84958 | N43: Comprimento da mesa colaborante. | V43: ='Propriedades geométricas LAJE'!B11 -> -15 | W43: ='Propriedades geométricas LAJE'!C11 -> 60
K44: bwapoio | L44: =L26 -> 30 | M44: =IF(M18="1 - Sim",L44*L93,0) -> 23.2379 | N44: Largura de apoio da mesa colaborante. | V44: ='Propriedades geométricas LAJE'!B12 -> -15 | W44: ='Propriedades geométricas LAJE'!C12 -> 60
K45: Hcapa | L45: 5 | M45: =IF(M18="1 - Sim",L45,0) -> 5 | N45: Altura da capa de concreto. | V45: ='Propriedades geométricas LAJE'!B13 -> -11.61895 | W45: ='Propriedades geométricas LAJE'!C13 -> 60
K46: Hycapa | L46: =ROUNDUP(((L45+M46)/2),0) -> 7 | M46: =L45+3 -> 8 | N46: Altura da capa para consideração de carga devido a contraflecha. | V46: ='Propriedades geométricas LAJE'!B14 -> -11.61895 | W46: ='Propriedades geométricas LAJE'!C14 -> 85
K47: Dados | V47: ='Propriedades geométricas LAJE'!B15 -> -72.424789 | W47: ='Propriedades geométricas LAJE'!C15 -> 85
K48: Ac | L48: =IF(L1=TRUE(),Homogeneização!L51,'Propriedades geométricas VIGA'!M6) -> 1800 | M48: =IF(L1=TRUE(),IF(M18="1 - Sim",Homogeneização!R51,Homogeneização!L51),IF(M18="1 - Sim",'Propriedades geométricas LAJE'!M6,L48)) -> 3105.1954 | N48: Área de concreto da seção transversal. | V48: ='Propriedades geométricas LAJE'!B16 -> -72.424789 | W48: ='Propriedades geométricas LAJE'!C16 -> 90
K49: Ic | L49: =IF(L1=TRUE(),Homogeneização!L57,'Propriedades geométricas VIGA'!M9) -> 540000 | M49: =IF(L1=TRUE(),IF(M18="1 - Sim",Homogeneização!R57,Homogeneização!L57),IF(M18="1 - Sim",'Propriedades geométricas LAJE'!M9,L49)) -> 2598580.9 | N49: Momento de inércia. | V49: ='Propriedades geométricas LAJE'!B17 -> 72.424789 | W49: ='Propriedades geométricas LAJE'!C17 -> 90
K50: hcgsup | L50: =L299/100 -> 0.1875 | N50: Altura do centro de gravidade até o centro da armadura superior. | V50: ='Propriedades geométricas LAJE'!B18 -> 72.424789 | W50: ='Propriedades geométricas LAJE'!C18 -> 85
K51: hcginf | L51: =L301/100 -> 0.3 | N51: Altura do centro de gravidade até o centro da armadura inferior. | V51: ='Propriedades geométricas LAJE'!B19 -> 11.61895 | W51: ='Propriedades geométricas LAJE'!C19 -> 85
K52: Wsup | L52: =IF(L1=TRUE(),Homogeneização!L62,'Propriedades geométricas VIGA'!M11) -> 18000 | M52: =IF(L1=TRUE(),IF(M18="1 - Sim",Homogeneização!R62,Homogeneização!L62),IF(M18="1 - Sim",'Propriedades geométricas LAJE'!M11,L52)) -> 67255.289 | N52: Módulo resistente da fibra superior. | V52: ='Propriedades geométricas LAJE'!B20 -> 11.61895 | W52: ='Propriedades geométricas LAJE'!C20 -> 60
K53: Winf | L53: =IF(L1=TRUE(),Homogeneização!L63,'Propriedades geométricas VIGA'!M10) -> 18000 | M53: =IF(L1=TRUE(),IF(M18="1 - Sim",Homogeneização!R63,Homogeneização!L63),IF(M18="1 - Sim",'Propriedades geométricas LAJE'!M10,L53)) -> 50593.027 | N53: Módulo resistente da fibra inferior. | V53: ='Propriedades geométricas LAJE'!B21 -> 15 | W53: ='Propriedades geométricas LAJE'!C21 -> 60
K54: K1 | L54: =L53/L48 -> 10 | N54: Distância nuclear inferior. | V54: ='Propriedades geométricas LAJE'!B22 -> 15 | W54: ='Propriedades geométricas LAJE'!C22 -> 60
K55: K2 | L55: =L52/L48 -> 10 | N55: Distância nuclear superior. | V55: ='Propriedades geométricas LAJE'!B23 -> 15 | W55: ='Propriedades geométricas LAJE'!C23 -> 45
K56: Rendimento | L56: =(L55+L54)/L27 -> 0.33333333 | N56: Rendimento da protensão. | V56: ='Propriedades geométricas LAJE'!B24 -> 15 | W56: ='Propriedades geométricas LAJE'!C24 -> 40
K57: σf | L57: =R75 -> 1.5 | N57: Coeficiente devido a geometria da seção transversal. | V57: ='Propriedades geométricas LAJE'!B25 -> 15 | W57: ='Propriedades geométricas LAJE'!C25 -> 0
K58: Epinf | L58: =(L27/2)-R253 -> 18.75 | N58: Excêntricidade de protensão inferior. | V58: ='Propriedades geométricas LAJE'!B26 -> 0 | W58: ='Propriedades geométricas LAJE'!C26 -> 0
K59: Geometria da viga i ou T
K60: bf | L60: 30 | M60: cm | N60: Largura do topo da viga.
K61: tw | L61: 12 | M61: cm | N61: Espessura da alma.
K62: bw | L62: 40 | M62: cm | N62: Largura da base da viga.
K63: hf1 | L63: 20 | M63: cm | N63: Altura da mesa superior 1.
K64: hf2 | L64: 5 | M64: cm | N64: Altura da mesa superior 2.
K65: hf3 | L65: 30 | M65: cm | N65: Altura da mesa central 3.
K66: hf4 | L66: 5 | M66: cm | N66: Altura da mesa inferior 4.
K67: hf5 | L67: 15 | M67: cm | N67: Altura da mesa inferior 5.
K68: Lvão | L68: =L29 -> 785 | M68: cm | N68: Tamanho da viga.
K69: bw | L69: =L62 -> 40 | M69: cm | N69: Largura da base da viga.
K70: h | L70: =SUM(L63:L67) -> 75 | M70: cm | N70: Altura da viga.
K72: 3. Coeficientes de cargas
K74: Tabela 11.2 | N74: Coeficientes majoradores | Q74: Dados do projeto
K75: Ψ0 | L75: 0.7 | N75: yf,PP | O75: 1.3 | Q75: σ | R75: =IF(M19="1 - Retângular",1.5,IF(M19="2 - i",1.3,IF(M19="3 - Transição",1.3))) -> 1.5
K76: Ψ1 | L76: 0.6 | N76: y,aço | O76: 1.1 | Q76: c | R76: =Apoio!A21/10 -> 3
K77: Ψ2 | L77: 0.4 | N77: yf,2 | O77: 1.4 | Q77: γp = | R77: 0.9
K78: γp: protensão no ELU | γc: minoração do concreto (viga / capa) | N78: γc,pré | O78: 1.4 | Q78: γc,capa = | R78: 1.4
K79: 2 . Resistência dos materiais
K80: CAA = | L80: II | M80: - | N80: Classe de agressividade ambiental – cobrimento pela tabela de fábrica (aba Apoio).
K81: fyk = | L81: 500 | M81: MPa | N81: Resistência caracterítica ao escoamento das barras de aço.
K82: fck = | L82: 50 | M82: MPa | N82: Resistência característica à compressão do concreto.
K83: fck = | L83: 30 | M83: MPa | N83: Resistência característica à compressão do concreto da laje.
K84: Fckj = | L84: 35 | M84: MPa | N84: Resistência do concreto na liberação da protensão (ato) – dado da fábrica/ensaio.
K85: Lpista = | L85: 100 | M85: m | N85: Tamanho da pista de protensão.
K86: Cimento = | L86: CPV-ARI | N86: Cimento utilizado na concretagem da viga.
K87: Cimento da capa = | L87: CPI E CPII | N87: Cimento utilizado na concretagem da capa da laje.
K88: Cp = | L88: 190 | M88: kgf/mm² | N88: Tipo de cordoalha
K89: fpyk = | L89: 1710 | M89: MPa | N89: tensão onde a cordoalha começa a ceder
K90: Controle rigoroso = | L90: Não | M90: - | N90: Controle de qualidade rigoroso (NBR 6118, 7.4.7.4): reduz o cobrimento em 5 mm.
K91: 3 . Redução da largura da mesa colaborante
K93: r = Ecapa / Eviga | L93: =L1188/L1172 -> 0.77459667 | M93: Por conta da diferença de concreto entre a viga e a solidarização, deve ser feito uma redução da largura da mesa colaborante
K95: Cargas adicionais
K96: Distribuidas
J97: Trecho | K97: xiniail | L97: xfinal | M97: g0 | N97: g1 | O97: g2 | P97: g3 | Q97: g4 | R97: q0 | S97: G Total | T97: Q Total
J98: 1 | K98: 0 | L98: 0 | M98: 0 | N98: 0 | O98: 0 | P98: 0 | Q98: 0 | R98: 0 | S98: =SUM(M98:Q98) -> 0 | T98: =R98 -> 0
J99: 2 | K99: 0 | L99: 0 | M99: 0 | N99: 0 | O99: 0 | P99: 0 | Q99: 0 | R99: 0 | S99: =SUM(M99:Q99) -> 0 | T99: =R99 -> 0
J100: 3 | K100: =L99 -> 0 | L100: 0 | M100: 0 | N100: 0 | O100: 0 | P100: 0 | Q100: 0 | R100: 0 | S100: =SUM(M100:Q100) -> 0 | T100: =R100 -> 0
J101: 4 | K101: =L100 -> 0 | L101: 0 | M101: 0 | N101: 0 | O101: 0 | P101: 0 | Q101: 0 | R101: 0 | S101: =SUM(M101:Q101) -> 0 | T101: =R101 -> 0
J102: 5 | K102: =L101 -> 0 | L102: 0 | M102: 0 | N102: 0 | O102: 0 | P102: 0 | Q102: 0 | R102: 0 | S102: =SUM(M102:Q102) -> 0 | T102: =R102 -> 0
J103: 6 | K103: =L102 -> 0 | L103: 0 | M103: 0 | N103: 0 | O103: 0 | P103: 0 | Q103: 0 | R103: 0 | S103: =SUM(M103:Q103) -> 0 | T103: =R103 -> 0
J104: 7 | K104: =L103 -> 0 | L104: 0 | M104: 0 | N104: 0 | O104: 0 | P104: 0 | Q104: 0 | R104: 0 | S104: =SUM(M104:Q104) -> 0 | T104: =R104 -> 0
J105: 8 | K105: =L104 -> 0 | L105: 0 | M105: 0 | N105: 0 | O105: 0 | P105: 0 | Q105: 0 | R105: 0 | S105: =SUM(M105:Q105) -> 0 | T105: =R105 -> 0
...

Sheet ELU i
T2: Seção 1
T3: x | U3: y | AD3: Section Properties About Centroidal Axis Parallel to Original Axis | AK3: PROPRIEDADES EM TORNO DO EIXO X | AP3: About Original Axis | AU3: DX = | AV3: =MAX(XX)-MIN(XX) -> 30
AD4: f = | AE4: =IF(AE10=0,0,IF(AE8-AE9=0,45,DEGREES(1/2*ATAN(-2*AE10/(AE8-AE9))))) -> 0 | AF4: deg | AG4: X-dim = | AH4: =MAX(XX)-MIN(XX) -> 30 | AI4: =$B$2 -> 0 | AJ4: Ix = | AK4: h | AL4: =AH5 -> 20 | AM4: =AA1 -> 0 | AP4: {=SUM((OFFSET(XX,1,0)-XX)*(YY+OFFSET(YY,1,0))/24*((OFFSET(YY,1,0)+YY)^2+(OFFSET(YY,1,0)-YY)^2))} -> 2555000 | AQ4: =$B$2&"^4" -> ^4 | AR4: Imax = | AS4: =+(AE8+AE9)/2-SQRT((AE8-AE9)^2/4+AE10^2) -> 20000 | AT4: =$B$2&"^4" -> ^4 | AU4: DY= | AV4: =MAX(YY)-MIN(YY) -> 20
AD5: A = | AE5: {=SUM((YY-OFFSET(YY,1,0))*(XX+OFFSET(XX,1,0)))/2} -> 600 | AF5: =$B$2 & "^2" -> ^2 | AG5: Y-dim = | AH5: =MAX(YY)-MIN(YY) -> 20 | AI5: =$B$2 -> 0 | AJ5: Iy = | AK5: A | AL5: =ABS(AE5) -> 600 | AM5: =CONCATENATE(AA1,"²") -> ² | AP5: {=-SUM((OFFSET(YY,1,0)-YY)*(XX+OFFSET(XX,1,0))/24*((OFFSET(XX,1,0)+XX)^2+(OFFSET(XX,1,0)-XX)^2))} -> 45000 | AQ5: =AA1&"^4" -> ^4 | AR5: Imin = | AS5: =+(AE8+AE9)/2+SQRT((AE8-AE9)^2/4+AE10^2) -> 45000 | AT5: =$B$2&"^4" -> ^4 | AU5: Plot of diagonal
AD6: Xcg = | AE6: {=SUM((YY-OFFSET(YY,1,0))/8*((XX+OFFSET(XX,1,0))^2+(OFFSET(XX,1,0)-XX)^2/3))/$AE$5} -> 0 | AF6: =AA1 -> 0 | AG6: Sx(top) = | AH6: =AE8/ABS(MAX(YY)-AE7) -> 2000 | AI6: =$B$2&"^3" -> ^3 | AJ6: Ixy = | AK6: Yi | AL6: =AE7 -> 65 | AM6: =AA1 -> 0 | AP6: {=SUM(((OFFSET(YY,1,0)-YY)^2*(OFFSET(XX,1,0)+XX)*(OFFSET(XX,1,0)^2+XX^2)/8+(OFFSET(YY,1,0)-YY)*(OFFSET(XX,1,0)*YY-XX*OFFSET(YY,1,0))*(OFFSET(XX,1,0)^2+OFFSET(XX,1,0)*XX+XX^2)/3+(OFFSET(XX,1,0)*YY-XX*OFFSET(YY,1,0))^2*(OFFSET(XX,1,0)+XX)/4)*IF(OFFSET(XX,1,0)=XX,0,1/(OFFSET(XX,1,0)-XX)))} -> 0 | AQ6: =AA1&"^4" -> ^4 | AR6: Principal Axis Plot | AU6: to control XY scale
AD7: Ycg = | AE7: {=SUM((OFFSET(XX,1,0)-XX)/8*((YY+OFFSET(YY,1,0))^2+(OFFSET(YY,1,0)-YY)^2/3))/$AE$5} -> 65 | AF7: =AA1 -> 0 | AG7: Sx(bot) = | AH7: =AE8/ABS(MIN(YY)-AE7) -> 2000 | AI7: =$B$2&"^3" -> ^3 | AK7: Ys | AL7: =AH5-AL6 -> -45 | AM7: =AA1 -> 0 | AR7: x | AS7: y | AU7: x | AV7: y
T8: 0 | U8: =U9 -> 55 | AD8: Ixo = | AE8: =AP4-AE5*AE7^2 -> 20000 | AF8: =$B$2&"^4" -> ^4 | AG8: Sy(left) = | AH8: =AE9/ABS(MIN(XX)-AE6) -> 3000 | AI8: =$B$2&"^3" -> ^3 | AK8: Ix | AL8: =ABS(AE8) -> 20000 | AM8: =CONCATENATE(AA1,"4") -> 4 | AR8: =MIN(XX) -> -15 | AS8: =(AR8-$F$7)*TAN(RADIANS($F$5))+$F$8 -> 0 | AU8: =IF(AV3>=AV4,MIN(XX),(MAX(XX)+MIN(XX)-AV4)/2) -> -15 | AV8: =IF(AV3>=AV4,(MAX(YY)+MIN(YY)-AV3)/2,MIN(YY)) -> 50
T9: =Seções!K30 -> -15 | U9: =Seções!L30 -> 55 | AD9: Iyo = | AE9: =AP5-AE5*AE6^2 -> 45000 | AF9: =$B$2&"^4" -> ^4 | AG9: Sy(right)= | AH9: =AE9/ABS(MAX(XX)-AE6) -> 3000 | AI9: =$B$2&"^3" -> ^3 | AK9: Wi | AL9: =ABS(AH7) -> 2000 | AM9: =CONCATENATE(AA1,"³") -> ³ | AR9: =MAX(XX) -> 15 | AS9: =(AR9-$F$7)*TAN(RADIANS($F$5))+$F$8 -> 0 | AU9: =IF(AV3>=AV4,MAX(XX),(MAX(XX)+MIN(XX)+AV4)/2) -> 15 | AV9: =IF(AV3>=AV4,(MAX(YY)+MIN(YY)+AV3)/2,MAX(YY)) -> 80
T10: =Seções!K31 -> -15 | U10: =Seções!L31 -> 75 | AD10: Ixyo = | AE10: =+AP6-AE5*AE6*AE7 -> 0 | AF10: =$B$2&"^4" -> ^4 | AK10: Ws | AL10: =ABS(AH6) -> 2000 | AM10: =CONCATENATE(AA1,"³") -> ³
T11: =Seções!K32 -> 0 | U11: =Seções!L32 -> 75 | AR11: =(AS11-$F$8)*TAN(RADIANS(-$F$5))+$F$7 -> 0 | AS11: =MIN(Y) -> 0
T12: =Seções!K33 -> 15 | U12: =Seções!L33 -> 75 | AD12: Section Properties About Principal Axis | AR12: =(AS12-$F$8)*TAN(RADIANS(-$F$5))+$F$7 -> 0 | AS12: =MAX(Y) -> 60
T13: =Seções!K34 -> 15 | U13: =Seções!L34 -> 55 | AD13: f = | AE13: =AE4 -> 0 | AF13: deg | AG13: Sxp(top) = | AH13: {=ABS(AE14/MAX(SQRT((XX-AE6)^2+(YY-AE7)^2)*SIN(ATAN2(XX-AE6,YY-AE7)-RADIANS(AE4))))} -> 2000 | AI13: =$B$2&"^3" -> ^3
T14: 0 | U14: =U13 -> 55 | AD14: Ixp = | AE14: =AE8*COS(RADIANS(AE13))^2+AE9*SIN(RADIANS(AE13))^2-AE10*SIN(2*RADIANS(AE13)) -> 20000 | AF14: =$B$2&"^4" -> ^4 | AG14: Sxp(bot) = | AH14: {=ABS(AE14/MIN(SQRT((XX-AE6)^2+(YY-AE7)^2)*SIN(ATAN2(XX-AE6,YY-AE7)-RADIANS(AE4))))} -> 307.69231 | AI14: =$B$2&"^3" -> ^3
AD15: Iyp = | AE15: =AE9*COS(RADIANS(AE13))^2+AE8*SIN(RADIANS(AE13))^2+AE10*SIN(2*RADIANS(AE13)) -> 45000 | AF15: =$B$2&"^4" -> ^4 | AG15: Syp(left) = | AH15: {=ABS($F$16/MIN(SQRT((XX-AE6)^2+(YY-AE7)^2)*COS(ATAN2(XX-AE6,YY-AE7)-RADIANS(AE4))))} -> 0 | AI15: =$B$2&"^3" -> ^3
AD16: Ixyp = | AE16: =+(AE8-AE9)/2*SIN(RADIANS(AE13)*2)+AE10*COS(2*RADIANS(AE13)) -> 0 | AF16: =$B$2&"^4" -> ^4 | AG16: Syp(right)= | AH16: {=ABS(AE15/MAX(SQRT((XX-AE6)^2+(YY-AE7)^2)*COS(ATAN2(XX-AE6,YY-AE7)-RADIANS(AE4))))} -> 3000 | AI16: =$B$2&"^3" -> ^3
AD17: J = | AE17: =+AE14+AE15 -> 65000 | AF17: =$B$2&"^4" -> ^4 | AK17: =IF($C$3="Retângular",Seções!AA7,Seções!AJ24) -> 0
F24: Geometria da viga i ou T
F25: bf | G25: =Geometria!L60 -> 30 | H25: cm | I25: Largura do topo da viga. | T25: Seção 2
F26: tw | G26: =Geometria!L61 -> 12 | H26: cm | I26: Espessura da alma. | T26: x | U26: y | AD26: Section Properties About Centroidal Axis Parallel to Original Axis | AK26: PROPRIEDADES EM TORNO DO EIXO X | AP26: About Original Axis | AU26: DX = | AV26: =MAX(XXX)-MIN(XXX) -> 30
F27: bw | G27: =Geometria!L62 -> 40 | H27: cm | I27: Largura da base da viga. | AD27: f = | AE27: =IF(AE33=0,0,IF(AE31-AE32=0,45,DEGREES(1/2*ATAN(-2*AE33/(AE31-AE32))))) -> 0 | AF27: deg | AG27: X-dim = | AH27: =MAX(XXX)-MIN(XXX) -> 30 | AI27: =$B$2 -> 0 | AJ27: Ix = | AK27: h | AL27: =AH28 -> 5 | AM27: =AA24 -> 0 | AP27: {=SUM((OFFSET(XXX,1,0)-XXX)*(YYY+OFFSET(YYY,1,0))/24*((OFFSET(YYY,1,0)+YYY)^2+(OFFSET(YYY,1,0)-YYY)^2))} -> 293562.5 | AQ27: =$B$2&"^4" -> ^4 | AR27: Imax = | AS27: =+(AE31+AE32)/2-SQRT((AE31-AE32)^2/4+AE33^2) -> 205.35714 | AT27: =$B$2&"^4" -> ^4 | AU27: DY= | AV27: =MAX(YYY)-MIN(YYY) -> 5
F28: hf1 | G28: =Geometria!L63 -> 20 | H28: cm | I28: Altura da mesa superior 1. | AD28: A = | AE28: {=SUM((YYY-OFFSET(YYY,1,0))*(XXX+OFFSET(XXX,1,0)))/2} -> 105 | AF28: =$B$2 & "^2" -> ^2 | AG28: Y-dim = | AH28: =MAX(YYY)-MIN(YYY) -> 5 | AI28: =$B$2 -> 0 | AJ28: Iy = | AK28: A | AL28: =ABS(AE28) -> 105 | AM28: =CONCATENATE(AA24,"²") -> ² | AP28: {=-SUM((OFFSET(YYY,1,0)-YYY)*(XXX+OFFSET(XXX,1,0))/24*((OFFSET(XXX,1,0)+XXX)^2+(OFFSET(XXX,1,0)-XXX)^2))} -> 4567.5 | AQ28: =AA24&"^4" -> ^4 | AR28: Imin = | AS28: =+(AE31+AE32)/2+SQRT((AE31-AE32)^2/4+AE33^2) -> 4567.5 | AT28: =$B$2&"^4" -> ^4 | AU28: Plot of diagonal
F29: hf2 | G29: =Geometria!L64 -> 5 | H29: cm | I29: Altura da mesa superior 2. | AD29: Xcg = | AE29: {=SUM((YYY-OFFSET(YYY,1,0))/8*((XXX+OFFSET(XXX,1,0))^2+(OFFSET(XXX,1,0)-XXX)^2/3))/AE28} -> 0 | AF29: =AA24 -> 0 | AG29: Sx(top) = | AH29: =AE31/ABS(MAX(YYY)-AE30) -> 95.833333 | AI29: =$B$2&"^3" -> ^3 | AJ29: Ixy = | AK29: Yi | AL29: =AE30 -> 52.857143 | AM29: =AA24 -> 0 | AP29: {=SUM(((OFFSET(YYY,1,0)-YYY)^2*(OFFSET(XXX,1,0)+XXX)*(OFFSET(XXX,1,0)^2+XXX^2)/8+(OFFSET(YYY,1,0)-YYY)*(OFFSET(XXX,1,0)*YYY-XXX*OFFSET(YYY,1,0))*(OFFSET(XXX,1,0)^2+OFFSET(XXX,1,0)*XXX+XXX^2)/3+(OFFSET(XXX,1,0)*YYY-XXX*OFFSET(YYY,1,0))^2*(OFFSET(XXX,1,0)+XXX)/4)*IF(OFFSET(XXX,1,0)=XXX,0,1/(OFFSET(XXX,1,0)-XXX)))} -> 0 | AQ29: =AA24&"^4" -> ^4 | AR29: Principal Axis Plot | AU29: to control XY scale
F30: hf3 | G30: =Geometria!L65 -> 30 | H30: cm | I30: Altura da mesa central 3. | T30: 0 | U30: =U31 -> 50 | AD30: Ycg = | AE30: {=SUM((OFFSET(XXX,1,0)-XXX)/8*((YYY+OFFSET(YYY,1,0))^2+(OFFSET(YYY,1,0)-YYY)^2/3))/AE28} -> 52.857143 | AF30: =AA24 -> 0 | AG30: Sx(bot) = | AH30: =AE31/ABS(MIN(YYY)-AE30) -> 71.875 | AI30: =$B$2&"^3" -> ^3 | AK30: Ys | AL30: =AH28-AL29 -> -47.857143 | AM30: =AA24 -> 0 | AR30: x | AS30: y | AU30: x | AV30: y
F31: hf4 | G31: =Geometria!L66 -> 5 | H31: cm | I31: Altura da mesa inferior 4. | T31: =Seções!K29 -> -6 | U31: =Seções!L29 -> 50 | AD31: Ixo = | AE31: =AP27-AE28*AE30^2 -> 205.35714 | AF31: =$B$2&"^4" -> ^4 | AG31: Sy(left) = | AH31: =AE32/ABS(MIN(XXX)-AE29) -> 304.5 | AI31: =$B$2&"^3" -> ^3 | AK31: Ix | AL31: =ABS(AE31) -> 205.35714 | AM31: =CONCATENATE(AA24,"4") -> 4 | AR31: =MIN(XXX) -> -15 | AS31: =(AR31-$F$7)*TAN(RADIANS($F$5))+$F$8 -> 0 | AU31: =IF(AV26>=AV27,MIN(XXX),(MAX(XXX)+MIN(XXX)-AV27)/2) -> -15 | AV31: =IF(AV26>=AV27,(MAX(YYY)+MIN(YYY)-AV26)/2,MIN(YYY)) -> 37.5
F32: hf5 | G32: =Geometria!L67 -> 15 | H32: cm | I32: Altura da mesa inferior 5. | T32: =Seções!K30 -> -15 | U32: =Seções!L30 -> 55 | AD32: Iyo = | AE32: =AP28-AE28*AE29^2 -> 4567.5 | AF32: =$B$2&"^4" -> ^4 | AG32: Sy(right)= | AH32: =AE32/ABS(MAX(XXX)-AE29) -> 304.5 | AI32: =$B$2&"^3" -> ^3 | AK32: Wi | AL32: =ABS(AH30) -> 71.875 | AM32: =CONCATENATE(AA24,"³") -> ³ | AR32: =MAX(XXX) -> 15 | AS32: =(AR32-$F$7)*TAN(RADIANS($F$5))+$F$8 -> 0 | AU32: =IF(AV26>=AV27,MAX(XXX),(MAX(XXX)+MIN(XXX)+AV27)/2) -> 15 | AV32: =IF(AV26>=AV27,(MAX(YYY)+MIN(YYY)+AV26)/2,MAX(YYY)) -> 67.5
F33: Lvão | G33: =Geometria!L68 -> 785 | H33: cm | I33: Tamanho da viga. | T33: =Seções!K31 -> -15 | U33: =U32 -> 55 | AD33: Ixyo = | AE33: =+AP29-AE28*AE29*AE30 -> 0 | AF33: =$B$2&"^4" -> ^4 | AK33: Ws | AL33: =ABS(AH29) -> 95.833333 | AM33: =CONCATENATE(AA24,"³") -> ³
F34: bw | G34: =Geometria!L69 -> 40 | H34: cm | I34: Largura da base da viga. | T34: =Seções!K32 -> 0 | U34: =U33 -> 55 | AR34: =(AS34-$F$8)*TAN(RADIANS(-$F$5))+$F$7 -> 0 | AS34: =MIN(Y) -> 0
F35: h | G35: =Geometria!L70 -> 75 | H35: cm | I35: Altura da viga. | T35: =Seções!K33 -> 15 | U35: =U36 -> 55 | AD35: Section Properties About Principal Axis | AR35: =(AS35-$F$8)*TAN(RADIANS(-$F$5))+$F$7 -> 0 | AS35: =MAX(Y) -> 60
T36: =Seções!K34 -> 15 | U36: =Seções!L34 -> 55 | AD36: f = | AE36: =AE27 -> 0 | AF36: deg | AG36: Sxp(top) = | AH36: {=ABS(AE37/MAX(SQRT((XXX-AE29)^2+(YYY-AE30)^2)*SIN(ATAN2(XXX-$F$7,YYY-AE30)-RADIANS(AE27))))} -> 95.833333 | AI36: =$B$2&"^3" -> ^3
F37: Em casos de seção "i" | T37: =Seções!K35 -> 6 | U37: =Seções!L35 -> 50 | AD37: Ixp = | AE37: =AE31*COS(RADIANS(AE36))^2+AE32*SIN(RADIANS(AE36))^2-AE33*SIN(2*RADIANS(AE36)) -> 205.35714 | AF37: =$B$2&"^4" -> ^4 | AG37: Sxp(bot) = | AH37: {=ABS(AE37/MIN(SQRT((XXX-AE29)^2+(YYY-AE30)^2)*SIN(ATAN2(XXX-AE29,YYY-AE30)-RADIANS(AE27))))} -> 3.8851351 | AI37: =$B$2&"^3" -> ^3
F38: Md | G38: =Geometria!L1038*100 -> 202227.8 | H38: kN*cm | T38: 0 | U38: =U37 -> 50 | AD38: Iyp = | AE38: =AE32*COS(RADIANS(AE36))^2+AE31*SIN(RADIANS(AE36))^2+AE33*SIN(2*RADIANS(AE36)) -> 4567.5 | AF38: =$B$2&"^4" -> ^4 | AG38: Syp(left) = | AH38: {=ABS(AE38/MIN(SQRT((XXX-AE29)^2+(YYY-AE30)^2)*COS(ATAN2(XXX-AE29,YYY-AE30)-RADIANS(AE27))))} -> 304.5 | AI38: =$B$2&"^3" -> ^3
F39: Kmd,"i" | G39: =Geometria!R1038 -> 0.46442678 | H39: =G38/100 -> 2022.278 | AD39: Ixyp = | AE39: =+(AE31-AE32)/2*SIN(RADIANS(AE36)*2)+AE33*COS(2*RADIANS(AE36)) -> 0 | AF39: =$B$2&"^4" -> ^4 | AG39: Syp(right)= | AH39: {=ABS(AE38/MAX(SQRT((XXX-AE29)^2+(YYY-AE30)^2)*COS(ATAN2(XXX-AE29,YYY-AE30)-RADIANS(AE27))))} -> 304.5 | AI39: =$B$2&"^3" -> ^3
F40: kx | G40: =Geometria!R1039 -> 0.628 | AD40: J = | AE40: =+AE37+AE38 -> 4772.8571 | AF40: =$B$2&"^4" -> ^4 | AK40: =IF($C$3="Retângular",Seções!AA30,Seções!AJ47) -> 0
F41: kz | G41: =Geometria!R1040 -> 0.748
F42: ε,s | G42: =Geometria!R1041 -> 2.06
F43: x | G43: =Geometria!R1042 -> 0.27859271
F44: fpd | G44: =Geometria!R1043 -> 132
F46: fyk = | G46: =Geometria!L81 -> 500 | H46: MPa | I46: Resistência caracterítica ao escoamento das barras de aço.
F47: fck = | G47: =Geometria!L82 -> 50 | H47: MPa | I47: Resistência característica à compressão do concreto.
F48: fck = | G48: =Geometria!L83 -> 30 | H48: MPa | I48: Resistência característica à compressão do concreto da laje.
F49: Fckj = | G49: =Geometria!L84 -> 35 | H49: MPa | I49: Resistência característica à compressão do concreto t=1.
F50: Lpista = | G50: 100 | H50: m | I50: Tamanho da pista de protensão. | T50: Seção 3
F51: Cimento = | G51: CPV-ARI | I51: Cimento utilizado na concretagem da viga. | T51: x | U51: y | AD51: Section Properties About Centroidal Axis Parallel to Original Axis | AK51: PROPRIEDADES EM TORNO DO EIXO X | AP51: About Original Axis | AU51: DX = | AV51: =MAX(XXXX)-MIN(XXXX) -> 12
F52: Cimento da capa = | G52: CPI E CPII | I52: Cimento utilizado na concretagem da capa da laje. | AD52: f = | AE52: =IF(AE58=0,0,IF(AE56-AE57=0,45,DEGREES(1/2*ATAN(-2*AE58/(AE56-AE57))))) -> 0 | AF52: deg | AG52: X-dim = | AH52: =MAX(XXXX)-MIN(XXXX) -> 12 | AI52: =$B$2 -> 0 | AJ52: Ix = | AK52: h | AL52: =AH53 -> 30 | AM52: =AA49 -> 0 | AP52: {=SUM((OFFSET(XXXX,1,0)-XXXX)*(YYYY+OFFSET(YYYY,1,0))/24*((OFFSET(YYYY,1,0)+YYYY)^2+(OFFSET(YYYY,1,0)-YYYY)^2))} -> 468000 | AQ52: =$B$2&"^4" -> ^4 | AR52: Imax = | AS52: =+(AE56+AE57)/2-SQRT((AE56-AE57)^2/4+AE58^2) -> 4320 | AT52: =$B$2&"^4" -> ^4 | AU52: DY= | AV52: =MAX(YYYY)-MIN(YYYY) -> 30
AD53: A = | AE53: {=SUM((YYYY-OFFSET(YYYY,1,0))*(XXXX+OFFSET(XXXX,1,0)))/2} -> 360 | AF53: =$B$2 & "^2" -> ^2 | AG53: Y-dim = | AH53: =MAX(YYYY)-MIN(YYYY) -> 30 | AI53: =$B$2 -> 0 | AJ53: Iy = | AK53: A | AL53: =ABS(AE53) -> 360 | AM53: =CONCATENATE(AA49,"²") -> ² | AP53: {=-SUM((OFFSET(YYYY,1,0)-YYYY)*(XXXX+OFFSET(XXXX,1,0))/24*((OFFSET(XXXX,1,0)+XXXX)^2+(OFFSET(XXXX,1,0)-XXXX)^2))} -> 4320 | AQ53: =AA49&"^4" -> ^4 | AR53: Imin = | AS53: =+(AE56+AE57)/2+SQRT((AE56-AE57)^2/4+AE58^2) -> 27000 | AT53: =$B$2&"^4" -> ^4 | AU53: Plot of diagonal
F54: d = | G54: =Geometria!L70-Geometria!R76 -> 72 | I54: Altura da linha neutra. | T54: 0 | U54: =U55 -> 20 | AD54: Xcg = | AE54: {=SUM((YYYY-OFFSET(YYYY,1,0))/8*((XXXX+OFFSET(XXXX,1,0))^2+(OFFSET(XXXX,1,0)-XXXX)^2/3))/AE53} -> 0 | AF54: =AA49 -> 0 | AG54: Sx(top) = | AH54: =AE56/ABS(MAX(YYYY)-AE55) -> 1800 | AI54: =$B$2&"^3" -> ^3 | AJ54: Ixy = | AK54: Yi | AL54: =AE55 -> 35 | AM54: =AA49 -> 0 | AP54: {=SUM(((OFFSET(YYYY,1,0)-YYYY)^2*(OFFSET(XXXX,1,0)+XXXX)*(OFFSET(XXXX,1,0)^2+XXXX^2)/8+(OFFSET(YYYY,1,0)-YYYY)*(OFFSET(XXXX,1,0)*YYYY-XXXX*OFFSET(YYYY,1,0))*(OFFSET(XXXX,1,0)^2+OFFSET(XXXX,1,0)*XXXX+XXXX^2)/3+(OFFSET(XXXX,1,0)*YYYY-XXXX*OFFSET(YYYY,1,0))^2*(OFFSET(XXXX,1,0)+XXXX)/4)*IF(OFFSET(XXXX,1,0)=XXXX,0,1/(OFFSET(XXXX,1,0)-XXXX)))} -> 0 | AQ54: =AA49&"^4" -> ^4 | AR54: Principal Axis Plot | AU54: to control XY scale
T55: =Seções!K28 -> -6 | U55: =Seções!L28 -> 20 | AD55: Ycg = | AE55: {=SUM((OFFSET(XXXX,1,0)-XXXX)/8*((YYYY+OFFSET(YYYY,1,0))^2+(OFFSET(YYYY,1,0)-YYYY)^2/3))/AE53} -> 35 | AF55: =AA49 -> 0 | AG55: Sx(bot) = | AH55: =AE56/ABS(MIN(YYYY)-AE55) -> 1800 | AI55: =$B$2&"^3" -> ^3 | AK55: Ys | AL55: =AH53-AL54 -> -5 | AM55: =AA49 -> 0 | AR55: x | AS55: y | AU55: x | AV55: y
F56: x23 = | G56: =0.259*G54 -> 18.648 | I56: Domínio 2. | T56: =Seções!K29 -> -6 | U56: =Seções!L29 -> 50 | AD56: Ixo = | AE56: =AP52-AE53*AE55^2 -> 27000 | AF56: =$B$2&"^4" -> ^4 | AG56: Sy(left) = | AH56: =AE57/ABS(MIN(XXXX)-AE54) -> 720 | AI56: =$B$2&"^3" -> ^3 | AK56: Ix | AL56: =ABS(AE56) -> 27000 | AM56: =CONCATENATE(AA49,"4") -> 4 | AR56: =MIN(XXXX) -> -6 | AS56: =(AR56-$F$7)*TAN(RADIANS($F$5))+$F$8 -> 0 | AU56: =IF(AV51>=AV52,MIN(XXXX),(MAX(XXXX)+MIN(XXXX)-AV52)/2) -> -15 | AV56: =IF(AV51>=AV52,(MAX(YYYY)+MIN(YYYY)-AV51)/2,MIN(YYYY)) -> 20
F57: x34 = | G57: =0.628*G54 -> 45.216 | I57: Domínio 3 | T57: =T56 -> -6 | U57: =U56 -> 50 | AD57: Iyo = | AE57: =AP53-AE53*AE54^2 -> 4320 | AF57: =$B$2&"^4" -> ^4 | AG57: Sy(right)= | AH57: =AE57/ABS(MAX(XXXX)-AE54) -> 720 | AI57: =$B$2&"^3" -> ^3 | AK57: Wi | AL57: =ABS(AH55) -> 1800 | AM57: =CONCATENATE(AA49,"³") -> ³ | AR57: =MAX(XXXX) -> 6 | AS57: =(AR57-$F$7)*TAN(RADIANS($F$5))+$F$8 -> 0 | AU57: =IF(AV51>=AV52,MAX(XXXX),(MAX(XXXX)+MIN(XXXX)+AV52)/2) -> 15 | AV57: =IF(AV51>=AV52,(MAX(YYYY)+MIN(YYYY)+AV51)/2,MAX(YYYY)) -> 50
T58: =T57 -> -6 | U58: =U57 -> 50 | AD58: Ixyo = | AE58: =+AP54-AE53*AE54*AE55 -> 0 | AF58: =$B$2&"^4" -> ^4 | AK58: Ws | AL58: =ABS(AH54) -> 1800 | AM58: =CONCATENATE(AA49,"³") -> ³
T59: =Seções!K32 -> 0 | U59: =U58 -> 50 | AR59: =(AS59-$F$8)*TAN(RADIANS(-$F$5))+$F$7 -> 0 | AS59: =MIN(Y) -> 0
T60: =T61 -> 6 | U60: =U59 -> 50 | AD60: Section Properties About Principal Axis | AR60: =(AS60-$F$8)*TAN(RADIANS(-$F$5))+$F$7 -> 0 | AS60: =MAX(Y) -> 60
F61: Linha neutra na seção 1 | T61: =T62 -> 6 | U61: =U62 -> 50 | AD61: f = | AE61: =AE52 -> 0 | AF61: deg | AG61: Sxp(top) = | AH61: {=ABS(AE62/MAX(SQRT((XXXX-AE54)^2+(YYYY-AE55)^2)*SIN(ATAN2(XXXX-AE54,YYYY-AE55)-RADIANS(AE52))))} -> 1800 | AI61: =$B$2&"^3" -> ^3
T62: =Seções!K35 -> 6 | U62: =Seções!L35 -> 50 | AD62: Ixp = | AE62: =AE56*COS(RADIANS(AE61))^2+AE57*SIN(RADIANS(AE61))^2-AE58*SIN(2*RADIANS(AE61)) -> 27000 | AF62: =$B$2&"^4" -> ^4 | AG62: Sxp(bot) = | AH62: {=ABS(AE62/MIN(SQRT((XXXX-AE54)^2+(YYYY-AE55)^2)*SIN(ATAN2(XXXX-AE54,YYYY-AE55)-RADIANS(AE52))))} -> 771.42857 | AI62: =$B$2&"^3" -> ^3
F63: Rcd1 | G63: =0.85*((G47/10)/Geometria!$O$78)*AL5 -> 1821.4286 | H63: kN | T63: =Seções!K36 -> 6 | U63: =Seções!L36 -> 20 | AD63: Iyp = | AE63: =AE57*COS(RADIANS(AE61))^2+AE56*SIN(RADIANS(AE61))^2+AE58*SIN(2*RADIANS(AE61)) -> 4320 | AF63: =$B$2&"^4" -> ^4 | AG63: Syp(left) = | AH63: {=ABS(AE63/MIN(SQRT((XXXX-AE54)^2+(YYYY-AE55)^2)*COS(ATAN2(XXXX-AE54,YYYY-AE55)-RADIANS(AE52))))} -> 720 | AI63: =$B$2&"^3" -> ^3
F64: Md1 | G64: =G63*(G54-(AH5/2)) -> 112928.57 | H64: kN*cm | T64: 0 | U64: =U63 -> 20 | AD64: Ixyp = | AE64: =+(AE56-AE57)/2*SIN(RADIANS(AE61)*2)+AE58*COS(2*RADIANS(AE61)) -> 0 | AF64: =$B$2&"^4" -> ^4 | AG64: Syp(right)= | AH64: {=ABS(AE63/MAX(SQRT((XXXX-AE54)^2+(YYYY-AE55)^2)*COS(ATAN2(XXXX-AE54,YYYY-AE55)-RADIANS(AE52))))} -> 720 | AI64: =$B$2&"^3" -> ^3
G65: =IF(G64>G38,"Ok, linha neutra passa na seção 1","Recalcular") -> Recalcular | AD65: J = | AE65: =+AE62+AE63 -> 31320 | AF65: =$B$2&"^4" -> ^4 | AK65: =IF($C$3="Retângular",Seções!AA55,Seções!AJ72) -> 0
F67: x | G67: =IF(Geometria!$M$19="2 - i",((Geometria!L1049*Geometria!L1050*(Geometria!L82/10)/Geometria!$O$78*Geometria!L60*(Geometria!L70-Geometria!R253))-SQRT((Geometria!L1049*Geometria!L1050*(Geometria!L82/10)/Geometria!$O$78*Geometria!L60*(Geometria!L70-Geometria!R253))^2-4*((Geometria!L1049*Geometria!L1050^2*(Geometria!L82/10)/Geometria!$O$78*Geometria!L60)/2)*Geometria!L1038*100))/(2*((Geometria!L1049*Geometria!L1050^2*(Geometria!L82/10)/Geometria!$O$78*Geometria!L60)/2)),0) -> 0 | I67: cm | J67: =IF(Geometria!$M$19="2 - i",IF(G67<G56,I56,IF(AND(G67>G56,G67<G57,I57),I57,IF(G67>G57,"Domínio 4"))),0) -> 0
F68: As | G68: =G63/((G46/10)/Geometria!O76) -> 40.071429 | H68: cm²
F70: Linha neutra na seção 2
F72: Rcd2 | G72: =0.85*((G47/10)/Geometria!$O$78)*AL28 -> 318.75 | H72: kN
F73: Md2 | G73: =G72*(G54-AL4-AL27/3) -> 16043.75 | H73: kN*cm
G74: =IF(G73+G64>G38,"Ok, linha neutra passa na seção 2","Recalcular") -> Recalcular
F77: Contas
F78: l,aba | G78: =T93-T95 -> 9 | H78: cm | I78: Comprimento da aba a partir da alma
F79: h,mis | G79: =U90-U89 -> 5 | H79: cm | I79: Altura da mísula
F80: =G78/G79 -> 1.8 | G80: h
F81: 0.8 | G81: x- | H81: =U91-U90 -> 20
F83: rcd1 | G83: =G63 -> 1821.4286 | H83: kN*cm
F84: md1 | G84: =G64 -> 112928.57 | H84: kN*cm | T84: x | U84: y | AD84: Section Properties About Centroidal Axis Parallel to Original Axis | AK84: PROPRIEDADES EM TORNO DO EIXO X | AP84: About Original Axis | AU84: DX = | AV84: =MAX(testex)-MIN(testex) -> 40
F85: md | G85: =G38-G84 -> 89299.229 | H85: kN*cm | I85: Resíduo de momento | T85: =Seções!K25 -> 0 | U85: =Seções!L25 -> 0 | AD85: f = | AE85: =IF(AE91=0,0,IF(AE89-AE90=0,45,DEGREES(1/2*ATAN(-2*AE91/(AE89-AE90))))) -> 0 | AF85: deg | AG85: X-dim = | AH85: =MAX(testex)-MIN(testex) -> 40 | AI85: =$B$2 -> 0 | AJ85: Ix = | AK85: h | AL85: =AH86 -> 75 | AM85: =AA82 -> 0 | AP85: {=SUM((OFFSET(testex,1,0)-testex)*(testey+OFFSET(testey,1,0))/24*((OFFSET(testey,1,0)+testey)^2+(OFFSET(testey,1,0)-testey)^2))} -> 3399604.2 | AQ85: =$B$2&"^4" -> ^4 | AR85: Imax = | AS85: =+(AE89+AE90)/2-SQRT((AE89-AE90)^2/4+AE91^2) -> 143334.17 | AT85: =$B$2&"^4" -> ^4 | AU85: DY= | AV85: =MAX(testey)-MIN(testey) -> 75
T86: =Seções!K26 -> -20 | U86: =Seções!L26 -> 0 | AD86: A = | AE86: {=SUM((testey-OFFSET(testey,1,0))*(testex+OFFSET(testex,1,0)))/2} -> 1795 | AF86: =$B$2 & "^2" -> ^2 | AG86: Y-dim = | AH86: =MAX(testey)-MIN(testey) -> 75 | AI86: =$B$2 -> 0 | AJ86: Iy = | AK86: A | AL86: =ABS(AE86) -> 1795 | AM86: =CONCATENATE(AA82,"²") -> ² | AP86: {=-SUM((OFFSET(testey,1,0)-testey)*(testex+OFFSET(testex,1,0))/24*((OFFSET(testex,1,0)+testex)^2+(OFFSET(testex,1,0)-testex)^2))} -> 143334.17 | AQ86: =AA82&"^4" -> ^4 | AR86: Imin = | AS86: =+(AE89+AE90)/2+SQRT((AE89-AE90)^2/4+AE91^2) -> 1127208 | AT86: =$B$2&"^4" -> ^4 | AU86: Plot of diagonal
F87: Rcd2 | G87: =0.85*(G47/10)/Geometria!$O$78*(ABS(T91)+T93) -> 91.071429 | H87: h | T87: =Seções!K27 -> -20 | U87: =Seções!L27 -> 15 | AD87: Xcg = | AE87: {=SUM((testey-OFFSET(testey,1,0))/8*((testex+OFFSET(testex,1,0))^2+(OFFSET(testex,1,0)-testex)^2/3))/AE86} -> 0 | AF87: =AA82 -> 0 | AG87: Sx(top) = | AH87: =AE89/ABS(MAX(testey)-AE88) -> 28595.054 | AI87: =$B$2&"^3" -> ^3 | AJ87: Ixy = | AK87: Yi | AL87: =AE88 -> 35.580316 | AM87: =AA82 -> 0 | AP87: {=SUM(((OFFSET(testey,1,0)-testey)^2*(OFFSET(testex,1,0)+testex)*(OFFSET(testex,1,0)^2+testex^2)/8+(OFFSET(testey,1,0)-testey)*(OFFSET(testex,1,0)*testey-testex*OFFSET(testey,1,0))*(OFFSET(testex,1,0)^2+OFFSET(testex,1,0)*testex+testex^2)/3+(OFFSET(testex,1,0)*testey-testex*OFFSET(testey,1,0))^2*(OFFSET(testex,1,0)+testex)/4)*IF(OFFSET(testex,1,0)=testex,0,1/(OFFSET(testex,1,0)-testex)))} -> 0 | AQ87: =AA82&"^4" -> ^4 | AR87: Principal Axis Plot | AU87: to control XY scale
F88: Rcd3 | G88: =0.85*(G47/10)/Geometria!$O$78*F80 -> 5.4642857 | H88: h^2 | T88: =Seções!K28 -> -6 | U88: =Seções!L28 -> 20 | AD88: Ycg = | AE88: {=SUM((OFFSET(testex,1,0)-testex)/8*((testey+OFFSET(testey,1,0))^2+(OFFSET(testey,1,0)-testey)^2/3))/AE86} -> 35.580316 | AF88: =AA82 -> 0 | AG88: Sx(bot) = | AH88: =AE89/ABS(MIN(testey)-AE88) -> 31680.663 | AI88: =$B$2&"^3" -> ^3 | AK88: Ys | AL88: =AH86-AL87 -> 39.419684 | AM88: =AA82 -> 0 | AR88: x | AS88: y | AU88: x | AV88: y | AY88: Calculo manual da raiz da cubica (substitui GoalSeek / macro AjustarH)
T89: =Seções!K29 -> -6 | U89: =Seções!L29 -> 50 | AD89: Ixo = | AE89: =AP85-AE86*AE88^2 -> 1127208 | AF89: =$B$2&"^4" -> ^4 | AG89: Sy(left) = | AH89: =AE90/ABS(MIN(testex)-AE87) -> 7166.7083 | AI89: =$B$2&"^3" -> ^3 | AK89: Ix | AL89: =ABS(AE89) -> 1127208 | AM89: =CONCATENATE(AA82,"4") -> 4 | AR89: =MIN(testex) -> -20 | AS89: =(AR89-$F$7)*TAN(RADIANS($F$5))+$F$8 -> 0 | AU89: =IF(AV84>=AV85,MIN(testex),(MAX(testex)+MIN(testex)-AV85)/2) -> -37.5 | AV89: =IF(AV84>=AV85,(MAX(testey)+MIN(testey)-AV84)/2,MIN(testey)) -> 0 | AY89: a | AZ89: 6.0714286
F90: =G85 -> 89299.229 | G90: = | H90: =G87*(G54-(U91-U90)) -> 4735.7143 | I90: h | J90: =G87*0.5 -> 45.535714 | K90: h^2 | L90: =G88*(G54-(U91-U90)) -> 284.14286 | M90: h^2 | N90: =G88*(2/3) -> 3.6428571 | O90: h^3 | T90: =Seções!K30 -> -15 | U90: =Seções!L30 -> 55 | AD90: Iyo = | AE90: =AP86-AE86*AE87^2 -> 143334.17 | AF90: =$B$2&"^4" -> ^4 | AG90: Sy(right)= | AH90: =AE90/ABS(MAX(testex)-AE87) -> 7166.7083 | AI90: =$B$2&"^3" -> ^3 | AK90: Wi | AL90: =ABS(AH88) -> 31680.663 | AM90: =CONCATENATE(AA82,"³") -> ³ | AR90: =MAX(testex) -> 20 | AS90: =(AR90-$F$7)*TAN(RADIANS($F$5))+$F$8 -> 0 | AU90: =IF(AV84>=AV85,MAX(testex),(MAX(testex)+MIN(testex)+AV85)/2) -> 37.5 | AV90: =IF(AV84>=AV85,(MAX(testey)+MIN(testey)+AV84)/2,MAX(testey)) -> 75 | AY90: b | AZ90: -815.1
T91: =Seções!K31 -> -15 | U91: =Seções!L31 -> 75 | AD91: Ixyo = | AE91: =+AP87-AE86*AE87*AE88 -> 0 | AF91: =$B$2&"^4" -> ^4 | AK91: Ws | AL91: =ABS(AH87) -> 28595.054 | AM91: =CONCATENATE(AA82,"³") -> ³ | AY91: c | AZ91: 11201.79
F92: =N90 -> 3.6428571 | G92: =O90 -> h^3 | H92: - | I92: =J90+L90 -> 329.67857 | J92: h^2 | K92: + | L92: =+H90 -> 4735.7143 | M92: h | N92: - | O92: =F90 -> 89299.229 | P92: = | Q92: 0 | T92: =Seções!K32 -> 0 | U92: =Seções!L32 -> 75 | AR92: =(AS92-$F$8)*TAN(RADIANS(-$F$5))+$F$7 -> 0 | AS92: =MIN(Y) -> 0 | AY92: d | AZ92: -21431
T93: =Seções!K33 -> 15 | U93: =Seções!L33 -> 75 | AD93: Section Properties About Principal Axis | AR93: =(AS93-$F$8)*TAN(RADIANS(-$F$5))+$F$7 -> 0 | AS93: =MAX(Y) -> 60 | AY93: p (cubica deprimida) | AZ93: =AZ91/AZ89-(AZ90/AZ89)^2/3 -> -4162.8447
F94: h | G94: =AZ101 -> 2.2874168 | H94: macro | T94: =Seções!K34 -> 15 | U94: =Seções!L34 -> 55 | AD94: f = | AE94: =AE85 -> 0 | AF94: deg | AG94: Sxp(top) = | AH94: {=ABS(AE95/MAX(SQRT((testex-AE87)^2+(testey-AE88)^2)*SIN(ATAN2(testex-AE87,testey-AE88)-RADIANS(AE85))))} -> 28595.054 | AI94: =$B$2&"^3" -> ^3 | AY94: q (cubica deprimida) | AZ94: =2*(AZ90/AZ89)^3/27-(AZ90/AZ89)*(AZ91/AZ89)/3+AZ92/AZ89 -> -100201.36
F95: eq | G95: =6.071428571*G94^3-815.1*G94^2+11201.79*G94-21431 -> 0 | T95: =Seções!K35 -> 6 | U95: =Seções!L35 -> 50 | AD95: Ixp = | AE95: =AE89*COS(RADIANS(AE94))^2+AE90*SIN(RADIANS(AE94))^2-AE91*SIN(2*RADIANS(AE94)) -> 1127208 | AF95: =$B$2&"^4" -> ^4 | AG95: Sxp(bot) = | AH95: {=ABS(AE95/MIN(SQRT((testex-AE87)^2+(testey-AE88)^2)*SIN(ATAN2(testex-AE87,testey-AE88)-RADIANS(AE85))))} -> 31680.663 | AI95: =$B$2&"^3" -> ^3 | AY95: shift (h = t + shift) | AZ95: =-(AZ90/AZ89)/3 -> 44.750588
T96: =Seções!K36 -> 6 | U96: =Seções!L36 -> 20 | AD96: Iyp = | AE96: =AE90*COS(RADIANS(AE94))^2+AE89*SIN(RADIANS(AE94))^2+AE91*SIN(2*RADIANS(AE94)) -> 143334.17 | AF96: =$B$2&"^4" -> ^4 | AG96: Syp(left) = | AH96: {=ABS(AE96/MIN(SQRT((testex-AE87)^2+(testey-AE88)^2)*COS(ATAN2(testex-AE87,testey-AE88)-RADIANS(AE85))))} -> 7166.7083 | AI96: =$B$2&"^3" -> ^3 | AY96: discriminante = (q/2)^2+(p/3)^3 | AZ96: =(AZ94/2)^2+(AZ93/3)^3 -> -1.6174006e+08
F97: x | G97: =((U91-U90)+G94)/F81 -> 27.859271 | H97: cm | T97: =Seções!K37 -> 20 | U97: =Seções!L37 -> 15 | AD97: Ixyp = | AE97: =+(AE89-AE90)/2*SIN(RADIANS(AE94)*2)+AE91*COS(2*RADIANS(AE94)) -> 0 | AF97: =$B$2&"^4" -> ^4 | AG97: Syp(right)= | AH97: {=ABS(AE96/MAX(SQRT((testex-AE87)^2+(testey-AE88)^2)*COS(ATAN2(testex-AE87,testey-AE88)-RADIANS(AE85))))} -> 7166.7083 | AI97: =$B$2&"^3" -> ^3 | AY97: r = RAIZ(-(p/3)^3) | AZ97: =SQRT(-(AZ93/3)^3) -> 51689.632
G98: =IF(G97<G56,I56,IF(AND(G97>G56,G97<G57,I57),I57,IF(G97>G57,"Domínio 4"))) -> Domínio 3 | T98: =Seções!K38 -> 20 | U98: =Seções!L38 -> 0 | AD98: J = | AE98: =+AE95+AE96 -> 1270542.2 | AF98: =$B$2&"^4" -> ^4 | AK98: =IF($C$3="Retângular",Seções!AA88,Seções!AJ105) -> 0 | AY98: phi = ACOS(-(q/2)/r) | AZ98: =ACOS(-(AZ94/2)/AZ97) -> 0.24859232
T99: =Seções!K39 -> 0 | U99: =Seções!L39 -> 0 | AY99: Raizes reais (t1, t2, t3 + shift) | AZ99: =2*SQRT(-AZ93/3)*COS(AZ98/3)+AZ95 -> 118.99636 | BA99: =2*SQRT(-AZ93/3)*COS((AZ98+2*PI())/3)+AZ95 -> 2.2874168 | BB99: =2*SQRT(-AZ93/3)*COS((AZ98+4*PI())/3)+AZ95 -> 12.967987
F100: Armadura | AY100: Candidatos validos (>0, senao 1E99) | AZ100: =IF(AZ99>0,AZ99,1E+99) -> 118.99636 | BA100: =IF(BA99>0,BA99,1E+99) -> 2.2874168 | BB100: =IF(BB99>0,BB99,1E+99) -> 12.967987
F101: Rcd1 | G101: =G83 -> 1821.4286 | AY101: h fisico = menor raiz positiva (= G94) | AZ101: =MIN(AZ100,BA100,BB100) -> 2.2874168
F102: Rcd2 | G102: =G87*G94 -> 208.31832
F103: Rcd3 | G103: =G88*G94^2 -> 28.590649
F105: Rcd | G105: =G101+G102-G103 -> 2001.1562 | H105: kN
F106: As | G106: =G105/((G46/10)/Geometria!O76) -> 44.025437 | H106: cm²
F110: Linha neutra na seção 3
F112: Rcd3 | G112: =0.85*((G47/10)/Geometria!$O$78)*AL53 -> 1092.8571 | H112: kN
F113: Md3 | G113: =G112*(G54-AL4-AL27-AL52/2) -> 34971.429 | H113: kN*cm
G114: =IF(G73+G64+G113>G38,"Ok, linha neutra passa na seção 3","Recalcular") -> Recalcular
G115: =(G54-AL4-AL27-AL52/2) -> 32
F117: Continuação — Seção 3 (alma): altura da linha neutra (x) e As líquido considerando a força já resistida pela protensão existente (Ap)
F118: Obs.: o bloco 'Armadura' das linhas 94-106 resolve x por uma cúbica cujos coeficientes (AZ89:AZ92) são valores fixos, não fórmulas vivas — esse bloco (e a continuação da Seção 3, linhas 117-137) ainda apresenta erro #N/A para os dados atuais e não deve ser usado; isso é irrelevante aqui porque G65 já confirma que a linha neutra está na Seção 1, que governa (ver RESULTADO FINAL, linhas 139-146).
F119: l,alma (tw) | G119: =G26 -> 12 | H119: cm | I119: Largura da alma, constante ao longo da Seção 3
F120: d0 | G120: =G54-AL4-AL27 -> 47 | H120: cm | I120: Profundidade ate o topo da Seção 3 (abaixo das Seções 1+2, ja plenamente comprimidas)
...

Sheet Homogeneização
K2: 2 . Homogeneização da seção - Cordoalhas
K4: Ac = | L4: ='Propriedades geométricas VIGA'!M6 -> 1800 | M4: cm²
K5: I = | L5: ='Propriedades geométricas VIGA'!M9 -> 540000 | M5: cm²
K6: y'.1 = | L6: ='Propriedades geométricas VIGA'!M7 -> 30 | M6: cm
K7: y'.2 = | L7: ='Propriedades geométricas VIGA'!M8 -> 30 | M7: cm
K9: Ach = | L9: =L4-(Geometria!L252+Geometria!L266)+L11*(Geometria!L252+Geometria!L266) -> 1864.9829 | M9: cm²
K11: α = | L11: =L73 -> 6.8020463
K12: yhs = | L12: =IF(Geometria!$M$19="2 - i",Geometria!$L$70,Geometria!$L$27)-L13 -> 30.65332 | M12: cm | N12: yhs = H - yhi (mesma referencia, complementar)
K13: yhi = | L13: =(L4*L6+(L11-1)*Geometria!L252*Geometria!R253+(L11-1)*Geometria!L266*(IF(Geometria!$M$19="2 - i",Geometria!$L$70,Geometria!$L$27)-Geometria!R267))/L9 -> 29.34668 | M13: cm | N13: yhi = (Ac.Yi + (a-1).Ap.hp + (a-1).A'p.h'p) / Ach -> media ponderada DIRETA das areas em relacao a base, com as duas armaduras (Ap e A'p) ao mesmo tempo. Antes: calculava cada armadura isolada e tirava media simetrica (aproximacao errada)
K14: Dy = | L14: =L17 -> 30.65332
K15: Ih = | L15: =L5+L4*(L6-L13)^2+(L11-1)*Geometria!L252*(L13-Geometria!R253)^2+(L11-1)*Geometria!L266*(L13-(IF(Geometria!$M$19="2 - i",Geometria!$L$70,Geometria!$L$27)-Geometria!R267))^2 -> 562049.53 | M15: cm^4 | N15: Ih = I + Ac.(Yi-yhi)^2 + (a-1).Ap.(yhi-hp)^2 + (a-1).A'p.(yhi-h'p)^2 -> Steiner com AREA BRUTA (Ac) e distancias ATE O NOVO centroide (yhi), nao ate o antigo
K17: yhs = | L17: =IF(Geometria!$M$19="2 - i",Geometria!$L$70,Geometria!$L$27)-L18 -> 30.65332
K18: yhi = | L18: =L13 -> 29.34668
K19: Wh
K20: Whs = | L20: =L15/L17 -> 18335.682 | M20: cm³
K21: Whi = | L21: =L15/L18 -> 19152.065 | M21: cm³
K23: 2 . Homogeneização da seção composta
K25: Ac = | L25: ='Propriedades geométricas LAJE'!M6 -> 3105.1954 | M25: cm²
K26: I = | L26: =IF(Geometria!$M$18="1 - Sim",'Propriedades geométricas LAJE'!M9,0) -> 2598580.9 | M26: cm²
K27: y'.1 = | L27: =IF(Geometria!$M$18="1 - Sim",'Propriedades geométricas LAJE'!M7,0) -> 51.362431 | M27: cm
K28: y'.2 = | L28: =IF(Geometria!$M$18="1 - Sim",'Propriedades geométricas LAJE'!M8,0) -> 38.637569 | M28: cm
K30: Ach,comp = | L30: =L25-(Geometria!L252+Geometria!L266)+L32*(Geometria!L252+Geometria!L266) -> 3155.1506 | M30: cm²
K32: α = | L32: =L78 -> 5.460284
K33: yhs = | L33: =IF(Geometria!$M$18="1 - Sim",IF(Geometria!$M$19="2 - i",Geometria!$L$70,Geometria!$L$27)+Geometria!L42+Geometria!L45-L34,0) -> 39.272665 | M33: cm | N33: yhs = H,total - yhi (H,total = viga + capa + laje)
K34: yhi = | L34: =IF(Geometria!$M$18="1 - Sim",(L25*L27+(L32-1)*Geometria!L252*Geometria!R253+(L32-1)*Geometria!L266*(IF(Geometria!$M$19="2 - i",Geometria!$L$70,Geometria!$L$27)-Geometria!R267))/L30,0) -> 50.727335 | M34: cm | N34: yhi = (Ac,comp.Yi,comp + (a-1).Ap.hp + (a-1).A'p.h'p) / Ach,comp -> agora usa a area/Yi da SECAO COMPOSTA (L25/L28). Antes usava por engano a area/Yi da viga isolada (L4/L6) - maior erro de todos, ~3cm de LN e ~16% no Ih
K35: Dy = | L35: =IF(Geometria!$M$18="1 - Sim",L38,0) -> 39.272665
K36: Ih = | L36: =IF(Geometria!$M$18="1 - Sim",L26+L25*(L27-L34)^2+(L32-1)*Geometria!L252*(L34-Geometria!R253)^2+(L32-1)*Geometria!L266*(L34-(IF(Geometria!$M$19="2 - i",Geometria!$L$70,Geometria!$L$27)-Geometria!R267))^2,0) -> 2677686.5 | M36: cm^4 | N36: Ih = I,comp + Ac,comp.(Yi,comp-yhi)^2 + (a-1).Ap.(yhi-hp)^2 + (a-1).A'p.(yhi-h'p)^2
K38: yhs = | L38: =IF(Geometria!$M$18="1 - Sim",IF(Geometria!$M$19="2 - i",Geometria!$L$70,Geometria!$L$27)+Geometria!L42+Geometria!L45-L39,0) -> 39.272665
K39: yhi = | L39: =IF(Geometria!$M$18="1 - Sim",L34,0) -> 50.727335
K40: Wh
K41: Whs = | L41: =IF(Geometria!$M$18="1 - Sim",L36/L38,0) -> 68181.94 | M41: cm³
K42: Whi = | L42: =IF(Geometria!$M$18="1 - Sim",L36/L39,0) -> 52785.87 | M42: cm³
K44: 2 . Homogeneização da seção - Vergalhão
L45: seção pré | R45: seção composta
K46: Ac = | L46: =L9 -> 1864.9829 | M46: cm² | Q46: Ac = | R46: =L30 -> 3155.1506 | S46: cm²
K47: I = | L47: =L15 -> 562049.53 | M47: cm² | Q47: I = | R47: =IF(Geometria!$M$18="1 - Sim",L36,0) -> 2677686.5 | S47: cm²
K48: y'.1 = | L48: =L18 -> 29.34668 | M48: cm | Q48: y'.1 = | R48: =IF(Geometria!$M$18="1 - Sim",L39,0) -> 50.727335 | S48: cm
K49: y'.2 = | L49: =L17 -> 30.65332 | M49: cm | Q49: y'.2 = | R49: =IF(Geometria!$M$18="1 - Sim",L38,0) -> 39.272665 | S49: cm
K51: Ach = | L51: =L46-(IFERROR(Taxas!K51,0)+IFERROR(Taxas!K58,0))+L53*(IFERROR(Taxas!K51,0)+IFERROR(Taxas!K58,0)) -> 2050.1318 | M51: cm² | Q51: Ach = | R51: =R46-(IFERROR(Taxas!K51,0)+IFERROR(Taxas!K58,0))+R53*(IFERROR(Taxas!K51,0)+IFERROR(Taxas!K58,0)) -> 3297.8311 | S51: cm²
K53: α = | L53: =L74 -> 7.1421486 | Q53: α = | R53: =L79 -> 5.7332982
K54: yhs = | L54: =IF(Geometria!$M$19="2 - i",Geometria!$L$70,Geometria!$L$27)-L55 -> 32.014003 | M54: cm | N54: yhs = H - yhi | Q54: yhs = | R54: =IF(Geometria!$M$18="1 - Sim",IF(Geometria!$M$19="2 - i",Geometria!$L$70,Geometria!$L$27)+Geometria!L42+Geometria!L45-R55,0) -> 40.849558 | S54: cm | U54: yhs = H,total - yhi
K55: yhi = | L55: =(L46*L48+(L53-1)*IFERROR(Taxas!K58,0)*(Geometria!R76+IFERROR(Taxas!I57,0)/20)+(L53-1)*IFERROR(Taxas!K51,0)*(IF(Geometria!$M$19="2 - i",Geometria!$L$70,Geometria!$L$27)-(Geometria!R76+IFERROR(Taxas!I50,0)/20)))/L51 -> 27.985997 | M55: cm | N55: yhi = (Ach.Yi,ach + (a-1).As,inf.hs,inf + (a-1).As,sup.hs,sup) / Ach,verg -> As,sup convertido p/ distancia-da-base (H-(cobrim+bitola/2)), consistente com As,inf | Q55: yhi = | R55: =IF(Geometria!$M$18="1 - Sim",(R46*R48+(R53-1)*IFERROR(Taxas!K58,0)*(Geometria!R76+IFERROR(Taxas!I57,0)/20)+(R53-1)*IFERROR(Taxas!K51,0)*(IF(Geometria!$M$19="2 - i",Geometria!$L$70,Geometria!$L$27)-(Geometria!R76+IFERROR(Taxas!I50,0)/20)))/R51,0) -> 49.150442 | S55: cm | U55: yhi = mesma logica do lado "pre", partindo de R46/R48 (secao composta ja homogeneizada com cordoalhas, bloco 2 corrigido)
K56: Dy = | L56: =L59 -> 32.014003 | Q56: Dy = | R56: =IF(Geometria!$M$18="1 - Sim",R59,0) -> 40.849558
K57: Ih = | L57: =L47+L46*(L48-L55)^2+(L53-1)*IFERROR(Taxas!K58,0)*(L55-(Geometria!R76+IFERROR(Taxas!I57,0)/20))^2+(L53-1)*IFERROR(Taxas!K51,0)*(L55-(IF(Geometria!$M$19="2 - i",Geometria!$L$70,Geometria!$L$27)-(Geometria!R76+IFERROR(Taxas!I50,0)/20)))^2 -> 681623.43 | M57: cm^4 | N57: Ih = Ih,anterior + Ach.(Yi,ach-yhi)^2 + (a-1).As,inf.(yhi-hs,inf)^2 + (a-1).As,sup.(yhi-hs,sup)^2 | Q57: Ih = | R57: =IF(Geometria!$M$18="1 - Sim",R47+R46*(R48-R55)^2+(R53-1)*IFERROR(Taxas!K58,0)*(R55-(Geometria!R76+IFERROR(Taxas!I57,0)/20))^2+(R53-1)*IFERROR(Taxas!K51,0)*(R55-(IF(Geometria!$M$19="2 - i",Geometria!$L$70,Geometria!$L$27)-(Geometria!R76+IFERROR(Taxas!I50,0)/20)))^2,0) -> 2921706.8 | S57: cm^4 | U57: Ih corrigido: a formula original referenciava L26/L30/L27/L34/L32 (bloco 2) por engano, em vez de R47/R46/R48/R55/R53 (bloco 3, secao composta)
K59: yhs = | L59: =IF(Geometria!$M$19="2 - i",Geometria!$L$70,Geometria!$L$27)-L60 -> 32.014003 | N59: yhs (redundante) corrigido: antes usava L18 (yhi do bloco 1, errado) em vez de L60 (yhi deste bloco). Whs=L57/L59 tinha o Ih certo mas dividia pelo yhs errado | Q59: yhs = | R59: =IF(Geometria!$M$18="1 - Sim",IF(Geometria!$M$19="2 - i",Geometria!$L$70,Geometria!$L$27)+Geometria!L42+Geometria!L45-R60,0) -> 40.849558
K60: yhi = | L60: =L55 -> 27.985997 | Q60: yhi = | R60: =IF(Geometria!$M$18="1 - Sim",R55,0) -> 49.150442
K61: Wh | Q61: Wh
K62: Whs = | L62: =L57/L59 -> 21291.415 | M62: cm³ | Q62: Whs = | R62: =IF(Geometria!$M$18="1 - Sim",R57/R59,0) -> 71523.584 | S62: cm³
K63: Whi = | L63: =L57/L60 -> 24355.874 | M63: cm³ | Q63: Whi = | R63: =IF(Geometria!$M$18="1 - Sim",R57/R60,0) -> 59444.161 | S63: cm³
K66: Parâmetros da homogeneização (como na planilha de referência: α = Ep/Ecs(t) para cordoalhas e Es/Ecs(t) para vergalhões)
K68: Ep = | L68: 200000 | M68: MPa | N68: Módulo de elasticidade das cordoalhas (NBR 6118, 8.4.4).
K69: Es = | L69: 210000 | M69: MPa | N69: Módulo de elasticidade dos vergalhões (NBR 6118, 8.3.5).
K70: t,pré = | L70: =Geometria!$M$332 -> 1 | M70: dias | N70: Idade da seção pré-fabricada na homogeneização (ato da protensão).
K71: β1(t,pré) = | L71: =EXP(Fluência!$B$17*(1-(28/L70)^(1/2))) -> 0.42388185 | M71: - | N71: Crescimento da resistência do concreto com a idade.
K72: Ecs(t,pré) = | L72: =MIN(1,0.8+0.2*MAX(Geometria!$L$84,MIN(Geometria!$L$82,L71*Geometria!$L$82))/80)*IF(Geometria!$L$82<=50,(MAX(Geometria!$L$84,MIN(Geometria!$L$82,L71*Geometria!$L$82))/Geometria!$L$82)^0.5,(MAX(Geometria!$L$84,MIN(Geometria!$L$82,L71*Geometria!$L$82))/Geometria!$L$82)^0.3)*Geometria!$L$1172*1000 -> 29402.917 | M72: MPa | N72: Módulo secante do concreto da viga nessa idade.
K73: αp,pré = | L73: =L68/L72 -> 6.8020463 | M73: - | N73: Relação Ep/Ecs – cordoalhas na seção pré-fabricada.
K74: αe,pré = | L74: =L69/L72 -> 7.1421486 | M74: - | N74: Relação Es/Ecs – vergalhões na seção pré-fabricada.
K75: t,comp = | L75: =Geometria!$M$335 -> 30 | M75: dias | N75: Idade na solidarização (seção composta).
K76: β1(t,comp) = | L76: =EXP(Fluência!$B$17*(1-(28/L75)^(1/2))) -> 1.0068047 | M76: - | N76: Crescimento da resistência do concreto com a idade.
K77: Ecs(t,comp) = | L77: =MIN(1,0.8+0.2*MAX(Geometria!$L$84,MIN(Geometria!$L$82,L76*Geometria!$L$82))/80)*IF(Geometria!$L$82<=50,(MAX(Geometria!$L$84,MIN(Geometria!$L$82,L76*Geometria!$L$82))/Geometria!$L$82)^0.5,(MAX(Geometria!$L$84,MIN(Geometria!$L$82,L76*Geometria!$L$82))/Geometria!$L$82)^0.3)*Geometria!$L$1172*1000 -> 36628.131 | M77: MPa | N77: Módulo secante do concreto da viga nessa idade.
K78: αp,comp = | L78: =L68/L77 -> 5.460284 | M78: - | N78: Relação Ep/Ecs – cordoalhas na seção composta.
K79: αe,comp = | L79: =L69/L77 -> 5.7332982 | M79: - | N79: Relação Es/Ecs – vergalhões na seção composta.

Sheet Isolamento de cabos
L2: 9 . Perdas de protensão
L3: Tamanho da pista | M3: =Geometria!L280 -> 100 | N3: m
L4: Acomodação da cunha | M4: 0.6 | N4: cm
L6: Δσancoragem | M6: =(2*10^4*M4/100)/M3 -> 1.2 | N6: kN/cm²
L10: Relaxação da armadura | Q10: Perdas diferidas
L12: σ,pi | M12: =Geometria!N236-M6 -> 145.1 | N12: kN/cm² | Q12: Seção 1 (viga)
Q13: Ac | R13: =Geometria!Q290 -> 1800
L14: R | M14: =M12/190 -> 0.76368421 | N14: =M14*100 -> 76.368421 | Q14: Perímetro | R14: =Geometria!Q291 -> 201.62278 | S14: cm
L15: Ѱ | M15: 1.772
L16: Δσ,pr | M16: =M15/100*M12 -> 2.571172 | N16: kN/cm² | Q16: Seção 2 (laje)
Q17: Ac | R17: =Geometria!Q294 -> 3105.1954
Q18: Perímetro | R18: =Geometria!Q295 -> 187 | S18: cm
L19: Perda por deformação imediata do concreto
L21: A,p | M21: =Geometria!P1414 -> 5.6 | N21: cm² | Q21: Np | R21: =M21*N47+M23*N48 -> 749.9028 | S21: kN
L22: e,p | M22: =Geometria!L30-Geometria!P1406 -> 28.5 | N22: cm | Q22: Mp | R22: =M21*N47*M22/100-M23*N48*M24/100 -> 213.7223 | S22: kN*m
L23: A',p | M23: =Geometria!P1429 -> 0 | N23: cm²
L24: e',p | M24: =Geometria!L31-Geometria!P1421 -> 30 | N24: cm
Q25: A | R25: =(R21/(Geometria!L48/100^2)+(R22-Geometria!M206)/(Geometria!L49/100^4)*(M22/100))*O54 -> 32881.447 | S25: kN/m²
Q26: B | R26: =((Geometria!M207*R56+Geometria!M208*R57)*(M22/100))/(Geometria!L49/100^4) -> 25379.208 | S26: kN/m²
L27: σ,pi | M27: =Geometria!N236-(M6+M16) -> 142.52883 | N27: kN/cm² | Q27: C | R27: =((Geometria!M210*R58+Geometria!M209*R59)*((Geometria!M30/100)-(Geometria!L277/100)))/(Geometria!M49/100^4) -> 1228.6509 | S27: kN/m²
Q28: D | R28: =Geometria!L77*((Geometria!M211*((Geometria!M30/100)-(Geometria!L277/100)))/(Geometria!M49/100^4))*R60 -> 11479.365 | S28: kN/m²
L30: Np | M30: =M21*M27+M23*M27 -> 798.16144 | N30: kN
L31: Mp | M31: =M21*M27*M22/100-M23*M27*M24/100 -> 227.47601 | N31: kN*cm | Q31: σ,p | R31: =Geometria!Q308 -> 5.0507627
Q32: Δσ,p,c,inf | R32: =(R31*(R25-R26-R27-R28)) -> -26293.139 | S32: kN/m²
R33: =R32/100^2 -> -2.6293139 | S33: kN/cm²
L34: σc,po+g,inf | M34: =(M30/(Geometria!L48/100^2)+((M31-Geometria!M206)/(Geometria!L49/100^4))*M22/100) -> 14275.097 | N34: kN/m²
L35: σc,po+g,sup | M35: =(M30/(Geometria!L48/100^2)+((-M31+Geometria!M206)/(Geometria!L49/100^4))*M24/100) -> -5924.5772 | N35: kN/m²
Q37: A' | R37: =(R21/(Geometria!L48/100^2)+((-R22+Geometria!M206)/(Geometria!L49/100^4))*M24/100)*R54 -> -13440.13 | S37: kN/m²
Q38: B | R38: =((Geometria!M207*R56+Geometria!M208*R57)*M24/100)/(Geometria!L49/100^4) -> 26714.955 | S38: kN/m²
L39: Eci | M39: =Geometria!L316 -> 33130.047 | N39: Mpa | Q39: C | R39: =((Geometria!M210*R58+Geometria!M209*R59)*((Geometria!M31-Geometria!R76-Geometria!L42-Geometria!L45)/100))/(Geometria!M49/100^4) -> 172.67974 | S39: kN/m²
L40: σp | M40: =200000/M39 -> 6.0368161 | Q40: D | R40: =Geometria!L77*((Geometria!M211*((Geometria!M31-Geometria!R76-Geometria!L42-Geometria!L45)/100)))/(Geometria!M49/100^4)*R60 -> 1613.358 | S40: kN/m²
L43: Δσcg,inf | M43: =M40*M34/10000 -> 8.6176137 | N43: kN/cm² | Q43: Δσ,p,c,sup | R43: =R31*ABS(-R37-R38-R39-R40) -> 76068.847 | S43: kN/m²
L44: Δσcg,sup | M44: =M40*M35/10000 -> -3.5765583 | N44: kN/cm² | R44: =R43/100^2 -> 7.6068847 | S44: kN/cm²
M47: σpinf,t=1 | N47: =Geometria!N236-M6-M16-M43 -> 133.91121 | O47: kN/cm² | P47: =100-(N47*100)/Geometria!N236 -> 8.4680695
M48: σpsup,t=1 | N48: =Geometria!N236-M6-M16-M44 -> 146.10539 | O48: kN/cm² | P48: =100-(N48*100)/Geometria!N236 -> 0.13302372
L51: 10 . Coeficientes de fluência
M53: Ação | N53: t₀ seção 01 | O53: Coeficiente φ seção 01 | P53: t₀ seção 02 | Q53: Coeficiente φ seção 02 | R53: Coeficiente φ final
M54: Protensão | N54: 1 | O54: =Fluência!$B$44 -> 2.4758069 | P54: -- | Q54: -- | R54: =AVERAGE(O54,Q54) -> 2.4758069
M55: Pp VIGA | N55: 1 | O55: =Fluência!$B$44 -> 2.4758069 | P55: -- | Q55: -- | R55: =AVERAGE(O55,Q55) -> 2.4758069
M56: PP Laje | N56: 15 | O56: =Fluência!$V$44 -> 1.5488539 | P56: -- | Q56: -- | R56: =AVERAGE(O56,Q56) -> 1.5488539
M57: Capa | N57: 30 | O57: =Fluência!$AF$44 -> 1.3348679 | P57: 1 | Q57: =IF(Geometria!M18="1 - Sim",IFERROR(Fluência!$B$92,0),O57) -> 3.7602554 | R57: =AVERAGE(O57,Q57) -> 2.5475617
M58: Alvenaria | N58: 45 | O58: =Fluência!$AP$44 -> 1.2168856 | P58: 15 | Q58: =IF(Geometria!M18="1 - Sim",IFERROR(Fluência!$L$92,0),O58) -> 2.7082556 | R58: =AVERAGE(O58,Q58) -> 1.9625706
M59: Revestimento | N59: 60 | O59: =Fluência!$AZ$44 -> 1.1348005 | P59: 30 | Q59: =IF(Geometria!M18="1 - Sim",IFERROR(Fluência!$V$92,0),O59) -> 2.4054951 | R59: =AVERAGE(O59,Q59) -> 1.7701478
M60: Carga acidental | N60: 75 | O60: =Fluência!$BJ$44 -> 1.0717386 | P60: 45 | Q60: =IF(Geometria!M18="1 - Sim",IFERROR(Fluência!$AF$92,0),O60) -> 2.2359825 | R60: =AVERAGE(O60,Q60) -> 1.6538606
M61: Perda protensão | N61: 75 | O61: =Fluência!$BJ$44 -> 1.0717386 | P61: 45 | Q61: =IF(Geometria!M18="1 - Sim",IFERROR(Fluência!$AF$92,0),O60) -> 2.2359825 | R61: =AVERAGE(O61,Q61) -> 1.6538606
L64: Perda por retração do concreto | P64: Simultaneidade das perdas
L66: Δσ,p,s | M66: =Fluência!$D$30*2*10^4 -> -10.617091 | N66: kN/cm² | P66: Xp,inf | Q66: =1+M77 -> 1.0658182
P67: Xp,inf | Q67: =1+M78 -> 1.0831033
L69: Relaxação da armadura | P69: X,c | Q69: =1+0.5*R54 -> 2.2379035
L70: Porcentagem da força de tração da cordoalha | P70: N,inf | Q70: =1+(M22/100)^2*((Geometria!L48/100^2)/(Geometria!L49/100^4)) -> 3.7075
L71: R,inf | M71: =N47/Geometria!$L$88 -> 0.70479586 | P71: N,sup | Q71: =1+(M24/100)^2*((Geometria!L48/100^2)/(Geometria!L49/100^4)) -> 4
L72: R,sup | M72: =N48/Geometria!$L$88 -> 0.76897572 | P72: P,p | Q72: =(M21+M23)/(Geometria!L48) -> 0.0031111111
L74: Ѱ(inf,1) | M74: =2.5*Q84 -> 6.3698966 | P74: Δσ,p(inf,1)inf | Q74: =(M66-R33-M80)/(Q67+Q69*R31*Q70*Q72) -> -13.845797 | R74: kN/cm²
L75: Ѱ(sup,1) | M75: =2.5*Q85 -> 7.9743929 | P75: Δσ,p(inf,1)sup | Q75: =(M66-R44-M81)/(Q67+Q69*R31*Q71*Q72) -> -24.813451 | R75: kN/cm²
P76: Valores de Ѱ,1000 em porcentagem
L77: X(inf,1)inf | M77: =-LN(1-M74/100) -> 0.065818237 | Q77: Cordoalhas | R77: Barras
L78: X(inf,1)sup | M78: =-LN(1-M75/100) -> 0.08310331 | P78: fptk (%) | Q78: Rb
P79: 0.5 | Q79: 0 | R79: 0
L80: Δσ,pr,inf | M80: =N47*M77 -> 8.8138 | N80: kN/cm² | P80: 0.6 | Q80: 1.3 | R80: 1.5
L81: Δσ,pr,sup | M81: =N48*M78 -> 12.141841 | N81: kN/cm² | P81: 0.7 | Q81: 2.5 | R81: 4
P82: 0.8 | Q82: 3.5 | R82: 7
P84: =M71 -> 0.70479586 | Q84: =IF(P84<=INDEX($P$79:$P$82,1),0,INDEX($Q$79:$Q$82,MIN(MATCH(P84,$P$79:$P$82,1),3))+(P84-INDEX($P$79:$P$82,MIN(MATCH(P84,$P$79:$P$82,1),3)))*(INDEX($Q$79:$Q$82,MIN(MATCH(P84,$P$79:$P$82,1),3)+1)-INDEX($Q$79:$Q$82,MIN(MATCH(P84,$P$79:$P$82,1),3)))/(INDEX($P$79:$P$82,MIN(MATCH(P84,$P$79:$P$82,1),3)+1)-INDEX($P$79:$P$82,MIN(MATCH(P84,$P$79:$P$82,1),3)))) -> 2.5479586
P85: =M72 -> 0.76897572 | Q85: =IF(P85<=INDEX($P$79:$P$82,1),0,INDEX($Q$79:$Q$82,MIN(MATCH(P85,$P$79:$P$82,1),3))+(P85-INDEX($P$79:$P$82,MIN(MATCH(P85,$P$79:$P$82,1),3)))*(INDEX($Q$79:$Q$82,MIN(MATCH(P85,$P$79:$P$82,1),3)+1)-INDEX($Q$79:$Q$82,MIN(MATCH(P85,$P$79:$P$82,1),3)))/(INDEX($P$79:$P$82,MIN(MATCH(P85,$P$79:$P$82,1),3)+1)-INDEX($P$79:$P$82,MIN(MATCH(P85,$P$79:$P$82,1),3)))) -> 3.1897572
L87: Tensão final dos cabos
N88: Perda (%)
L89: σ,pinf | M89: =N47-ABS(Q74) -> 120.06542 | N89: =100-(M89*100)/Geometria!N236 -> 17.932045
L90: σ,psup | M90: =N48-ABS(Q75) -> 121.29194 | N90: =100-(M90*100)/Geometria!N236 -> 17.093687
D93: Np,isol | E93: =Geometria!L909 -> 749.9028 | F93: kN | AA93: Np,isol | AB93: =Geometria!L376 -> 621.77981 | AC93: kN
D94: Mp,isol | E94: =Geometria!L910 -> 213.7223 | F94: kN*m | M94: TENSÕES | AA94: Mp,isol | AB94: =Geometria!L377 -> 177.20725 | AC94: kN*m
H95: 15331.407
AE96: -710 | BC96: =(IF(AW125="Sim",IF(AU125="Sim",$AB$93,Geometria!$L$1452),IF(AU125="Sim",Geometria!$L$1454,Geometria!$L$373))) -> 621.77981 | BD96: =(IF(AW125="Sim",IF(AU125="Sim",$AB$94,Geometria!$L$1453),IF(AU125="Sim",Geometria!$L$1455,Geometria!$L$374))) -> 177.20725 | BZ96: =(IF(BT125="Sim",IF(BR125="Sim",$AB$93,Geometria!$L$1452),IF(BR125="Sim",Geometria!$L$1454,Geometria!$L$373))) -> 621.77981 | CA96: =(IF(BT125="Sim",IF(BR125="Sim",$AB$94,Geometria!$L$1453),IF(BR125="Sim",Geometria!$L$1455,Geometria!$L$374))) -> 177.20725 | CW96: =(IF(CQ125="Sim",IF(CO125="Sim",$AB$93,Geometria!$L$1452),IF(CO125="Sim",Geometria!$L$1454,Geometria!$L$373))) -> 621.77981 | CX96: =(IF(CQ125="Sim",IF(CO125="Sim",$AB$94,Geometria!$L$1453),IF(CO125="Sim",Geometria!$L$1455,Geometria!$L$374))) -> 177.20725
D97: ATO | AA97: ELS-F MÁXIMO | AX97: ELS-F MÍNIMO | BU97: ELS-D MÁXIMO | CR97: ELS-D MÍNIMO
F99: Tensão ajustada | G99: Tensão reduzida pelo comprimento de transferência | I99: Tensão calculada | L99: Np | M99: Mp | AC99: Tensão ajustada | AD99: Tensão reduzida pelo comprimento de transferência | AF99: Tensão calculada | AI99: Np | AJ99: Mp | AZ99: Tensão ajustada | BA99: Tensão reduzida pelo comprimento de transferência | BC99: Tensão calculada | BF99: Np | BG99: Mp | BW99: Tensão ajustada | BX99: Tensão reduzida pelo comprimento de transferência | BZ99: Tensão calculada | CC99: Np | CD99: Mp | CT99: Tensão ajustada | CU99: Tensão reduzida pelo comprimento de transferência | CW99: Tensão calculada | CZ99: Np | DA99: Mp
B100: (m) | C100: Isolado? | R100: Borda Superior | W100: Limite | Y100: (m) | Z100: Isolado? | AO100: Borda Superior | AT100: Limite | AV100: (m) | AW100: Isolado? | BL100: Borda Superior | BQ100: Limite | BS100: (m) | BT100: Isolado? | CI100: Borda Superior | CN100: Limite | CP100: (m) | CQ100: Isolado? | DF100: Borda Superior | DK100: Limite | EA100: ELU-ATO | EB100: (reduzir) | EC100: FINAL c/ furo | ED100: ELS-F mín | EE100: (reduzir) | EF100: FINAL c/ furo | EG100: ELS-F máx | EH100: (reduzir) | EI100: FINAL c/ furo | EJ100: ELS-D máx | EK100: (reduzir) | EL100: FINAL c/ furo | EM100: ELS-D mín | EN100: (reduzir) | EO100: FINAL c/ furo | EP100: sideA(inf) | EQ100: sideB(inf) | ER100: NpA_correta | ES100: MpA_correta | ET100: NpB_correta | EU100: MpB_correta | EV100: sideA(ATO) | EW100: sideB(ATO) | EX100: NpA_ATO_correta | EY100: MpA_ATO_correta | EZ100: NpB_ATO_correta | FA100: MpB_ATO_correta
A101: =IF(OR(AND(B101<Geometria!$L$1405/100,Geometria!$K$1405>0),AND((Geometria!$L$29/100-B101)<Geometria!$R$1405/100,Geometria!$Q$1405>0)),"Sim","Não") -> Sim | B101: =Tensões!$B$63 -> 0 | C101: =IF(OR(AND(B101<Geometria!$L$1409/100,OR(Geometria!$K$1409>0,Geometria!$K$1407>0)),AND((Geometria!$L$29/100-B101)<Geometria!$R$1409/100,OR(Geometria!$Q$1409>0,Geometria!$Q$1407>0))),"Sim","Não") -> Não | D101: σi,1 | E101: =IF(Geometria!$K$437<Geometria!$N$1307/100,"Reduzir","OK") -> Reduzir | F101: =IF(E101="Reduzir",G101,I101) -> 0 | G101: 0 | H101: 0 | I101: =Geometria!$C$913 -> 0 | L101: 0 | M101: 0 | R101: σi,1 | S101: 0 | T101: kN/m² | U101: =S101/1000 -> 0 | V101: MPa | W101: =Geometria!V938 -> 0 | X101: =IF(OR(AND(Y101<Geometria!$L$1405/100,Geometria!$K$1405>0),AND((Geometria!$L$29/100-Y101)<Geometria!$R$1405/100,Geometria!$Q$1405>0)),"Sim","Não") -> Sim | Y101: =Geometria!$K$415 -> 0 | Z101: =IF(OR(AND(Y101<Geometria!$L$1409/100,OR(Geometria!$K$1409>0,Geometria!$K$1407>0)),AND((Geometria!$L$29/100-Y101)<Geometria!$R$1409/100,OR(Geometria!$Q$1409>0,Geometria!$Q$1407>0))),"Sim","Não") -> Não | AA101: σi,1 | AB101: =IF(Geometria!$K$437<Geometria!$N$1307/100,"Reduzir","OK") -> Reduzir | AC101: =IF(AB101="Reduzir",AD101,AF101) -> 0 | AD101: 0 | AE101: 0 | AF101: =Geometria!$C$913 -> 0 | AI101: 0 | AJ101: 0 | AO101: σi,1 | AP101: 0 | AQ101: kN/m² | AR101: =AP101/1000 -> 0 | AS101: MPa | AT101: =Geometria!AS938 -> 0 | AU101: =IF(OR(AND(AV101<Geometria!$L$1405/100,Geometria!$K$1405>0),AND((Geometria!$L$29/100-AV101)<Geometria!$R$1405/100,Geometria!$Q$1405>0)),"Sim","Não") -> Sim | AV101: =Geometria!$K$415 -> 0 | AW101: =IF(OR(AND(AV101<Geometria!$L$1409/100,OR(Geometria!$K$1409>0,Geometria!$K$1407>0)),AND((Geometria!$L$29/100-AV101)<Geometria!$R$1409/100,OR(Geometria!$Q$1409>0,Geometria!$Q$1407>0))),"Sim","Não") -> Não | AX101: σi,1 | AY101: =IF(Geometria!$K$437<Geometria!$N$1307/100,"Reduzir","OK") -> Reduzir | AZ101: =IF(AY101="Reduzir",BA101,BC101) -> 0 | BA101: 0 | BB101: 0 | BC101: =Geometria!$C$913 -> 0 | BF101: 0 | BG101: 0 | BL101: σi,1 | BM101: 0 | BN101: kN/m² | BO101: =BM101/1000 -> 0 | BP101: MPa | BQ101: =Geometria!BP938 -> 0 | BR101: =IF(OR(AND(BS101<Geometria!$L$1405/100,Geometria!$K$1405>0),AND((Geometria!$L$29/100-BS101)<Geometria!$R$1405/100,Geometria!$Q$1405>0)),"Sim","Não") -> Sim | BS101: =Geometria!$K$415 -> 0 | BT101: =IF(OR(AND(BS101<Geometria!$L$1409/100,OR(Geometria!$K$1409>0,Geometria!$K$1407>0)),AND((Geometria!$L$29/100-BS101)<Geometria!$R$1409/100,OR(Geometria!$Q$1409>0,Geometria!$Q$1407>0))),"Sim","Não") -> Não | BU101: σi,1 | BV101: =IF(Geometria!$K$437<Geometria!$N$1307/100,"Reduzir","OK") -> Reduzir | BW101: =IF(BV101="Reduzir",BX101,BZ101) -> 0 | BX101: 0 | BY101: 0 | BZ101: =Geometria!$C$913 -> 0 | CC101: 0 | CD101: 0 | CI101: σi,1 | CJ101: 0 | CK101: kN/m² | CL101: =CJ101/1000 -> 0 | CM101: MPa | CN101: =Geometria!CM938 -> 0 | CO101: =IF(OR(AND(CP101<Geometria!$L$1405/100,Geometria!$K$1405>0),AND((Geometria!$L$29/100-CP101)<Geometria!$R$1405/100,Geometria!$Q$1405>0)),"Sim","Não") -> Sim | CP101: =Geometria!$K$415 -> 0 | CQ101: =IF(OR(AND(CP101<Geometria!$L$1409/100,OR(Geometria!$K$1409>0,Geometria!$K$1407>0)),AND((Geometria!$L$29/100-CP101)<Geometria!$R$1409/100,OR(Geometria!$Q$1409>0,Geometria!$Q$1407>0))),"Sim","Não") -> Não | CR101: σi,1 | CS101: =IF(Geometria!$K$437<Geometria!$N$1307/100,"Reduzir","OK") -> Reduzir | CT101: =IF(CS101="Reduzir",CU101,CW101) -> 0 | CU101: 0 | CV101: 0 | CW101: =Geometria!$C$913 -> 0 | CZ101: 0 | DA101: 0 | DF101: σi,1 | DG101: 0 | DH101: kN/m² | DI101: =DG101/1000 -> 0 | DJ101: MPa | DK101: =Geometria!DJ938 -> 0 | EA101: =0 -> 0 | EB101: =Geometria!$C$913 -> 0 | EC101: =IF(AND('Aberturas na Alma'!$M$18="NÃO DISPENSADO — furo deve ser verificado (cálculo abaixo)",OR(AND(B101>=('Aberturas na Alma'!$M$4-'Aberturas na Alma'!$M$7/2)/100,B101<=('Aberturas na Alma'!$M$4+'Aberturas na Alma'!$M$7/2)/100),ABS(B101-'Aberturas na Alma'!$M$4/100)<=Geometria!$L$29/4000)),IF(E101="Reduzir",EA101,EB101),F101) -> 0 | ED101: =0 -> 0 | EE101: =Geometria!$C$913 -> 0 | EF101: =IF(AND('Aberturas na Alma'!$M$18="NÃO DISPENSADO — furo deve ser verificado (cálculo abaixo)",OR(AND(B101>=('Aberturas na Alma'!$M$4-'Aberturas na Alma'!$M$7/2)/100,B101<=('Aberturas na Alma'!$M$4+'Aberturas na Alma'!$M$7/2)/100),ABS(B101-'Aberturas na Alma'!$M$4/100)<=Geometria!$L$29/4000)),IF(AB101="Reduzir",ED101,EE101),AC101) -> 0 | EG101: =0 -> 0 | EH101: =Geometria!$C$913 -> 0 | EI101: =IF(AND('Aberturas na Alma'!$M$18="NÃO DISPENSADO — furo deve ser verificado (cálculo abaixo)",OR(AND(B101>=('Aberturas na Alma'!$M$4-'Aberturas na Alma'!$M$7/2)/100,B101<=('Aberturas na Alma'!$M$4+'Aberturas na Alma'!$M$7/2)/100),ABS(B101-'Aberturas na Alma'!$M$4/100)<=Geometria!$L$29/4000)),IF(AY101="Reduzir",EG101,EH101),AZ101) -> 0 | EJ101: =0 -> 0 | EK101: =Geometria!$C$913 -> 0 | EL101: =IF(AND('Aberturas na Alma'!$M$18="NÃO DISPENSADO — furo deve ser verificado (cálculo abaixo)",OR(AND(B101>=('Aberturas na Alma'!$M$4-'Aberturas na Alma'!$M$7/2)/100,B101<=('Aberturas na Alma'!$M$4+'Aberturas na Alma'!$M$7/2)/100),ABS(B101-'Aberturas na Alma'!$M$4/100)<=Geometria!$L$29/4000)),IF(BV101="Reduzir",EJ101,EK101),BW101) -> 0 | EM101: =0 -> 0 | EN101: =Geometria!$C$913 -> 0 | EO101: =IF(AND('Aberturas na Alma'!$M$18="NÃO DISPENSADO — furo deve ser verificado (cálculo abaixo)",OR(AND(B101>=('Aberturas na Alma'!$M$4-'Aberturas na Alma'!$M$7/2)/100,B101<=('Aberturas na Alma'!$M$4+'Aberturas na Alma'!$M$7/2)/100),ABS(B101-'Aberturas na Alma'!$M$4/100)<=Geometria!$L$29/4000)),IF(CS101="Reduzir",EM101,EN101),CT101) -> 0 | EP101: =IF(AND(Y101<Geometria!$L$1409/100,OR(Geometria!$K$1409>0,Geometria!$K$1407>0)),"ESQ",IF(AND((Geometria!$L$29/100-Y101)<Geometria!$R$1409/100,OR(Geometria!$Q$1409>0,Geometria!$Q$1407>0)),"DIR","N/A")) -> N/A | EQ101: =IF(AND(Y101<Geometria!$L$1405/100,Geometria!$K$1405>0),"ESQ",IF(AND((Geometria!$L$29/100-Y101)<Geometria!$R$1405/100,Geometria!$Q$1405>0),"DIR","N/A")) -> ESQ | ER101: =IF(EP101="DIR",Geometria!$L$1470,Geometria!$L$1452) -> 1243.5596 | ES101: =IF(EP101="DIR",Geometria!$L$1471,Geometria!$L$1453) -> 233.16743 | ET101: =IF(EQ101="DIR",Geometria!$L$1472,Geometria!$L$1454) -> 621.77981 | EU101: =IF(EQ101="DIR",Geometria!$L$1473,Geometria!$L$1455) -> 177.20725 | EV101: =IF(AND(B101<Geometria!$L$1409/100,OR(Geometria!$K$1409>0,Geometria!$K$1407>0)),"ESQ",IF(AND((Geometria!$L$29/100-B101)<Geometria!$R$1409/100,OR(Geometria!$Q$1409>0,Geometria!$Q$1407>0)),"DIR","N/A")) -> N/A | EW101: =IF(AND(B101<Geometria!$L$1405/100,Geometria!$K$1405>0),"ESQ",IF(AND((Geometria!$L$29/100-B101)<Geometria!$R$1405/100,Geometria!$Q$1405>0),"DIR","N/A")) -> ESQ | EX101: =IF(EV101="DIR",Geometria!$L$1465,Geometria!$L$1447) -> 1499.8056 | EY101: =IF(EV101="DIR",Geometria!$L$1466,Geometria!$L$1448) -> 281.21355 | EZ101: =IF(EW101="DIR",Geometria!$L$1467,Geometria!$L$1449) -> 749.9028 | FA101: =IF(EW101="DIR",Geometria!$L$1468,Geometria!$L$1450) -> 213.7223
A102: =IF(OR(AND(B102<Geometria!$L$1405/100,Geometria!$K$1405>0),AND((Geometria!$L$29/100-B102)<Geometria!$R$1405/100,Geometria!$Q$1405>0)),"Sim","Não") -> Sim | B102: =Tensões!$C$63 -> 0.3925 | C102: =IF(OR(AND(B102<Geometria!$L$1409/100,OR(Geometria!$K$1409>0,Geometria!$K$1407>0)),AND((Geometria!$L$29/100-B102)<Geometria!$R$1409/100,OR(Geometria!$Q$1409>0,Geometria!$Q$1407>0))),"Sim","Não") -> Não | D102: σi,2 | E102: =IF(Geometria!$L$437<Geometria!$N$1307/100,"Reduzir","OK") -> Reduzir | F102: =IF(E102="Reduzir",G102,I102) -> 1922.4068 | G102: =-L102/(Geometria!$L$48/100^2)+M102/(Geometria!$L$52/100^3)-Geometria!$L$898/(Geometria!$L$52/100^3) -> 1922.4068 | H102: =(((Geometria!$L$326*(Geometria!$L$897*100))/Geometria!$N$1307)) -> 48.979188 | I102: =-(Geometria!$L$906-(Geometria!$L$906-EX102)*(1-(MIN(MIN(1,MAX(0,(B102-Geometria!$L$1409/100)/(Geometria!$N$1307/100))),MIN(1,MAX(0,((Geometria!$L$29/100-B102)-Geometria!$R$1409/100)/(Geometria!$N$1307/100))))))*(IF(OR(Geometria!$K$1409>0,Geometria!$K$1407>0,Geometria!$Q$1409>0,Geometria!$Q$1407>0),1,0))-(Geometria!$L$906-EZ102)*(1-(MIN(MIN(1,MAX(0,(B102-Geometria!$L$1405/100)/(Geometria!$N$1307/100))),MIN(1,MAX(0,((Geometria!$L$29/100-B102)-Geometria!$R$1405/100)/(Geometria!$N$1307/100))))))*(IF(OR(Geometria!$K$1405>0,Geometria!$K$1403>0,Geometria!$Q$1405>0,Geometria!$Q$1403>0),1,0)))/(Geometria!$L$48/100^2)+(Geometria!$L$907-(Geometria!$L$907-EY102)*(1-(MIN(MIN(1,MAX(0,(B102-Geometria!$L$1409/100)/(Geometria!$N$1307/100))),MIN(1,MAX(0,((Geometria!$L$29/100-B102)-Geometria!$R$1409/100)/(Geometria!$N$1307/100))))))*(IF(OR(Geometria!$K$1409>0,Geometria!$K$1407>0,Geometria!$Q$1409>0,Geometria!$Q$1407>0),1,0))-(Geometria!$L$907-FA102)*(1-(MIN(MIN(1,MAX(0,(B102-Geometria!$L$1405/100)/(Geometria!$N$1307/100))),MIN(1,MAX(0,((Geometria!$L$29/100-B102)-Geometria!$R$1405/100)/(Geometria!$N$1307/100))))))*(IF(OR(Geometria!$K$1405>0,Geometria!$K$1403>0,Geometria!$Q$1405>0,Geometria!$Q$1403>0),1,0)))/(Geometria!$L$52/100^3)-Geometria!$L$898/(Geometria!$L$52/100^3) -> 7274.3721 | L102: =(Geometria!$L$298-(Geometria!$L$298-IF(B102<Geometria!$L$1409/100,Geometria!$L$1442,Geometria!$L$1460))*(1-(MIN(MIN(1,MAX(0,(B102-Geometria!$L$1409/100)/(Geometria!$N$1307/100))),MIN(1,MAX(0,((Geometria!$L$29/100-B102)-Geometria!$R$1409/100)/(Geometria!$N$1307/100))))))*(IF(OR(Geometria!$K$1409>0,Geometria!$K$1407>0,Geometria!$Q$1409>0,Geometria!$Q$1407>0),1,0))-(Geometria!$L$298-IF(B102<Geometria!$L$1405/100,Geometria!$L$1444,Geometria!$L$1462))*(1-(MIN(MIN(1,MAX(0,(B102-Geometria!$L$1405/100)/(Geometria!$N$1307/100))),MIN(1,MAX(0,((Geometria!$L$29/100-B102)-Geometria!$R$1405/100)/(Geometria!$N$1307/100))))))*(IF(OR(Geometria!$K$1405>0,Geometria!$K$1403>0,Geometria!$Q$1405>0,Geometria!$Q$1403>0),1,0)))*H125+Geometria!$P$1429*H102 -> 229.17104 | M102: =(Geometria!$L$298-(Geometria!$L$298-IF(B102<Geometria!$L$1409/100,Geometria!$L$1442,Geometria!$L$1460))*(1-(MIN(MIN(1,MAX(0,(B102-Geometria!$L$1409/100)/(Geometria!$N$1307/100))),MIN(1,MAX(0,((Geometria!$L$29/100-B102)-Geometria!$R$1409/100)/(Geometria!$N$1307/100))))))*(IF(OR(Geometria!$K$1409>0,Geometria!$K$1407>0,Geometria!$Q$1409>0,Geometria!$Q$1407>0),1,0))-(Geometria!$L$298-IF(B102<Geometria!$L$1405/100,Geometria!$L$1444,Geometria!$L$1462))*(1-(MIN(MIN(1,MAX(0,(B102-Geometria!$L$1405/100)/(Geometria!$N$1307/100))),MIN(1,MAX(0,((Geometria!$L$29/100-B102)-Geometria!$R$1405/100)/(Geometria!$N$1307/100))))))*(IF(OR(Geometria!$K$1405>0,Geometria!$K$1403>0,Geometria!$Q$1405>0,Geometria!$Q$1403>0),1,0)))*H125*(Geometria!$L$299-(Geometria!$L$299-IF(B102<Geometria!$L$1409/100,Geometria!$L$1443,Geometria!$L$1461))*(1-(MIN(MIN(1,MAX(0,(B102-Geometria!$L$1409/100)/(Geometria!$N$1307/100))),MIN(1,MAX(0,((Geometria!$L$29/100-B102)-Geometria!$R$1409/100)/(Geometria!$N$1307/100))))))*(IF(OR(Geometria!$K$1409>0,Geometria!$K$1407>0,Geometria!$Q$1409>0,Geometria!$Q$1407>0),1,0))-(Geometria!$L$299-IF(B102<Geometria!$L$1405/100,Geometria!$L$1445,Geometria!$L$1463))*(1-(MIN(MIN(1,MAX(0,(B102-Geometria!$L$1405/100)/(Geometria!$N$1307/100))),MIN(1,MAX(0,((Geometria!$L$29/100-B102)-Geometria!$R$1405/100)/(Geometria!$N$1307/100))))))*(IF(OR(Geometria!$K$1405>0,Geometria!$K$1403>0,Geometria!$Q$1405>0,Geometria!$Q$1403>0),1,0)))/100-Geometria!$P$1429*H102*Geometria!$L$1438/100 -> 65.313748 | O102: =(IF(C102="Sim",IF(A102="Sim",$E$93,EX102),IF(A102="Sim",EZ102,Geometria!$L$906))) -> 749.9028 | P102: =(IF(C102="Sim",IF(A102="Sim",$E$94,EY102),IF(A102="Sim",FA102,Geometria!$L$907))) -> 213.7223 | R102: σi,2 | S102: =F102 -> 1922.4068 | T102: kN/m² | U102: =S102/1000 -> 1.9224068 | V102: MPa | W102: =W101 -> 0 | X102: =IF(OR(AND(Y102<Geometria!$L$1405/100,Geometria!$K$1405>0),AND((Geometria!$L$29/100-Y102)<Geometria!$R$1405/100,Geometria!$Q$1405>0)),"Sim","Não") -> Sim | Y102: =Geometria!$L$415 -> 0.3925 | Z102: =IF(OR(AND(Y102<Geometria!$L$1409/100,OR(Geometria!$K$1409>0,Geometria!$K$1407>0)),AND((Geometria!$L$29/100-Y102)<Geometria!$R$1409/100,OR(Geometria!$Q$1409>0,Geometria!$Q$1407>0))),"Sim","Não") -> Não | AA102: σi,2 | AB102: =IF(Geometria!$L$437<Geometria!$N$1307/100,"Reduzir","OK") -> Reduzir | AC102: =IF(AB102="Reduzir",AD102,AF102) -> -1066.7547 | AD102: =-(AI102/(Geometria!$L$48/100^2))+(AJ102/(Geometria!$L$52/100^3))-((Geometria!$L$416)/(Geometria!$L$52/100^3))-((Geometria!$L$427)/(Geometria!$M$52))-((Geometria!$L$76*Geometria!$L$438)/(Geometria!$M$52)) -> -1066.7547 | AE102: =(((Geometria!$N$369*(Geometria!$L$897*100))/Geometria!$N$1307)) -> 41.387508 | AF102: =-((Geometria!$L$373-(Geometria!$L$373-ER102)*(1-(MIN(MIN(1,MAX(0,(Y102-Geometria!$L$1409/100)/(Geometria!$N$1307/100))),MIN(1,MAX(0,((Geometria!$L$29/100-Y102)-Geometria!$R$1409/100)/(Geometria!$N$1307/100))))))*(IF(OR(Geometria!$K$1409>0,Geometria!$K$1407>0,Geometria!$Q$1409>0,Geometria!$Q$1407>0),1,0))-(Geometria!$L$373-ET102)*(1-(MIN(MIN(1,MAX(0,(Y102-Geometria!$L$1405/100)/(Geometria!$N$1307/100))),MIN(1,MAX(0,((Geometria!$L$29/100-Y102)-Geometria!$R$1405/100)/(Geometria!$N$1307/100))))))*(IF(OR(Geometria!$K$1405>0,Geometria!$K$1403>0,Geometria!$Q$1405>0,Geometria!$Q$1403>0),1,0))))/(Geometria!$L$48/100^2)+((Geometria!$L$374-(Geometria!$L$374-ES102)*(1-(MIN(MIN(1,MAX(0,(Y102-Geometria!$L$1409/100)/(Geometria!$N$1307/100))),MIN(1,MAX(0,((Geometria!$L$29/100-Y102)-Geometria!$R$1409/100)/(Geometria!$N$1307/100))))))*(IF(OR(Geometria!$K$1409>0,Geometria!$K$1407>0,Geometria!$Q$1409>0,Geometria!$Q$1407>0),1,0))-(Geometria!$L$374-EU102)*(1-(MIN(MIN(1,MAX(0,(Y102-Geometria!$L$1405/100)/(Geometria!$N$1307/100))),MIN(1,MAX(0,((Geometria!$L$29/100-Y102)-Geometria!$R$1405/100)/(Geometria!$N$1307/100))))))*(IF(OR(Geometria!$K$1405>0,Geometria!$K$1403>0,Geometria!$Q$1405>0,Geometria!$Q$1403>0),1,0))))/(Geometria!$L$52/100^3)-((Geometria!$L$416)/(Geometria!$L$52/100^3))-((Geometria!$L$427)/(Geometria!$M$52))-((Geometria!$L$76*Geometria!$L$438)/(Geometria!$M$52)) -> 3338.5252 | AI102: =(IF(Z102="Sim",IF(X102="Sim",IF(Y102<Geometria!$L$1405/100,Geometria!$L$1435,Geometria!$L$1476),IF(Y102<Geometria!$L$1409/100,Geometria!$L$1442,Geometria!$L$1460)),IF(X102="Sim",IF(Y102<Geometria!$L$1405/100,Geometria!$L$1444,Geometria!$L$1462),Geometria!$L$298)))*AE125+Geometria!$P$1429*AE102 -> 193.15799 | AJ102: =(IF(Z102="Sim",IF(X102="Sim",IF(Y102<Geometria!$L$1405/100,Geometria!$L$1435,Geometria!$L$1476),IF(Y102<Geometria!$L$1409/100,Geometria!$L$1442,Geometria!$L$1460)),IF(X102="Sim",IF(Y102<Geometria!$L$1405/100,Geometria!$L$1444,Geometria!$L$1462),Geometria!$L$298)))*AE125*(IF(Z102="Sim",IF(X102="Sim",IF(Y102<Geometria!$L$1405/100,Geometria!$L$1436,Geometria!$L$1484),IF(Y102<Geometria!$L$1409/100,Geometria!$L$1443,Geometria!$L$1461)),IF(X102="Sim",IF(Y102<Geometria!$L$1405/100,Geometria!$L$1445,Geometria!$L$1463),Geometria!$L$299)))/100-Geometria!$P$1429*AE102*Geometria!$L$1438/100 -> 55.050026 | AL102: =(IF(Z102="Sim",IF(X102="Sim",$AB$93,ER102),IF(X102="Sim",ET102,Geometria!$L$373))) -> 621.77981 | AM102: =(IF(Z102="Sim",IF(X102="Sim",$AB$94,ES102),IF(X102="Sim",EU102,Geometria!$L$374))) -> 177.20725 | AO102: σi,2 | AP102: =AC102 -> -1066.7547 | AQ102: kN/m² | AR102: =AP102/1000 -> -1.0667547 | AS102: MPa | AT102: =AT101 -> 0 | AU102: =IF(OR(AND(AV102<Geometria!$L$1405/100,Geometria!$K$1405>0),AND((Geometria!$L$29/100-AV102)<Geometria!$R$1405/100,Geometria!$Q$1405>0)),"Sim","Não") -> Sim | AV102: =Geometria!$L$415 -> 0.3925 | AW102: =IF(OR(AND(AV102<Geometria!$L$1409/100,OR(Geometria!$K$1409>0,Geometria!$K$1407>0)),AND((Geometria!$L$29/100-AV102)<Geometria!$R$1409/100,OR(Geometria!$Q$1409>0,Geometria!$Q$1407>0))),"Sim","Não") -> Não | AX102: σi,2 | AY102: =IF(Geometria!$L$437<Geometria!$N$1307/100,"Reduzir","OK") -> Reduzir | AZ102: =IF(AY102="Reduzir",BA102,BC102) -> -1066.7547 | BA102: =-(BF102/(Geometria!$L$48/100^2))+(BG102/(Geometria!$L$52/100^3))-((Geometria!$L$416)/(Geometria!$L$52/100^3))-((Geometria!$L$427)/(Geometria!$M$52))-((Geometria!$L$76*Geometria!$L$438)/(Geometria!$M$52)) -> -1066.7547 | BB102: =(((Geometria!$N$369*(Geometria!$L$897*100))/Geometria!$N$1307)) -> 41.387508 | BC102: =-((Geometria!$L$373-(Geometria!$L$373-ER102)*(1-(MIN(MIN(1,MAX(0,(AV102-Geometria!$L$1409/100)/(Geometria!$N$1307/100))),MIN(1,MAX(0,((Geometria!$L$29/100-AV102)-Geometria!$R$1409/100)/(Geometria!$N$1307/100))))))*(IF(OR(Geometria!$K$1409>0,Geometria!$K$1407>0,Geometria!$Q$1409>0,Geometria!$Q$1407>0),1,0))-(Geometria!$L$373-ET102)*(1-(MIN(MIN(1,MAX(0,(AV102-Geometria!$L$1405/100)/(Geometria!$N$1307/100))),MIN(1,MAX(0,((Geometria!$L$29/100-AV102)-Geometria!$R$1405/100)/(Geometria!$N$1307/100))))))*(IF(OR(Geometria!$K$1405>0,Geometria!$K$1403>0,Geometria!$Q$1405>0,Geometria!$Q$1403>0),1,0))))/(Geometria!$L$48/100^2)+((Geometria!$L$374-(Geometria!$L$374-ES102)*(1-(MIN(MIN(1,MAX(0,(AV102-Geometria!$L$1409/100)/(Geometria!$N$1307/100))),MIN(1,MAX(0,((Geometria!$L$29/100-AV102)-Geometria!$R$1409/100)/(Geometria!$N$1307/100))))))*(IF(OR(Geometria!$K$1409>0,Geometria!$K$1407>0,Geometria!$Q$1409>0,Geometria!$Q$1407>0),1,0))-(Geometria!$L$374-EU102)*(1-(MIN(MIN(1,MAX(0,(AV102-Geometria!$L$1405/100)/(Geometria!$N$1307/100))),MIN(1,MAX(0,((Geometria!$L$29/100-AV102)-Geometria!$R$1405/100)/(Geometria!$N$1307/100))))))*(IF(OR(Geometria!$K$1405>0,Geometria!$K$1403>0,Geometria!$Q$1405>0,Geometria!$Q$1403>0),1,0))))/(Geometria!$L$52/100^3)-((Geometria!$L$416)/(Geometria!$L$52/100^3))-((Geometria!$L$427)/(Geometria!$M$52)) -> 3338.5271 | BF102: =(Geometria!$L$298-(Geometria!$L$298-IF(AV102<Geometria!$L$1409/100,Geometria!$L$1442,Geometria!$L$1460))*(1-(MIN(MIN(1,MAX(0,(AV102-Geometria!$L$1409/100)/(Geometria!$N$1307/100))),MIN(1,MAX(0,((Geometria!$L$29/100-AV102)-Geometria!$R$1409/100)/(Geometria!$N$1307/100))))))*(IF(OR(Geometria!$K$1409>0,Geometria!$K$1407>0,Geometria!$Q$1409>0,Geometria!$Q$1407>0),1,0))-(Geometria!$L$298-IF(AV102<Geometria!$L$1405/100,Geometria!$L$1444,Geometria!$L$1462))*(1-(MIN(MIN(1,MAX(0,(AV102-Geometria!$L$1405/100)/(Geometria!$N$1307/100))),MIN(1,MAX(0,((Geometria!$L$29/100-AV102)-Geometria!$R$1405/100)/(Geometria!$N$1307/100))))))*(IF(OR(Geometria!$K$1405>0,Geometria!$K$1403>0,Geometria!$Q$1405>0,Geometria!$Q$1403>0),1,0)))*BB125+Geometria!$P$1429*BB102 -> 193.15799 | BG102: =(Geometria!$L$298-(Geometria!$L$298-IF(AV102<Geometria!$L$1409/100,Geometria!$L$1442,Geometria!$L$1460))*(1-(MIN(MIN(1,MAX(0,(AV102-Geometria!$L$1409/100)/(Geometria!$N$1307/100))),MIN(1,MAX(0,((Geometria!$L$29/100-AV102)-Geometria!$R$1409/100)/(Geometria!$N$1307/100))))))*(IF(OR(Geometria!$K$1409>0,Geometria!$K$1407>0,Geometria!$Q$1409>0,Geometria!$Q$1407>0),1,0))-(Geometria!$L$298-IF(AV102<Geometria!$L$1405/100,Geometria!$L$1444,Geometria!$L$1462))*(1-(MIN(MIN(1,MAX(0,(AV102-Geometria!$L$1405/100)/(Geometria!$N$1307/100))),MIN(1,MAX(0,((Geometria!$L$29/100-AV102)-Geometria!$R$1405/100)/(Geometria!$N$1307/100))))))*(IF(OR(Geometria!$K$1405>0,Geometria!$K$1403>0,Geometria!$Q$1405>0,Geometria!$Q$1403>0),1,0)))*BB125*(Geometria!$L$299-(Geometria!$L$299-IF(AV102<Geometria!$L$1409/100,Geometria!$L$1443,Geometria!$L$1461))*(1-(MIN(MIN(1,MAX(0,(AV102-Geometria!$L$1409/100)/(Geometria!$N$1307/100))),MIN(1,MAX(0,((Geometria!$L$29/100-AV102)-Geometria!$R$1409/100)/(Geometria!$N$1307/100))))))*(IF(OR(Geometria!$K$1409>0,Geometria!$K$1407>0,Geometria!$Q$1409>0,Geometria!$Q$1407>0),1,0))-(Geometria!$L$299-IF(AV102<Geometria!$L$1405/100,Geometria!$L$1445,Geometria!$L$1463))*(1-(MIN(MIN(1,MAX(0,(AV102-Geometria!$L$1405/100)/(Geometria!$N$1307/100))),MIN(1,MAX(0,((Geometria!$L$29/100-AV102)-Geometria!$R$1405/100)/(Geometria!$N$1307/100))))))*(IF(OR(Geometria!$K$1405>0,Geometria!$K$1403>0,Geometria!$Q$1405>0,Geometria!$Q$1403>0),1,0)))/100-Geometria!$P$1429*BB102*Geometria!$L$1438/100 -> 55.050026 | BI102: =(IF(AW102="Sim",IF(AU102="Sim",$AB$93,ER102),IF(AU102="Sim",ET102,Geometria!$L$373))) -> 621.77981 | BJ102: =(IF(AW102="Sim",IF(AU102="Sim",$AB$94,ES102),IF(AU102="Sim",EU102,Geometria!$L$374))) -> 177.20725 | BL102: σi,2 | BM102: =AZ102 -> -1066.7547 | BN102: kN/m² | BO102: =BM102/1000 -> -1.0667547 | BP102: MPa | BQ102: =BQ101 -> 0 | BR102: =IF(OR(AND(BS102<Geometria!$L$1405/100,Geometria!$K$1405>0),AND((Geometria!$L$29/100-BS102)<Geometria!$R$1405/100,Geometria!$Q$1405>0)),"Sim","Não") -> Sim | BS102: =Geometria!$L$415 -> 0.3925 | BT102: =IF(OR(AND(BS102<Geometria!$L$1409/100,OR(Geometria!$K$1409>0,Geometria!$K$1407>0)),AND((Geometria!$L$29/100-BS102)<Geometria!$R$1409/100,OR(Geometria!$Q$1409>0,Geometria!$Q$1407>0))),"Sim","Não") -> Não | BU102: σi,2 | BV102: =IF(Geometria!$L$437<Geometria!$N$1307/100,"Reduzir","OK") -> Reduzir | BW102: =IF(BV102="Reduzir",BX102,BZ102) -> -1066.7547 | BX102: =-(CC102/(Geometria!$L$48/100^2))+(CD102/(Geometria!$L$52/100^3))-((Geometria!$L$416)/(Geometria!$L$52/100^3))-((Geometria!$L$427)/(Geometria!$M$52))-((Geometria!$L$76*Geometria!$L$438)/(Geometria!$M$52)) -> -1066.7547 | BY102: =(((Geometria!$N$369*(Geometria!$L$897*100))/Geometria!$N$1307)) -> 41.387508 | BZ102: =-((Geometria!$L$373-(Geometria!$L$373-ER102)*(1-(MIN(MIN(1,MAX(0,(BS102-Geometria!$L$1409/100)/(Geometria!$N$1307/100))),MIN(1,MAX(0,((Geometria!$L$29/100-BS102)-Geometria!$R$1409/100)/(Geometria!$N$1307/100))))))*(IF(OR(Geometria!$K$1409>0,Geometria!$K$1407>0,Geometria!$Q$1409>0,Geometria!$Q$1407>0),1,0))-(Geometria!$L$373-ET102)*(1-(MIN(MIN(1,MAX(0,(BS102-Geometria!$L$1405/100)/(Geometria!$N$1307/100))),MIN(1,MAX(0,((Geometria!$L$29/100-BS102)-Geometria!$R$1405/100)/(Geometria!$N$1307/100))))))*(IF(OR(Geometria!$K$1405>0,Geometria!$K$1403>0,Geometria!$Q$1405>0,Geometria!$Q$1403>0),1,0))))/(Geometria!$L$48/100^2)+((Geometria!$L$374-(Geometria!$L$374-ES102)*(1-(MIN(MIN(1,MAX(0,(BS102-Geometria!$L$1409/100)/(Geometria!$N$1307/100))),MIN(1,MAX(0,((Geometria!$L$29/100-BS102)-Geometria!$R$1409/100)/(Geometria!$N$1307/100))))))*(IF(OR(Geometria!$K$1409>0,Geometria!$K$1407>0,Geometria!$Q$1409>0,Geometria!$Q$1407>0),1,0))-(Geometria!$L$374-EU102)*(1-(MIN(MIN(1,MAX(0,(BS102-Geometria!$L$1405/100)/(Geometria!$N$1307/100))),MIN(1,MAX(0,((Geometria!$L$29/100-BS102)-Geometria!$R$1405/100)/(Geometria!$N$1307/100))))))*(IF(OR(Geometria!$K$1405>0,Geometria!$K$1403>0,Geometria!$Q$1405>0,Geometria!$Q$1403>0),1,0))))/(Geometria!$L$52/100^3)-((Geometria!$L$673)/(Geometria!$L$52/100^3))-((Geometria!$L$684)/(Geometria!$M$52))-((Geometria!$L$77*Geometria!$L$695)/(Geometria!$M$52)) -> 3338.5258 | CC102: =(Geometria!$L$298-(Geometria!$L$298-IF(BS102<Geometria!$L$1409/100,Geometria!$L$1442,Geometria!$L$1460))*(1-(MIN(MIN(1,MAX(0,(BS102-Geometria!$L$1409/100)/(Geometria!$N$1307/100))),MIN(1,MAX(0,((Geometria!$L$29/100-BS102)-Geometria!$R$1409/100)/(Geometria!$N$1307/100))))))*(IF(OR(Geometria!$K$1409>0,Geometria!$K$1407>0,Geometria!$Q$1409>0,Geometria!$Q$1407>0),1,0))-(Geometria!$L$298-IF(BS102<Geometria!$L$1405/100,Geometria!$L$1444,Geometria!$L$1462))*(1-(MIN(MIN(1,MAX(0,(BS102-Geometria!$L$1405/100)/(Geometria!$N$1307/100))),MIN(1,MAX(0,((Geometria!$L$29/100-BS102)-Geometria!$R$1405/100)/(Geometria!$N$1307/100))))))*(IF(OR(Geometria!$K$1405>0,Geometria!$K$1403>0,Geometria!$Q$1405>0,Geometria!$Q$1403>0),1,0)))*BY125+Geometria!$P$1429*BY102 -> 193.15799 | CD102: =(Geometria!$L$298-(Geometria!$L$298-IF(BS102<Geometria!$L$1409/100,Geometria!$L$1442,Geometria!$L$1460))*(1-(MIN(MIN(1,MAX(0,(BS102-Geometria!$L$1409/100)/(Geometria!$N$1307/100))),MIN(1,MAX(0,((Geometria!$L$29/100-BS102)-Geometria!$R$1409/100)/(Geometria!$N$1307/100))))))*(IF(OR(Geometria!$K$1409>0,Geometria!$K$1407>0,Geometria!$Q$1409>0,Geometria!$Q$1407>0),1,0))-(Geometria!$L$298-IF(BS102<Geometria!$L$1405/100,Geometria!$L$1444,Geometria!$L$1462))*(1-(MIN(MIN(1,MAX(0,(BS102-Geometria!$L$1405/100)/(Geometria!$N$1307/100))),MIN(1,MAX(0,((Geometria!$L$29/100-BS102)-Geometria!$R$1405/100)/(Geometria!$N$1307/100))))))*(IF(OR(Geometria!$K$1405>0,Geometria!$K$1403>0,Geometria!$Q$1405>0,Geometria!$Q$1403>0),1,0)))*BY125*(Geometria!$L$299-(Geometria!$L$299-IF(BS102<Geometria!$L$1409/100,Geometria!$L$1443,Geometria!$L$1461))*(1-(MIN(MIN(1,MAX(0,(BS102-Geometria!$L$1409/100)/(Geometria!$N$1307/100))),MIN(1,MAX(0,((Geometria!$L$29/100-BS102)-Geometria!$R$1409/100)/(Geometria!$N$1307/100))))))*(IF(OR(Geometria!$K$1409>0,Geometria!$K$1407>0,Geometria!$Q$1409>0,Geometria!$Q$1407>0),1,0))-(Geometria!$L$299-IF(BS102<Geometria!$L$1405/100,Geometria!$L$1445,Geometria!$L$1463))*(1-(MIN(MIN(1,MAX(0,(BS102-Geometria!$L$1405/100)/(Geometria!$N$1307/100))),MIN(1,MAX(0,((Geometria!$L$29/100-BS102)-Geometria!$R$1405/100)/(Geometria!$N$1307/100))))))*(IF(OR(Geometria!$K$1405>0,Geometria!$K$1403>0,Geometria!$Q$1405>0,Geometria!$Q$1403>0),1,0)))/100-Geometria!$P$1429*BY102*Geometria!$L$1438/100 -> 55.050026 | CF102: =(IF(BT102="Sim",IF(BR102="Sim",$AB$93,ER102),IF(BR102="Sim",ET102,Geometria!$L$373))) -> 621.77981 | CG102: =(IF(BT102="Sim",IF(BR102="Sim",$AB$94,ES102),IF(BR102="Sim",EU102,Geometria!$L$374))) -> 177.20725 | CI102: σi,2 | CJ102: =BW102 -> -1066.7547 | CK102: kN/m² | CL102: =CJ102/1000 -> -1.0667547 | CM102: MPa | CN102: =CN101 -> 0 | CO102: =IF(OR(AND(CP102<Geometria!$L$1405/100,Geometria!$K$1405>0),AND((Geometria!$L$29/100-CP102)<Geometria!$R$1405/100,Geometria!$Q$1405>0)),"Sim","Não") -> Sim | CP102: =Geometria!$L$415 -> 0.3925 | CQ102: =IF(OR(AND(CP102<Geometria!$L$1409/100,OR(Geometria!$K$1409>0,Geometria!$K$1407>0)),AND((Geometria!$L$29/100-CP102)<Geometria!$R$1409/100,OR(Geometria!$Q$1409>0,Geometria!$Q$1407>0))),"Sim","Não") -> Não | CR102: σi,2 | CS102: =IF(Geometria!$L$437<Geometria!$N$1307/100,"Reduzir","OK") -> Reduzir | CT102: =IF(CS102="Reduzir",CU102,CW102) -> -1066.7547 | CU102: =-(CZ102/(Geometria!$L$48/100^2))+(DA102/(Geometria!$L$52/100^3))-((Geometria!$L$416)/(Geometria!$L$52/100^3))-((Geometria!$L$427)/(Geometria!$M$52))-((Geometria!$L$76*Geometria!$L$438)/(Geometria!$M$52)) -> -1066.7547 | CV102: =(((Geometria!$N$369*(Geometria!$L$897*100))/Geometria!$N$1307)) -> 41.387508 | CW102: =-((Geometria!$L$373-(Geometria!$L$373-ER102)*(1-(MIN(MIN(1,MAX(0,(CP102-Geometria!$L$1409/100)/(Geometria!$N$1307/100))),MIN(1,MAX(0,((Geometria!$L$29/100-CP102)-Geometria!$R$1409/100)/(Geometria!$N$1307/100))))))*(IF(OR(Geometria!$K$1409>0,Geometria!$K$1407>0,Geometria!$Q$1409>0,Geometria!$Q$1407>0),1,0))-(Geometria!$L$373-ET102)*(1-(MIN(MIN(1,MAX(0,(CP102-Geometria!$L$1405/100)/(Geometria!$N$1307/100))),MIN(1,MAX(0,((Geometria!$L$29/100-CP102)-Geometria!$R$1405/100)/(Geometria!$N$1307/100))))))*(IF(OR(Geometria!$K$1405>0,Geometria!$K$1403>0,Geometria!$Q$1405>0,Geometria!$Q$1403>0),1,0))))/(Geometria!$L$48/100^2)+((Geometria!$L$374-(Geometria!$L$374-ES102)*(1-(MIN(MIN(1,MAX(0,(CP102-Geometria!$L$1409/100)/(Geometria!$N$1307/100))),MIN(1,MAX(0,((Geometria!$L$29/100-CP102)-Geometria!$R$1409/100)/(Geometria!$N$1307/100))))))*(IF(OR(Geometria!$K$1409>0,Geometria!$K$1407>0,Geometria!$Q$1409>0,Geometria!$Q$1407>0),1,0))-(Geometria!$L$374-EU102)*(1-(MIN(MIN(1,MAX(0,(CP102-Geometria!$L$1405/100)/(Geometria!$N$1307/100))),MIN(1,MAX(0,((Geometria!$L$29/100-CP102)-Geometria!$R$1405/100)/(Geometria!$N$1307/100))))))*(IF(OR(Geometria!$K$1405>0,Geometria!$K$1403>0,Geometria!$Q$1405>0,Geometria!$Q$1403>0),1,0))))/(Geometria!$L$52/100^3)-((Geometria!$L$673)/(Geometria!$L$52/100^3))-((Geometria!$L$684)/(Geometria!$M$52)) -> 3338.5271 | CZ102: =(IF(CQ102="Sim",IF(CO102="Sim",IF(CP102<Geometria!$L$1405/100,Geometria!$L$1435,Geometria!$L$1476),IF(CP102<Geometria!$L$1409/100,Geometria!$L$1442,Geometria!$L$1460)),IF(CO102="Sim",IF(CP102<Geometria!$L$1405/100,Geometria!$L$1444,Geometria!$L$1462),Geometria!$L$298)))*CV125+Geometria!$P$1429*CV102 -> 193.15799 | DA102: =(IF(CQ102="Sim",IF(CO102="Sim",IF(CP102<Geometria!$L$1405/100,Geometria!$L$1435,Geometria!$L$1476),IF(CP102<Geometria!$L$1409/100,Geometria!$L$1442,Geometria!$L$1460)),IF(CO102="Sim",IF(CP102<Geometria!$L$1405/100,Geometria!$L$1444,Geometria!$L$1462),Geometria!$L$298)))*CV125*(IF(CQ102="Sim",IF(CO102="Sim",IF(CP102<Geometria!$L$1405/100,Geometria!$L$1436,Geometria!$L$1484),IF(CP102<Geometria!$L$1409/100,Geometria!$L$1443,Geometria!$L$1461)),IF(CO102="Sim",IF(CP102<Geometria!$L$1405/100,Geometria!$L$1445,Geometria!$L$1463),Geometria!$L$299)))/100-Geometria!$P$1429*CV102*Geometria!$L$1438/100 -> 55.050026 | DC102: =(IF(CQ102="Sim",IF(CO102="Sim",$AB$93,ER102),IF(CO102="Sim",ET102,Geometria!$L$373))) -> 621.77981 | DD102: =(IF(CQ102="Sim",IF(CO102="Sim",$AB$94,ES102),IF(CO102="Sim",EU102,Geometria!$L$374))) -> 177.20725 | DF102: σi,2 | DG102: =CT102 -> -1066.7547 | DH102: kN/m² | DI102: =DG102/1000 -> -1.0667547 | DJ102: MPa | DK102: =DK101 -> 0 | EA102: =-L102/('Aberturas na Alma'!$M$112/100^2)+M102/('Aberturas na Alma'!$M$119/100^3)-Geometria!$L$898/('Aberturas na Alma'!$M$119/100^3) -> 1635.9302 | EB102: =-(IF(C102="Sim",IF(A102="Sim",$E$93,EX102),IF(A102="Sim",EZ102,Geometria!$L$906)))/('Aberturas na Alma'!$M$112/100^2)+(IF(C102="Sim",IF(A102="Sim",$E$94,EY102),IF(A102="Sim",FA102,Geometria!$L$907)))/('Aberturas na Alma'!$M$119/100^3)-Geometria!$L$898/('Aberturas na Alma'!$M$119/100^3) -> 6379.4102 | EC102: =IF(AND('Aberturas na Alma'!$M$18="NÃO DISPENSADO — furo deve ser verificado (cálculo abaixo)",OR(AND(B102>=('Aberturas na Alma'!$M$4-'Aberturas na Alma'!$M$7/2)/100,B102<=('Aberturas na Alma'!$M$4+'Aberturas na Alma'!$M$7/2)/100),ABS(B102-'Aberturas na Alma'!$M$4/100)<=Geometria!$L$29/4000)),IF(E102="Reduzir",EA102,EB102),F102) -> 1922.4068 | ED102: =-(AI102/('Aberturas na Alma'!$M$112/100^2))+(AJ102/('Aberturas na Alma'!$M$119/100^3))-((Geometria!$L$416)/('Aberturas na Alma'!$M$119/100^3))-((Geometria!$L$427)/('Aberturas na Alma'!$M$119/100^3))-((Geometria!$L$76*Geometria!$L$438)/('Aberturas na Alma'!$M$119/100^3)) -> -9346.0415 | EE102: =-((IF(Z102="Sim",IF(X102="Sim",$AB$93,ER102),IF(X102="Sim",ET102,Geometria!$L$373)))/('Aberturas na Alma'!$M$112/100^2))+((IF(Z102="Sim",IF(X102="Sim",$AB$94,ES102),IF(X102="Sim",EU102,Geometria!$L$374)))/('Aberturas na Alma'!$M$119/100^3))-((Geometria!$L$416)/('Aberturas na Alma'!$M$119/100^3))-((Geometria!$L$427)/('Aberturas na Alma'!$M$119/100^3))-((Geometria!$L$76*Geometria!$L$438)/('Aberturas na Alma'!$M$119/100^3)) -> -5441.6147 | EF102: =IF(AND('Aberturas na Alma'!$M$18="NÃO DISPENSADO — furo deve ser verificado (cálculo abaixo)",OR(AND(B102>=('Aberturas na Alma'!$M$4-'Aberturas na Alma'!$M$7/2)/100,B102<=('Aberturas na Alma'!$M$4+'Aberturas na Alma'!$M$7/2)/100),ABS(B102-'Aberturas na Alma'!$M$4/100)<=Geometria!$L$29/4000)),IF(AB102="Reduzir",ED102,EE102),AC102) -> -1066.7547 | EG102: =-(BF102/('Aberturas na Alma'!$M$112/100^2))+(BG102/('Aberturas na Alma'!$M$119/100^3))-((Geometria!$L$416)/('Aberturas na Alma'!$M$119/100^3))-((Geometria!$L$427)/('Aberturas na Alma'!$M$119/100^3))-((Geometria!$L$76*Geometria!$L$438)/('Aberturas na Alma'!$M$119/100^3)) -> -9346.0415 | EH102: =-((IF(AW102="Sim",IF(AU102="Sim",$AB$93,ER102),IF(AU102="Sim",ET102,Geometria!$L$373)))/('Aberturas na Alma'!$M$112/100^2))+((IF(AW102="Sim",IF(AU102="Sim",$AB$94,ES102),IF(AU102="Sim",EU102,Geometria!$L$374)))/('Aberturas na Alma'!$M$119/100^3))-((Geometria!$L$416)/('Aberturas na Alma'!$M$119/100^3))-((Geometria!$L$427)/('Aberturas na Alma'!$M$119/100^3)) -> 1985.1317 | EI102: =IF(AND('Aberturas na Alma'!$M$18="NÃO DISPENSADO — furo deve ser verificado (cálculo abaixo)",OR(AND(B102>=('Aberturas na Alma'!$M$4-'Aberturas na Alma'!$M$7/2)/100,B102<=('Aberturas na Alma'!$M$4+'Aberturas na Alma'!$M$7/2)/100),ABS(B102-'Aberturas na Alma'!$M$4/100)<=Geometria!$L$29/4000)),IF(AY102="Reduzir",EG102,EH102),AZ102) -> -1066.7547 | EJ102: =-(CC102/('Aberturas na Alma'!$M$112/100^2))+(CD102/('Aberturas na Alma'!$M$119/100^3))-((Geometria!$L$416)/('Aberturas na Alma'!$M$119/100^3))-((Geometria!$L$427)/('Aberturas na Alma'!$M$119/100^3))-((Geometria!$L$76*Geometria!$L$438)/('Aberturas na Alma'!$M$119/100^3)) -> -9346.0415 | EK102: =-((IF(BT102="Sim",IF(BR102="Sim",$AB$93,ER102),IF(BR102="Sim",ET102,Geometria!$L$373)))/('Aberturas na Alma'!$M$112/100^2))+((IF(BT102="Sim",IF(BR102="Sim",$AB$94,ES102),IF(BR102="Sim",EU102,Geometria!$L$374)))/('Aberturas na Alma'!$M$119/100^3))-((Geometria!$L$673)/('Aberturas na Alma'!$M$119/100^3))-((Geometria!$L$684)/('Aberturas na Alma'!$M$119/100^3))-((Geometria!$L$77*Geometria!$L$695)/('Aberturas na Alma'!$M$119/100^3)) -> -2966.0325 | EL102: =IF(AND('Aberturas na Alma'!$M$18="NÃO DISPENSADO — furo deve ser verificado (cálculo abaixo)",OR(AND(B102>=('Aberturas na Alma'!$M$4-'Aberturas na Alma'!$M$7/2)/100,B102<=('Aberturas na Alma'!$M$4+'Aberturas na Alma'!$M$7/2)/100),ABS(B102-'Aberturas na Alma'!$M$4/100)<=Geometria!$L$29/4000)),IF(BV102="Reduzir",EJ102,EK102),BW102) -> -1066.7547 | EM102: =-(CZ102/('Aberturas na Alma'!$M$112/100^2))+(DA102/('Aberturas na Alma'!$M$119/100^3))-((Geometria!$L$416)/('Aberturas na Alma'!$M$119/100^3))-((Geometria!$L$427)/('Aberturas na Alma'!$M$119/100^3))-((Geometria!$L$76*Geometria!$L$438)/('Aberturas na Alma'!$M$119/100^3)) -> -9346.0415 | EN102: =-((IF(CQ102="Sim",IF(CO102="Sim",$AB$93,ER102),IF(CO102="Sim",ET102,Geometria!$L$373)))/('Aberturas na Alma'!$M$112/100^2))+((IF(CQ102="Sim",IF(CO102="Sim",$AB$94,ES102),IF(CO102="Sim",EU102,Geometria!$L$374)))/('Aberturas na Alma'!$M$119/100^3))-((Geometria!$L$673)/('Aberturas na Alma'!$M$119/100^3))-((Geometria!$L$684)/('Aberturas na Alma'!$M$119/100^3)) -> 1985.1317 | EO102: =IF(AND('Aberturas na Alma'!$M$18="NÃO DISPENSADO — furo deve ser verificado (cálculo abaixo)",OR(AND(B102>=('Aberturas na Alma'!$M$4-'Aberturas na Alma'!$M$7/2)/100,B102<=('Aberturas na Alma'!$M$4+'Aberturas na Alma'!$M$7/2)/100),ABS(B102-'Aberturas na Alma'!$M$4/100)<=Geometria!$L$29/4000)),IF(CS102="Reduzir",EM102,EN102),CT102) -> -1066.7547 | EP102: =IF(AND(Y102<Geometria!$L$1409/100,OR(Geometria!$K$1409>0,Geometria!$K$1407>0)),"ESQ",IF(AND((Geometria!$L$29/100-Y102)<Geometria!$R$1409/100,OR(Geometria!$Q$1409>0,Geometria!$Q$1407>0)),"DIR","N/A")) -> N/A | EQ102: =IF(AND(Y102<Geometria!$L$1405/100,Geometria!$K$1405>0),"ESQ",IF(AND((Geometria!$L$29/100-Y102)<Geometria!$R$1405/100,Geometria!$Q$1405>0),"DIR","N/A")) -> ESQ | ER102: =IF(EP102="DIR",Geometria!$L$1470,Geometria!$L$1452) -> 1243.5596 | ES102: =IF(EP102="DIR",Geometria!$L$1471,Geometria!$L$1453) -> 233.16743 | ET102: =IF(EQ102="DIR",Geometria!$L$1472,Geometria!$L$1454) -> 621.77981 | EU102: =IF(EQ102="DIR",Geometria!$L$1473,Geometria!$L$1455) -> 177.20725 | EV102: =IF(AND(B102<Geometria!$L$1409/100,OR(Geometria!$K$1409>0,Geometria!$K$1407>0)),"ESQ",IF(AND((Geometria!$L$29/100-B102)<Geometria!$R$1409/100,OR(Geometria!$Q$1409>0,Geometria!$Q$1407>0)),"DIR","N/A")) -> N/A | EW102: =IF(AND(B102<Geometria!$L$1405/100,Geometria!$K$1405>0),"ESQ",IF(AND((Geometria!$L$29/100-B102)<Geometria!$R$1405/100,Geometria!$Q$1405>0),"DIR","N/A")) -> ESQ | EX102: =IF(EV102="DIR",Geometria!$L$1465,Geometria!$L$1447) -> 1499.8056 | EY102: =IF(EV102="DIR",Geometria!$L$1466,Geometria!$L$1448) -> 281.21355 | EZ102: =IF(EW102="DIR",Geometria!$L$1467,Geometria!$L$1449) -> 749.9028 | FA102: =IF(EW102="DIR",Geometria!$L$1468,Geometria!$L$1450) -> 213.7223
A103: =IF(OR(AND(B103<Geometria!$L$1405/100,Geometria!$K$1405>0),AND((Geometria!$L$29/100-B103)<Geometria!$R$1405/100,Geometria!$Q$1405>0)),"Sim","Não") -> Sim | B103: =Tensões!$D$63 -> 0.785 | C103: =IF(OR(AND(B103<Geometria!$L$1409/100,OR(Geometria!$K$1409>0,Geometria!$K$1407>0)),AND((Geometria!$L$29/100-B103)<Geometria!$R$1409/100,OR(Geometria!$Q$1409>0,Geometria!$Q$1407>0))),"Sim","Não") -> Não | D103: σi,3 | E103: =IF(Geometria!$M$437<Geometria!$N$1307/100,"Reduzir","OK") -> Reduzir | F103: =IF(E103="Reduzir",G103,I103) -> 4277.7759 | G103: =-L103/(Geometria!$L$48/100^2)+M103/(Geometria!$L$52/100^3)-Geometria!$L$898/(Geometria!$L$52/100^3) -> 4277.7759 | H103: =((Geometria!$L$326*(Geometria!$M$897*100))/Geometria!$N$1307) -> 97.958377 | I103: =-(Geometria!$L$906-(Geometria!$L$906-EX103)*(1-(MIN(MIN(1,MAX(0,(B103-Geometria!$L$1409/100)/(Geometria!$N$1307/100))),MIN(1,MAX(0,((Geometria!$L$29/100-B103)-Geometria!$R$1409/100)/(Geometria!$N$1307/100))))))*(IF(OR(Geometria!$K$1409>0,Geometria!$K$1407>0,Geometria!$Q$1409>0,Geometria!$Q$1407>0),1,0))-(Geometria!$L$906-EZ103)*(1-(MIN(MIN(1,MAX(0,(B103-Geometria!$L$1405/100)/(Geometria!$N$1307/100))),MIN(1,MAX(0,((Geometria!$L$29/100-B103)-Geometria!$R$1405/100)/(Geometria!$N$1307/100))))))*(IF(OR(Geometria!$K$1405>0,Geometria!$K$1403>0,Geometria!$Q$1405>0,Geometria!$Q$1403>0),1,0)))/(Geometria!$L$48/100^2)+(Geometria!$L$907-(Geometria!$L$907-EY103)*(1-(MIN(MIN(1,MAX(0,(B103-Geometria!$L$1409/100)/(Geometria!$N$1307/100))),MIN(1,MAX(0,((Geometria!$L$29/100-B103)-Geometria!$R$1409/100)/(Geometria!$N$1307/100))))))*(IF(OR(Geometria!$K$1409>0,Geometria!$K$1407>0,Geometria!$Q$1409>0,Geometria!$Q$1407>0),1,0))-(Geometria!$L$907-FA103)*(1-(MIN(MIN(1,MAX(0,(B103-Geometria!$L$1405/100)/(Geometria!$N$1307/100))),MIN(1,MAX(0,((Geometria!$L$29/100-B103)-Geometria!$R$1405/100)/(Geometria!$N$1307/100))))))*(IF(OR(Geometria!$K$1405>0,Geometria!$K$1403>0,Geometria!$Q$1405>0,Geometria!$Q$1403>0),1,0)))/(Geometria!$L$52/100^3)-Geometria!$M$898/(Geometria!$L$52/100^3) -> 6886.9848 | L103: =(Geometria!$L$298-(Geometria!$L$298-IF(B103<Geometria!$L$1409/100,Geometria!$L$1442,Geometria!$L$1460))*(1-(MIN(MIN(1,MAX(0,(B103-Geometria!$L$1409/100)/(Geometria!$N$1307/100))),MIN(1,MAX(0,((Geometria!$L$29/100-B103)-Geometria!$R$1409/100)/(Geometria!$N$1307/100))))))*(IF(OR(Geometria!$K$1409>0,Geometria!$K$1407>0,Geometria!$Q$1409>0,Geometria!$Q$1407>0),1,0))-(Geometria!$L$298-IF(B103<Geometria!$L$1405/100,Geometria!$L$1444,Geometria!$L$1462))*(1-(MIN(MIN(1,MAX(0,(B103-Geometria!$L$1405/100)/(Geometria!$N$1307/100))),MIN(1,MAX(0,((Geometria!$L$29/100-B103)-Geometria!$R$1405/100)/(Geometria!$N$1307/100))))))*(IF(OR(Geometria!$K$1405>0,Geometria!$K$1403>0,Geometria!$Q$1405>0,Geometria!$Q$1403>0),1,0)))*H126+Geometria!$P$1429*H103 -> 458.34209 | M103: =(Geometria!$L$298-(Geometria!$L$298-IF(B103<Geometria!$L$1409/100,Geometria!$L$1442,Geometria!$L$1460))*(1-(MIN(MIN(1,MAX(0,(B103-Geometria!$L$1409/100)/(Geometria!$N$1307/100))),MIN(1,MAX(0,((Geometria!$L$29/100-B103)-Geometria!$R$1409/100)/(Geometria!$N$1307/100))))))*(IF(OR(Geometria!$K$1409>0,Geometria!$K$1407>0,Geometria!$Q$1409>0,Geometria!$Q$1407>0),1,0))-(Geometria!$L$298-IF(B103<Geometria!$L$1405/100,Geometria!$L$1444,Geometria!$L$1462))*(1-(MIN(MIN(1,MAX(0,(B103-Geometria!$L$1405/100)/(Geometria!$N$1307/100))),MIN(1,MAX(0,((Geometria!$L$29/100-B103)-Geometria!$R$1405/100)/(Geometria!$N$1307/100))))))*(IF(OR(Geometria!$K$1405>0,Geometria!$K$1403>0,Geometria!$Q$1405>0,Geometria!$Q$1403>0),1,0)))*H126*(Geometria!$L$299-(Geometria!$L$299-IF(B103<Geometria!$L$1409/100,Geometria!$L$1443,Geometria!$L$1461))*(1-(MIN(MIN(1,MAX(0,(B103-Geometria!$L$1409/100)/(Geometria!$N$1307/100))),MIN(1,MAX(0,((Geometria!$L$29/100-B103)-Geometria!$R$1409/100)/(Geometria!$N$1307/100))))))*(IF(OR(Geometria!$K$1409>0,Geometria!$K$1407>0,Geometria!$Q$1409>0,Geometria!$Q$1407>0),1,0))-(Geometria!$L$299-IF(B103<Geometria!$L$1405/100,Geometria!$L$1445,Geometria!$L$1463))*(1-(MIN(MIN(1,MAX(0,(B103-Geometria!$L$1405/100)/(Geometria!$N$1307/100))),MIN(1,MAX(0,((Geometria!$L$29/100-B103)-Geometria!$R$1405/100)/(Geometria!$N$1307/100))))))*(IF(OR(Geometria!$K$1405>0,Geometria!$K$1403>0,Geometria!$Q$1405>0,Geometria!$Q$1403>0),1,0)))/100-Geometria!$P$1429*H103*Geometria!$L$1438/100 -> 130.6275 | O103: =(IF(C103="Sim",IF(A103="Sim",$E$93,EX103),IF(A103="Sim",EZ103,Geometria!$L$906))) -> 749.9028 | P103: =(IF(C103="Sim",IF(A103="Sim",$E$94,EY103),IF(A103="Sim",FA103,Geometria!$L$907))) -> 213.7223 | R103: σi,3 | S103: =F103 -> 4277.7759 | T103: kN/m² | U103: =S103/1000 -> 4.2777759 | V103: MPa | W103: =W102 -> 0 | X103: =IF(OR(AND(Y103<Geometria!$L$1405/100,Geometria!$K$1405>0),AND((Geometria!$L$29/100-Y103)<Geometria!$R$1405/100,Geometria!$Q$1405>0)),"Sim","Não") -> Sim | Y103: =Geometria!$M$415 -> 0.785 | Z103: =IF(OR(AND(Y103<Geometria!$L$1409/100,OR(Geometria!$K$1409>0,Geometria!$K$1407>0)),AND((Geometria!$L$29/100-Y103)<Geometria!$R$1409/100,OR(Geometria!$Q$1409>0,Geometria!$Q$1407>0))),"Sim","Não") -> Não | AA103: σi,3 | AB103: =IF(Geometria!$M$437<Geometria!$N$1307/100,"Reduzir","OK") -> Reduzir | AC103: =IF(AB103="Reduzir",AD103,AF103) -> -1812.2473 | AD103: =-(AI103/(Geometria!$L$48/100^2))+(AJ103/(Geometria!$L$52/100^3))-((Geometria!$M$416)/(Geometria!$L$52/100^3))-((Geometria!$M$427)/(Geometria!$M$52))-((Geometria!$L$76*Geometria!$M$438)/(Geometria!$M$52)) -> -1812.2473 | AE103: =((Geometria!$N$369*(Geometria!$M$897*100))/Geometria!$N$1307) -> 82.775016 | AF103: =-((Geometria!$L$373-(Geometria!$L$373-ER103)*(1-(MIN(MIN(1,MAX(0,(Y103-Geometria!$L$1409/100)/(Geometria!$N$1307/100))),MIN(1,MAX(0,((Geometria!$L$29/100-Y103)-Geometria!$R$1409/100)/(Geometria!$N$1307/100))))))*(IF(OR(Geometria!$K$1409>0,Geometria!$K$1407>0,Geometria!$Q$1409>0,Geometria!$Q$1407>0),1,0))-(Geometria!$L$373-ET103)*(1-(MIN(MIN(1,MAX(0,(Y103-Geometria!$L$1405/100)/(Geometria!$N$1307/100))),MIN(1,MAX(0,((Geometria!$L$29/100-Y103)-Geometria!$R$1405/100)/(Geometria!$N$1307/100))))))*(IF(OR(Geometria!$K$1405>0,Geometria!$K$1403>0,Geometria!$Q$1405>0,Geometria!$Q$1403>0),1,0))))/(Geometria!$L$48/100^2)+((Geometria!$L$374-(Geometria!$L$374-ES103)*(1-(MIN(MIN(1,MAX(0,(Y103-Geometria!$L$1409/100)/(Geometria!$N$1307/100))),MIN(1,MAX(0,((Geometria!$L$29/100-Y103)-Geometria!$R$1409/100)/(Geometria!$N$1307/100))))))*(IF(OR(Geometria!$K$1409>0,Geometria!$K$1407>0,Geometria!$Q$1409>0,Geometria!$Q$1407>0),1,0))-(Geometria!$L$374-EU103)*(1-(MIN(MIN(1,MAX(0,(Y103-Geometria!$L$1405/100)/(Geometria!$N$1307/100))),MIN(1,MAX(0,((Geometria!$L$29/100-Y103)-Geometria!$R$1405/100)/(Geometria!$N$1307/100))))))*(IF(OR(Geometria!$K$1405>0,Geometria!$K$1403>0,Geometria!$Q$1405>0,Geometria!$Q$1403>0),1,0))))/(Geometria!$L$52/100^3)-((Geometria!$M$416)/(Geometria!$L$52/100^3))-((Geometria!$M$427)/(Geometria!$M$52))-((Geometria!$L$76*Geometria!$M$438)/(Geometria!$M$52)) -> 607.79771 | AI103: =(IF(Z103="Sim",IF(X103="Sim",IF(Y103<Geometria!$L$1405/100,Geometria!$L$1435,Geometria!$L$1476),IF(Y103<Geometria!$L$1409/100,Geometria!$L$1442,Geometria!$L$1460)),IF(X103="Sim",IF(Y103<Geometria!$L$1405/100,Geometria!$L$1444,Geometria!$L$1462),Geometria!$L$298)))*AE126+Geometria!$P$1429*AE103 -> 386.31597 | AJ103: =(IF(Z103="Sim",IF(X103="Sim",IF(Y103<Geometria!$L$1405/100,Geometria!$L$1435,Geometria!$L$1476),IF(Y103<Geometria!$L$1409/100,Geometria!$L$1442,Geometria!$L$1460)),IF(X103="Sim",IF(Y103<Geometria!$L$1405/100,Geometria!$L$1444,Geometria!$L$1462),Geometria!$L$298)))*AE126*(IF(Z103="Sim",IF(X103="Sim",IF(Y103<Geometria!$L$1405/100,Geometria!$L$1436,Geometria!$L$1484),IF(Y103<Geometria!$L$1409/100,Geometria!$L$1443,Geometria!$L$1461)),IF(X103="Sim",IF(Y103<Geometria!$L$1405/100,Geometria!$L$1445,Geometria!$L$1463),Geometria!$L$299)))/100-Geometria!$P$1429*AE103*Geometria!$L$1438/100 -> 110.10005 | AL103: =(IF(Z103="Sim",IF(X103="Sim",$AB$93,ER103),IF(X103="Sim",ET103,Geometria!$L$373))) -> 621.77981 | AM103: =(IF(Z103="Sim",IF(X103="Sim",$AB$94,ES103),IF(X103="Sim",EU103,Geometria!$L$374))) -> 177.20725 | AO103: σi,3 | AP103: =AC103 -> -1812.2473 | AQ103: kN/m² | AR103: =AP103/1000 -> -1.8122473 | AS103: MPa | AT103: =AT102 -> 0 | AU103: =IF(OR(AND(AV103<Geometria!$L$1405/100,Geometria!$K$1405>0),AND((Geometria!$L$29/100-AV103)<Geometria!$R$1405/100,Geometria!$Q$1405>0)),"Sim","Não") -> Sim | AV103: =Geometria!$M$415 -> 0.785 | AW103: =IF(OR(AND(AV103<Geometria!$L$1409/100,OR(Geometria!$K$1409>0,Geometria!$K$1407>0)),AND((Geometria!$L$29/100-AV103)<Geometria!$R$1409/100,OR(Geometria!$Q$1409>0,Geometria!$Q$1407>0))),"Sim","Não") -> Não | AX103: σi,3 | AY103: =IF(Geometria!$M$437<Geometria!$N$1307/100,"Reduzir","OK") -> Reduzir | AZ103: =IF(AY103="Reduzir",BA103,BC103) -> -1812.2473 | BA103: =-(BF103/(Geometria!$L$48/100^2))+(BG103/(Geometria!$L$52/100^3))-((Geometria!$M$416)/(Geometria!$L$52/100^3))-((Geometria!$M$427)/(Geometria!$M$52))-((Geometria!$L$76*Geometria!$M$438)/(Geometria!$M$52)) -> -1812.2473 | BB103: =((Geometria!$N$369*(Geometria!$M$897*100))/Geometria!$N$1307) -> 82.775016 | BC103: =-((Geometria!$L$373-(Geometria!$L$373-ER103)*(1-(MIN(MIN(1,MAX(0,(AV103-Geometria!$L$1409/100)/(Geometria!$N$1307/100))),MIN(1,MAX(0,((Geometria!$L$29/100-AV103)-Geometria!$R$1409/100)/(Geometria!$N$1307/100))))))*(IF(OR(Geometria!$K$1409>0,Geometria!$K$1407>0,Geometria!$Q$1409>0,Geometria!$Q$1407>0),1,0))-(Geometria!$L$373-ET103)*(1-(MIN(MIN(1,MAX(0,(AV103-Geometria!$L$1405/100)/(Geometria!$N$1307/100))),MIN(1,MAX(0,((Geometria!$L$29/100-AV103)-Geometria!$R$1405/100)/(Geometria!$N$1307/100))))))*(IF(OR(Geometria!$K$1405>0,Geometria!$K$1403>0,Geometria!$Q$1405>0,Geometria!$Q$1403>0),1,0))))/(Geometria!$L$48/100^2)+((Geometria!$L$374-(Geometria!$L$374-ES103)*(1-(MIN(MIN(1,MAX(0,(AV103-Geometria!$L$1409/100)/(Geometria!$N$1307/100))),MIN(1,MAX(0,((Geometria!$L$29/100-AV103)-Geometria!$R$1409/100)/(Geometria!$N$1307/100))))))*(IF(OR(Geometria!$K$1409>0,Geometria!$K$1407>0,Geometria!$Q$1409>0,Geometria!$Q$1407>0),1,0))-(Geometria!$L$374-EU103)*(1-(MIN(MIN(1,MAX(0,(AV103-Geometria!$L$1405/100)/(Geometria!$N$1307/100))),MIN(1,MAX(0,((Geometria!$L$29/100-AV103)-Geometria!$R$1405/100)/(Geometria!$N$1307/100))))))*(IF(OR(Geometria!$K$1405>0,Geometria!$K$1403>0,Geometria!$Q$1405>0,Geometria!$Q$1403>0),1,0))))/(Geometria!$L$52/100^3)-((Geometria!$M$416)/(Geometria!$L$52/100^3))-((Geometria!$M$427)/(Geometria!$M$52)) -> 607.80132 | BF103: =(Geometria!$L$298-(Geometria!$L$298-IF(AV103<Geometria!$L$1409/100,Geometria!$L$1442,Geometria!$L$1460))*(1-(MIN(MIN(1,MAX(0,(AV103-Geometria!$L$1409/100)/(Geometria!$N$1307/100))),MIN(1,MAX(0,((Geometria!$L$29/100-AV103)-Geometria!$R$1409/100)/(Geometria!$N$1307/100))))))*(IF(OR(Geometria!$K$1409>0,Geometria!$K$1407>0,Geometria!$Q$1409>0,Geometria!$Q$1407>0),1,0))-(Geometria!$L$298-IF(AV103<Geometria!$L$1405/100,Geometria!$L$1444,Geometria!$L$1462))*(1-(MIN(MIN(1,MAX(0,(AV103-Geometria!$L$1405/100)/(Geometria!$N$1307/100))),MIN(1,MAX(0,((Geometria!$L$29/100-AV103)-Geometria!$R$1405/100)/(Geometria!$N$1307/100))))))*(IF(OR(Geometria!$K$1405>0,Geometria!$K$1403>0,Geometria!$Q$1405>0,Geometria!$Q$1403>0),1,0)))*BB126+Geometria!$P$1429*BB103 -> 386.31597 | BG103: =(Geometria!$L$298-(Geometria!$L$298-IF(AV103<Geometria!$L$1409/100,Geometria!$L$1442,Geometria!$L$1460))*(1-(MIN(MIN(1,MAX(0,(AV103-Geometria!$L$1409/100)/(Geometria!$N$1307/100))),MIN(1,MAX(0,((Geometria!$L$29/100-AV103)-Geometria!$R$1409/100)/(Geometria!$N$1307/100))))))*(IF(OR(Geometria!$K$1409>0,Geometria!$K$1407>0,Geometria!$Q$1409>0,Geometria!$Q$1407>0),1,0))-(Geometria!$L$298-IF(AV103<Geometria!$L$1405/100,Geometria!$L$1444,Geometria!$L$1462))*(1-(MIN(MIN(1,MAX(0,(AV103-Geometria!$L$1405/100)/(Geometria!$N$1307/100))),MIN(1,MAX(0,((Geometria!$L$29/100-AV103)-Geometria!$R$1405/100)/(Geometria!$N$1307/100))))))*(IF(OR(Geometria!$K$1405>0,Geometria!$K$1403>0,Geometria!$Q$1405>0,Geometria!$Q$1403>0),1,0)))*BB126*(Geometria!$L$299-(Geometria!$L$299-IF(AV103<Geometria!$L$1409/100,Geometria!$L$1443,Geometria!$L$1461))*(1-(MIN(MIN(1,MAX(0,(AV103-Geometria!$L$1409/100)/(Geometria!$N$1307/100))),MIN(1,MAX(0,((Geometria!$L$29/100-AV103)-Geometria!$R$1409/100)/(Geometria!$N$1307/100))))))*(IF(OR(Geometria!$K$1409>0,Geometria!$K$1407>0,Geometria!$Q$1409>0,Geometria!$Q$1407>0),1,0))-(Geometria!$L$299-IF(AV103<Geometria!$L$1405/100,Geometria!$L$1445,Geometria!$L$1463))*(1-(MIN(MIN(1,MAX(0,(AV103-Geometria!$L$1405/100)/(Geometria!$N$1307/100))),MIN(1,MAX(0,((Geometria!$L$29/100-AV103)-Geometria!$R$1405/100)/(Geometria!$N$1307/100))))))*(IF(OR(Geometria!$K$1405>0,Geometria!$K$1403>0,Geometria!$Q$1405>0,Geometria!$Q$1403>0),1,0)))/100-Geometria!$P$1429*BB103*Geometria!$L$1438/100 -> 110.10005 | BI103: =(IF(AW103="Sim",IF(AU103="Sim",$AB$93,ER103),IF(AU103="Sim",ET103,Geometria!$L$373))) -> 621.77981 | BJ103: =(IF(AW103="Sim",IF(AU103="Sim",$AB$94,ES103),IF(AU103="Sim",EU103,Geometria!$L$374))) -> 177.20725 | BL103: σi,3 | BM103: =AZ103 -> -1812.2473 | BN103: kN/m² | BO103: =BM103/1000 -> -1.8122473 | BP103: MPa | BQ103: =BQ102 -> 0 | BR103: =IF(OR(AND(BS103<Geometria!$L$1405/100,Geometria!$K$1405>0),AND((Geometria!$L$29/100-BS103)<Geometria!$R$1405/100,Geometria!$Q$1405>0)),"Sim","Não") -> Sim | BS103: =Geometria!$M$415 -> 0.785 | BT103: =IF(OR(AND(BS103<Geometria!$L$1409/100,OR(Geometria!$K$1409>0,Geometria!$K$1407>0)),AND((Geometria!$L$29/100-BS103)<Geometria!$R$1409/100,OR(Geometria!$Q$1409>0,Geometria!$Q$1407>0))),"Sim","Não") -> Não | BU103: σi,3 | BV103: =IF(Geometria!$M$437<Geometria!$N$1307/100,"Reduzir","OK") -> Reduzir | BW103: =IF(BV103="Reduzir",BX103,BZ103) -> -1812.2473 | BX103: =-(CC103/(Geometria!$L$48/100^2))+(CD103/(Geometria!$L$52/100^3))-((Geometria!$M$416)/(Geometria!$L$52/100^3))-((Geometria!$M$427)/(Geometria!$M$52))-((Geometria!$L$76*Geometria!$M$438)/(Geometria!$M$52)) -> -1812.2473 | BY103: =((Geometria!$N$369*(Geometria!$M$897*100))/Geometria!$N$1307) -> 82.775016 | BZ103: =-((Geometria!$L$373-(Geometria!$L$373-ER103)*(1-(MIN(MIN(1,MAX(0,(BS103-Geometria!$L$1409/100)/(Geometria!$N$1307/100))),MIN(1,MAX(0,((Geometria!$L$29/100-BS103)-Geometria!$R$1409/100)/(Geometria!$N$1307/100))))))*(IF(OR(Geometria!$K$1409>0,Geometria!$K$1407>0,Geometria!$Q$1409>0,Geometria!$Q$1407>0),1,0))-(Geometria!$L$373-ET103)*(1-(MIN(MIN(1,MAX(0,(BS103-Geometria!$L$1405/100)/(Geometria!$N$1307/100))),MIN(1,MAX(0,((Geometria!$L$29/100-BS103)-Geometria!$R$1405/100)/(Geometria!$N$1307/100))))))*(IF(OR(Geometria!$K$1405>0,Geometria!$K$1403>0,Geometria!$Q$1405>0,Geometria!$Q$1403>0),1,0))))/(Geometria!$L$48/100^2)+((Geometria!$L$374-(Geometria!$L$374-ES103)*(1-(MIN(MIN(1,MAX(0,(BS103-Geometria!$L$1409/100)/(Geometria!$N$1307/100))),MIN(1,MAX(0,((Geometria!$L$29/100-BS103)-Geometria!$R$1409/100)/(Geometria!$N$1307/100))))))*(IF(OR(Geometria!$K$1409>0,Geometria!$K$1407>0,Geometria!$Q$1409>0,Geometria!$Q$1407>0),1,0))-(Geometria!$L$374-EU103)*(1-(MIN(MIN(1,MAX(0,(BS103-Geometria!$L$1405/100)/(Geometria!$N$1307/100))),MIN(1,MAX(0,((Geometria!$L$29/100-BS103)-Geometria!$R$1405/100)/(Geometria!$N$1307/100))))))*(IF(OR(Geometria!$K$1405>0,Geometria!$K$1403>0,Geometria!$Q$1405>0,Geometria!$Q$1403>0),1,0))))/(Geometria!$L$52/100^3)-((Geometria!$M$673)/(Geometria!$L$52/100^3))-((Geometria!$M$684)/(Geometria!$M$52))-((Geometria!$L$77*Geometria!$M$695)/(Geometria!$M$52)) -> 607.79891 | CC103: =(Geometria!$L$298-(Geometria!$L$298-IF(BS103<Geometria!$L$1409/100,Geometria!$L$1442,Geometria!$L$1460))*(1-(MIN(MIN(1,MAX(0,(BS103-Geometria!$L$1409/100)/(Geometria!$N$1307/100))),MIN(1,MAX(0,((Geometria!$L$29/100-BS103)-Geometria!$R$1409/100)/(Geometria!$N$1307/100))))))*(IF(OR(Geometria!$K$1409>0,Geometria!$K$1407>0,Geometria!$Q$1409>0,Geometria!$Q$1407>0),1,0))-(Geometria!$L$298-IF(BS103<Geometria!$L$1405/100,Geometria!$L$1444,Geometria!$L$1462))*(1-(MIN(MIN(1,MAX(0,(BS103-Geometria!$L$1405/100)/(Geometria!$N$1307/100))),MIN(1,MAX(0,((Geometria!$L$29/100-BS103)-Geometria!$R$1405/100)/(Geometria!$N$1307/100))))))*(IF(OR(Geometria!$K$1405>0,Geometria!$K$1403>0,Geometria!$Q$1405>0,Geometria!$Q$1403>0),1,0)))*BY126+Geometria!$P$1429*BY103 -> 386.31597 | CD103: =(Geometria!$L$298-(Geometria!$L$298-IF(BS103<Geometria!$L$1409/100,Geometria!$L$1442,Geometria!$L$1460))*(1-(MIN(MIN(1,MAX(0,(BS103-Geometria!$L$1409/100)/(Geometria!$N$1307/100))),MIN(1,MAX(0,((Geometria!$L$29/100-BS103)-Geometria!$R$1409/100)/(Geometria!$N$1307/100))))))*(IF(OR(Geometria!$K$1409>0,Geometria!$K$1407>0,Geometria!$Q$1409>0,Geometria!$Q$1407>0),1,0))-(Geometria!$L$298-IF(BS103<Geometria!$L$1405/100,Geometria!$L$1444,Geometria!$L$1462))*(1-(MIN(MIN(1,MAX(0,(BS103-Geometria!$L$1405/100)/(Geometria!$N$1307/100))),MIN(1,MAX(0,((Geometria!$L$29/100-BS103)-Geometria!$R$1405/100)/(Geometria!$N$1307/100))))))*(IF(OR(Geometria!$K$1405>0,Geometria!$K$1403>0,Geometria!$Q$1405>0,Geometria!$Q$1403>0),1,0)))*BY126*(Geometria!$L$299-(Geometria!$L$299-IF(BS103<Geometria!$L$1409/100,Geometria!$L$1443,Geometria!$L$1461))*(1-(MIN(MIN(1,MAX(0,(BS103-Geometria!$L$1409/100)/(Geometria!$N$1307/100))),MIN(1,MAX(0,((Geometria!$L$29/100-BS103)-Geometria!$R$1409/100)/(Geometria!$N$1307/100))))))*(IF(OR(Geometria!$K$1409>0,Geometria!$K$1407>0,Geometria!$Q$1409>0,Geometria!$Q$1407>0),1,0))-(Geometria!$L$299-IF(BS103<Geometria!$L$1405/100,Geometria!$L$1445,Geometria!$L$1463))*(1-(MIN(MIN(1,MAX(0,(BS103-Geometria!$L$1405/100)/(Geometria!$N$1307/100))),MIN(1,MAX(0,((Geometria!$L$29/100-BS103)-Geometria!$R$1405/100)/(Geometria!$N$1307/100))))))*(IF(OR(Geometria!$K$1405>0,Geometria!$K$1403>0,Geometria!$Q$1405>0,Geometria!$Q$1403>0),1,0)))/100-Geometria!$P$1429*BY103*Geometria!$L$1438/100 -> 110.10005 | CF103: =(IF(BT103="Sim",IF(BR103="Sim",$AB$93,ER103),IF(BR103="Sim",ET103,Geometria!$L$373))) -> 621.77981 | CG103: =(IF(BT103="Sim",IF(BR103="Sim",$AB$94,ES103),IF(BR103="Sim",EU103,Geometria!$L$374))) -> 177.20725 | CI103: σi,3 | CJ103: =BW103 -> -1812.2473 | CK103: kN/m² | CL103: =CJ103/1000 -> -1.8122473 | CM103: MPa | CN103: =CN102 -> 0 | CO103: =IF(OR(AND(CP103<Geometria!$L$1405/100,Geometria!$K$1405>0),AND((Geometria!$L$29/100-CP103)<Geometria!$R$1405/100,Geometria!$Q$1405>0)),"Sim","Não") -> Sim | CP103: =Geometria!$M$415 -> 0.785 | CQ103: =IF(OR(AND(CP103<Geometria!$L$1409/100,OR(Geometria!$K$1409>0,Geometria!$K$1407>0)),AND((Geometria!$L$29/100-CP103)<Geometria!$R$1409/100,OR(Geometria!$Q$1409>0,Geometria!$Q$1407>0))),"Sim","Não") -> Não | CR103: σi,3 | CS103: =IF(Geometria!$M$437<Geometria!$N$1307/100,"Reduzir","OK") -> Reduzir | CT103: =IF(CS103="Reduzir",CU103,CW103) -> -1812.2473 | CU103: =-(CZ103/(Geometria!$L$48/100^2))+(DA103/(Geometria!$L$52/100^3))-((Geometria!$M$416)/(Geometria!$L$52/100^3))-((Geometria!$M$427)/(Geometria!$M$52))-((Geometria!$L$76*Geometria!$M$438)/(Geometria!$M$52)) -> -1812.2473 | CV103: =((Geometria!$N$369*(Geometria!$M$897*100))/Geometria!$N$1307) -> 82.775016 | CW103: =-((Geometria!$L$373-(Geometria!$L$373-ER103)*(1-(MIN(MIN(1,MAX(0,(CP103-Geometria!$L$1409/100)/(Geometria!$N$1307/100))),MIN(1,MAX(0,((Geometria!$L$29/100-CP103)-Geometria!$R$1409/100)/(Geometria!$N$1307/100))))))*(IF(OR(Geometria!$K$1409>0,Geometria!$K$1407>0,Geometria!$Q$1409>0,Geometria!$Q$1407>0),1,0))-(Geometria!$L$373-ET103)*(1-(MIN(MIN(1,MAX(0,(CP103-Geometria!$L$1405/100)/(Geometria!$N$1307/100))),MIN(1,MAX(0,((Geometria!$L$29/100-CP103)-Geometria!$R$1405/100)/(Geometria!$N$1307/100))))))*(IF(OR(Geometria!$K$1405>0,Geometria!$K$1403>0,Geometria!$Q$1405>0,Geometria!$Q$1403>0),1,0))))/(Geometria!$L$48/100^2)+((Geometria!$L$374-(Geometria!$L$374-ES103)*(1-(MIN(MIN(1,MAX(0,(CP103-Geometria!$L$1409/100)/(Geometria!$N$1307/100))),MIN(1,MAX(0,((Geometria!$L$29/100-CP103)-Geometria!$R$1409/100)/(Geometria!$N$1307/100))))))*(IF(OR(Geometria!$K$1409>0,Geometria!$K$1407>0,Geometria!$Q$1409>0,Geometria!$Q$1407>0),1,0))-(Geometria!$L$374-EU103)*(1-(MIN(MIN(1,MAX(0,(CP103-Geometria!$L$1405/100)/(Geometria!$N$1307/100))),MIN(1,MAX(0,((Geometria!$L$29/100-CP103)-Geometria!$R$1405/100)/(Geometria!$N$1307/100))))))*(IF(OR(Geometria!$K$1405>0,Geometria!$K$1403>0,Geometria!$Q$1405>0,Geometria!$Q$1403>0),1,0))))/(Geometria!$L$52/100^3)-((Geometria!$M$673)/(Geometria!$L$52/100^3))-((Geometria!$M$684)/(Geometria!$M$52)) -> 607.80132 | CZ103: =(IF(CQ103="Sim",IF(CO103="Sim",IF(CP103<Geometria!$L$1405/100,Geometria!$L$1435,Geometria!$L$1476),IF(CP103<Geometria!$L$1409/100,Geometria!$L$1442,Geometria!$L$1460)),IF(CO103="Sim",IF(CP103<Geometria!$L$1405/100,Geometria!$L$1444,Geometria!$L$1462),Geometria!$L$298)))*CV126+Geometria!$P$1429*CV103 -> 386.31597 | DA103: =(IF(CQ103="Sim",IF(CO103="Sim",IF(CP103<Geometria!$L$1405/100,Geometria!$L$1435,Geometria!$L$1476),IF(CP103<Geometria!$L$1409/100,Geometria!$L$1442,Geometria!$L$1460)),IF(CO103="Sim",IF(CP103<Geometria!$L$1405/100,Geometria!$L$1444,Geometria!$L$1462),Geometria!$L$298)))*CV126*(IF(CQ103="Sim",IF(CO103="Sim",IF(CP103<Geometria!$L$1405/100,Geometria!$L$1436,Geometria!$L$1484),IF(CP103<Geometria!$L$1409/100,Geometria!$L$1443,Geometria!$L$1461)),IF(CO103="Sim",IF(CP103<Geometria!$L$1405/100,Geometria!$L$1445,Geometria!$L$1463),Geometria!$L$299)))/100-Geometria!$P$1429*CV103*Geometria!$L$1438/100 -> 110.10005 | DC103: =(IF(CQ103="Sim",IF(CO103="Sim",$AB$93,ER103),IF(CO103="Sim",ET103,Geometria!$L$373))) -> 621.77981 | DD103: =(IF(CQ103="Sim",IF(CO103="Sim",$AB$94,ES103),IF(CO103="Sim",EU103,Geometria!$L$374))) -> 177.20725 | DF103: σi,3 | DG103: =CT103 -> -1812.2473 | DH103: kN/m² | DI103: =DG103/1000 -> -1.8122473 | DJ103: MPa | DK103: =DK102 -> 0 | EA103: =-L103/('Aberturas na Alma'!$M$112/100^2)+M103/('Aberturas na Alma'!$M$119/100^3)-Geometria!$L$898/('Aberturas na Alma'!$M$119/100^3) -> 3723.5084 | EB103: =-(IF(C103="Sim",IF(A103="Sim",$E$93,EX103),IF(A103="Sim",EZ103,Geometria!$L$906)))/('Aberturas na Alma'!$M$112/100^2)+(IF(C103="Sim",IF(A103="Sim",$E$94,EY103),IF(A103="Sim",FA103,Geometria!$L$907)))/('Aberturas na Alma'!$M$119/100^3)-Geometria!$M$898/('Aberturas na Alma'!$M$119/100^3) -> 5975.3041 | EC103: =IF(AND('Aberturas na Alma'!$M$18="NÃO DISPENSADO — furo deve ser verificado (cálculo abaixo)",OR(AND(B103>=('Aberturas na Alma'!$M$4-'Aberturas na Alma'!$M$7/2)/100,B103<=('Aberturas na Alma'!$M$4+'Aberturas na Alma'!$M$7/2)/100),ABS(B103-'Aberturas na Alma'!$M$4/100)<=Geometria!$L$29/4000)),IF(E103="Reduzir",EA103,EB103),F103) -> 4277.7759 | ED103: =-(AI103/('Aberturas na Alma'!$M$112/100^2))+(AJ103/('Aberturas na Alma'!$M$119/100^3))-((Geometria!$M$416)/('Aberturas na Alma'!$M$119/100^3))-((Geometria!$M$427)/('Aberturas na Alma'!$M$119/100^3))-((Geometria!$L$76*Geometria!$M$438)/('Aberturas na Alma'!$M$119/100^3)) -> -17523.076 | EE103: =-((IF(Z103="Sim",IF(X103="Sim",$AB$93,ER103),IF(X103="Sim",ET103,Geometria!$L$373)))/('Aberturas na Alma'!$M$112/100^2))+((IF(Z103="Sim",IF(X103="Sim",$AB$94,ES103),IF(X103="Sim",EU103,Geometria!$L$374)))/('Aberturas na Alma'!$M$119/100^3))-((Geometria!$M$416)/('Aberturas na Alma'!$M$119/100^3))-((Geometria!$M$427)/('Aberturas na Alma'!$M$119/100^3))-((Geometria!$L$76*Geometria!$M$438)/('Aberturas na Alma'!$M$119/100^3)) -> -15378.175 | EF103: =IF(AND('Aberturas na Alma'!$M$18="NÃO DISPENSADO — furo deve ser verificado (cálculo abaixo)",OR(AND(B103>=('Aberturas na Alma'!$M$4-'Aberturas na Alma'!$M$7/2)/100,B103<=('Aberturas na Alma'!$M$4+'Aberturas na Alma'!$M$7/2)/100),ABS(B103-'Aberturas na Alma'!$M$4/100)<=Geometria!$L$29/4000)),IF(AB103="Reduzir",ED103,EE103),AC103) -> -1812.2473 | EG103: =-(BF103/('Aberturas na Alma'!$M$112/100^2))+(BG103/('Aberturas na Alma'!$M$119/100^3))-((Geometria!$M$416)/('Aberturas na Alma'!$M$119/100^3))-((Geometria!$M$427)/('Aberturas na Alma'!$M$119/100^3))-((Geometria!$L$76*Geometria!$M$438)/('Aberturas na Alma'!$M$119/100^3)) -> -17523.076 | EH103: =-((IF(AW103="Sim",IF(AU103="Sim",$AB$93,ER103),IF(AU103="Sim",ET103,Geometria!$L$373)))/('Aberturas na Alma'!$M$112/100^2))+((IF(AW103="Sim",IF(AU103="Sim",$AB$94,ES103),IF(AU103="Sim",EU103,Geometria!$L$374)))/('Aberturas na Alma'!$M$119/100^3))-((Geometria!$M$416)/('Aberturas na Alma'!$M$119/100^3))-((Geometria!$M$427)/('Aberturas na Alma'!$M$119/100^3)) -> -1306.445 | EI103: =IF(AND('Aberturas na Alma'!$M$18="NÃO DISPENSADO — furo deve ser verificado (cálculo abaixo)",OR(AND(B103>=('Aberturas na Alma'!$M$4-'Aberturas na Alma'!$M$7/2)/100,B103<=('Aberturas na Alma'!$M$4+'Aberturas na Alma'!$M$7/2)/100),ABS(B103-'Aberturas na Alma'!$M$4/100)<=Geometria!$L$29/4000)),IF(AY103="Reduzir",EG103,EH103),AZ103) -> -1812.2473 | EJ103: =-(CC103/('Aberturas na Alma'!$M$112/100^2))+(CD103/('Aberturas na Alma'!$M$119/100^3))-((Geometria!$M$416)/('Aberturas na Alma'!$M$119/100^3))-((Geometria!$M$427)/('Aberturas na Alma'!$M$119/100^3))-((Geometria!$L$76*Geometria!$M$438)/('Aberturas na Alma'!$M$119/100^3)) -> -17523.076 | EK103: =-((IF(BT103="Sim",IF(BR103="Sim",$AB$93,ER103),IF(BR103="Sim",ET103,Geometria!$L$373)))/('Aberturas na Alma'!$M$112/100^2))+((IF(BT103="Sim",IF(BR103="Sim",$AB$94,ES103),IF(BR103="Sim",EU103,Geometria!$L$374)))/('Aberturas na Alma'!$M$119/100^3))-((Geometria!$M$673)/('Aberturas na Alma'!$M$119/100^3))-((Geometria!$M$684)/('Aberturas na Alma'!$M$119/100^3))-((Geometria!$L$77*Geometria!$M$695)/('Aberturas na Alma'!$M$119/100^3)) -> -10687.598 | EL103: =IF(AND('Aberturas na Alma'!$M$18="NÃO DISPENSADO — furo deve ser verificado (cálculo abaixo)",OR(AND(B103>=('Aberturas na Alma'!$M$4-'Aberturas na Alma'!$M$7/2)/100,B103<=('Aberturas na Alma'!$M$4+'Aberturas na Alma'!$M$7/2)/100),ABS(B103-'Aberturas na Alma'!$M$4/100)<=Geometria!$L$29/4000)),IF(BV103="Reduzir",EJ103,EK103),BW103) -> -1812.2473 | EM103: =-(CZ103/('Aberturas na Alma'!$M$112/100^2))+(DA103/('Aberturas na Alma'!$M$119/100^3))-((Geometria!$M$416)/('Aberturas na Alma'!$M$119/100^3))-((Geometria!$M$427)/('Aberturas na Alma'!$M$119/100^3))-((Geometria!$L$76*Geometria!$M$438)/('Aberturas na Alma'!$M$119/100^3)) -> -17523.076 | EN103: =-((IF(CQ103="Sim",IF(CO103="Sim",$AB$93,ER103),IF(CO103="Sim",ET103,Geometria!$L$373)))/('Aberturas na Alma'!$M$112/100^2))+((IF(CQ103="Sim",IF(CO103="Sim",$AB$94,ES103),IF(CO103="Sim",EU103,Geometria!$L$374)))/('Aberturas na Alma'!$M$119/100^3))-((Geometria!$M$673)/('Aberturas na Alma'!$M$119/100^3))-((Geometria!$M$684)/('Aberturas na Alma'!$M$119/100^3)) -> -1306.445 | EO103: =IF(AND('Aberturas na Alma'!$M$18="NÃO DISPENSADO — furo deve ser verificado (cálculo abaixo)",OR(AND(B103>=('Aberturas na Alma'!$M$4-'Aberturas na Alma'!$M$7/2)/100,B103<=('Aberturas na Alma'!$M$4+'Aberturas na Alma'!$M$7/2)/100),ABS(B103-'Aberturas na Alma'!$M$4/100)<=Geometria!$L$29/4000)),IF(CS103="Reduzir",EM103,EN103),CT103) -> -1812.2473 | EP103: =IF(AND(Y103<Geometria!$L$1409/100,OR(Geometria!$K$1409>0,Geometria!$K$1407>0)),"ESQ",IF(AND((Geometria!$L$29/100-Y103)<Geometria!$R$1409/100,OR(Geometria!$Q$1409>0,Geometria!$Q$1407>0)),"DIR","N/A")) -> N/A | EQ103: =IF(AND(Y103<Geometria!$L$1405/100,Geometria!$K$1405>0),"ESQ",IF(AND((Geometria!$L$29/100-Y103)<Geometria!$R$1405/100,Geometria!$Q$1405>0),"DIR","N/A")) -> ESQ | ER103: =IF(EP103="DIR",Geometria!$L$1470,Geometria!$L$1452) -> 1243.5596 | ES103: =IF(EP103="DIR",Geometria!$L$1471,Geometria!$L$1453) -> 233.16743 | ET103: =IF(EQ103="DIR",Geometria!$L$1472,Geometria!$L$1454) -> 621.77981 | EU103: =IF(EQ103="DIR",Geometria!$L$1473,Geometria!$L$1455) -> 177.20725 | EV103: =IF(AND(B103<Geometria!$L$1409/100,OR(Geometria!$K$1409>0,Geometria!$K$1407>0)),"ESQ",IF(AND((Geometria!$L$29/100-B103)<Geometria!$R$1409/100,OR(Geometria!$Q$1409>0,Geometria!$Q$1407>0)),"DIR","N/A")) -> N/A | EW103: =IF(AND(B103<Geometria!$L$1405/100,Geometria!$K$1405>0),"ESQ",IF(AND((Geometria!$L$29/100-B103)<Geometria!$R$1405/100,Geometria!$Q$1405>0),"DIR","N/A")) -> ESQ | EX103: =IF(EV103="DIR",Geometria!$L$1465,Geometria!$L$1447) -> 1499.8056 | EY103: =IF(EV103="DIR",Geometria!$L$1466,Geometria!$L$1448) -> 281.21355 | EZ103: =IF(EW103="DIR",Geometria!$L$1467,Geometria!$L$1449) -> 749.9028 | FA103: =IF(EW103="DIR",Geometria!$L$1468,Geometria!$L$1450) -> 213.7223
A104: =IF(OR(AND(B104<Geometria!$L$1405/100,Geometria!$K$1405>0),AND((Geometria!$L$29/100-B104)<Geometria!$R$1405/100,Geometria!$Q$1405>0)),"Sim","Não") -> Sim | B104: =Tensões!$E$63 -> 1.1775 | C104: =IF(OR(AND(B104<Geometria!$L$1409/100,OR(Geometria!$K$1409>0,Geometria!$K$1407>0)),AND((Geometria!$L$29/100-B104)<Geometria!$R$1409/100,OR(Geometria!$Q$1409>0,Geometria!$Q$1407>0))),"Sim","Não") -> Não | D104: σi,4 | E104: =IF(Geometria!$N$437<Geometria!$N$1307/100,"Reduzir","OK") -> OK | F104: =IF(E104="Reduzir",G104,I104) -> 6545.1725 | G104: =-L104/(Geometria!$L$48/100^2)+M104/(Geometria!$L$52/100^3)-Geometria!$L$898/(Geometria!$L$52/100^3) -> 6633.145 | H104: =((Geometria!$L$326*(Geometria!$N$897*100))/Geometria!$N$1307) -> 146.93757 | I104: =-(Geometria!$L$906-(Geometria!$L$906-EX104)*(1-(MIN(MIN(1,MAX(0,(B104-Geometria!$L$1409/100)/(Geometria!$N$1307/100))),MIN(1,MAX(0,((Geometria!$L$29/100-B104)-Geometria!$R$1409/100)/(Geometria!$N$1307/100))))))*(IF(OR(Geometria!$K$1409>0,Geometria!$K$1407>0,Geometria!$Q$1409>0,Geometria!$Q$1407>0),1,0))-(Geometria!$L$906-EZ104)*(1-(MIN(MIN(1,MAX(0,(B104-Geometria!$L$1405/100)/(Geometria!$N$1307/100))),MIN(1,MAX(0,((Geometria!$L$29/100-B104)-Geometria!$R$1405/100)/(Geometria!$N$1307/100))))))*(IF(OR(Geometria!$K$1405>0,Geometria!$K$1403>0,Geometria!$Q$1405>0,Geometria!$Q$1403>0),1,0)))/(Geometria!$L$48/100^2)+(Geometria!$L$907-(Geometria!$L$907-EY104)*(1-(MIN(MIN(1,MAX(0,(B104-Geometria!$L$1409/100)/(Geometria!$N$1307/100))),MIN(1,MAX(0,((Geometria!$L$29/100-B104)-Geometria!$R$1409/100)/(Geometria!$N$1307/100))))))*(IF(OR(Geometria!$K$1409>0,Geometria!$K$1407>0,Geometria!$Q$1409>0,Geometria!$Q$1407>0),1,0))-(Geometria!$L$907-FA104)*(1-(MIN(MIN(1,MAX(0,(B104-Geometria!$L$1405/100)/(Geometria!$N$1307/100))),MIN(1,MAX(0,((Geometria!$L$29/100-B104)-Geometria!$R$1405/100)/(Geometria!$N$1307/100))))))*(IF(OR(Geometria!$K$1405>0,Geometria!$K$1403>0,Geometria!$Q$1405>0,Geometria!$Q$1403>0),1,0)))/(Geometria!$L$52/100^3)-Geometria!$N$898/(Geometria!$L$52/100^3) -> 6545.1725 | L104: =(Geometria!$L$298-(Geometria!$L$298-IF(B104<Geometria!$L$1409/100,Geometria!$L$1442,Geometria!$L$1460))*(1-(MIN(MIN(1,MAX(0,(B104-Geometria!$L$1409/100)/(Geometria!$N$1307/100))),MIN(1,MAX(0,((Geometria!$L$29/100-B104)-Geometria!$R$1409/100)/(Geometria!$N$1307/100))))))*(IF(OR(Geometria!$K$1409>0,Geometria!$K$1407>0,Geometria!$Q$1409>0,Geometria!$Q$1407>0),1,0))-(Geometria!$L$298-IF(B104<Geometria!$L$1405/100,Geometria!$L$1444,Geometria!$L$1462))*(1-(MIN(MIN(1,MAX(0,(B104-Geometria!$L$1405/100)/(Geometria!$N$1307/100))),MIN(1,MAX(0,((Geometria!$L$29/100-B104)-Geometria!$R$1405/100)/(Geometria!$N$1307/100))))))*(IF(OR(Geometria!$K$1405>0,Geometria!$K$1403>0,Geometria!$Q$1405>0,Geometria!$Q$1403>0),1,0)))*H127+Geometria!$P$1429*H104 -> 687.51313 | M104: =(Geometria!$L$298-(Geometria!$L$298-IF(B104<Geometria!$L$1409/100,Geometria!$L$1442,Geometria!$L$1460))*(1-(MIN(MIN(1,MAX(0,(B104-Geometria!$L$1409/100)/(Geometria!$N$1307/100))),MIN(1,MAX(0,((Geometria!$L$29/100-B104)-Geometria!$R$1409/100)/(Geometria!$N$1307/100))))))*(IF(OR(Geometria!$K$1409>0,Geometria!$K$1407>0,Geometria!$Q$1409>0,Geometria!$Q$1407>0),1,0))-(Geometria!$L$298-IF(B104<Geometria!$L$1405/100,Geometria!$L$1444,Geometria!$L$1462))*(1-(MIN(MIN(1,MAX(0,(B104-Geometria!$L$1405/100)/(Geometria!$N$1307/100))),MIN(1,MAX(0,((Geometria!$L$29/100-B104)-Geometria!$R$1405/100)/(Geometria!$N$1307/100))))))*(IF(OR(Geometria!$K$1405>0,Geometria!$K$1403>0,Geometria!$Q$1405>0,Geometria!$Q$1403>0),1,0)))*H127*(Geometria!$L$299-(Geometria!$L$299-IF(B104<Geometria!$L$1409/100,Geometria!$L$1443,Geometria!$L$1461))*(1-(MIN(MIN(1,MAX(0,(B104-Geometria!$L$1409/100)/(Geometria!$N$1307/100))),MIN(1,MAX(0,((Geometria!$L$29/100-B104)-Geometria!$R$1409/100)/(Geometria!$N$1307/100))))))*(IF(OR(Geometria!$K$1409>0,Geometria!$K$1407>0,Geometria!$Q$1409>0,Geometria!$Q$1407>0),1,0))-(Geometria!$L$299-IF(B104<Geometria!$L$1405/100,Geometria!$L$1445,Geometria!$L$1463))*(1-(MIN(MIN(1,MAX(0,(B104-Geometria!$L$1405/100)/(Geometria!$N$1307/100))),MIN(1,MAX(0,((Geometria!$L$29/100-B104)-Geometria!$R$1405/100)/(Geometria!$N$1307/100))))))*(IF(OR(Geometria!$K$1405>0,Geometria!$K$1403>0,Geometria!$Q$1405>0,Geometria!$Q$1403>0),1,0)))/100-Geometria!$P$1429*H104*Geometria!$L$1438/100 -> 195.94124 | O104: =(IF(C104="Sim",IF(A104="Sim",$E$93,EX104),IF(A104="Sim",EZ104,Geometria!$L$906))) -> 749.9028 | P104: =(IF(C104="Sim",IF(A104="Sim",$E$94,EY104),IF(A104="Sim",FA104,Geometria!$L$907))) -> 213.7223 | R104: σi,4 | S104: =F104 -> 6545.1725 | T104: kN/m² | U104: =S104/1000 -> 6.5451725 | V104: MPa | W104: =W103 -> 0 | X104: =IF(OR(AND(Y104<Geometria!$L$1405/100,Geometria!$K$1405>0),AND((Geometria!$L$29/100-Y104)<Geometria!$R$1405/100,Geometria!$Q$1405>0)),"Sim","Não") -> Sim | Y104: =Geometria!$N$415 -> 1.1775 | Z104: =IF(OR(AND(Y104<Geometria!$L$1409/100,OR(Geometria!$K$1409>0,Geometria!$K$1407>0)),AND((Geometria!$L$29/100-Y104)<Geometria!$R$1409/100,OR(Geometria!$Q$1409>0,Geometria!$Q$1407>0))),"Sim","Não") -> Não | AA104: σi,4 | AB104: =IF(Geometria!$N$437<Geometria!$N$1307/100,"Reduzir","OK") -> OK | AC104: =IF(AB104="Reduzir",AD104,AF104) -> -1801.6677 | AD104: =-(AI104/(Geometria!$L$48/100^2))+(AJ104/(Geometria!$L$52/100^3))-((Geometria!$N$416)/(Geometria!$L$52/100^3))-((Geometria!$N$427)/(Geometria!$M$52))-((Geometria!$L$76*Geometria!$N$438)/(Geometria!$M$52)) -> -2236.4779 | AE104: =((Geometria!$N$369*(Geometria!$N$897*100))/Geometria!$N$1307) -> 124.16252 | AF104: =-((Geometria!$L$373-(Geometria!$L$373-ER104)*(1-(MIN(MIN(1,MAX(0,(Y104-Geometria!$L$1409/100)/(Geometria!$N$1307/100))),MIN(1,MAX(0,((Geometria!$L$29/100-Y104)-Geometria!$R$1409/100)/(Geometria!$N$1307/100))))))*(IF(OR(Geometria!$K$1409>0,Geometria!$K$1407>0,Geometria!$Q$1409>0,Geometria!$Q$1407>0),1,0))-(Geometria!$L$373-ET104)*(1-(MIN(MIN(1,MAX(0,(Y104-Geometria!$L$1405/100)/(Geometria!$N$1307/100))),MIN(1,MAX(0,((Geometria!$L$29/100-Y104)-Geometria!$R$1405/100)/(Geometria!$N$1307/100))))))*(IF(OR(Geometria!$K$1405>0,Geometria!$K$1403>0,Geometria!$Q$1405>0,Geometria!$Q$1403>0),1,0))))/(Geometria!$L$48/100^2)+((Geometria!$L$374-(Geometria!$L$374-ES104)*(1-(MIN(MIN(1,MAX(0,(Y104-Geometria!$L$1409/100)/(Geometria!$N$1307/100))),MIN(1,MAX(0,((Geometria!$L$29/100-Y104)-Geometria!$R$1409/100)/(Geometria!$N$1307/100))))))*(IF(OR(Geometria!$K$1409>0,Geometria!$K$1407>0,Geometria!$Q$1409>0,Geometria!$Q$1407>0),1,0))-(Geometria!$L$374-EU104)*(1-(MIN(MIN(1,MAX(0,(Y104-Geometria!$L$1405/100)/(Geometria!$N$1307/100))),MIN(1,MAX(0,((Geometria!$L$29/100-Y104)-Geometria!$R$1405/100)/(Geometria!$N$1307/100))))))*(IF(OR(Geometria!$K$1405>0,Geometria!$K$1403>0,Geometria!$Q$1405>0,Geometria!$Q$1403>0),1,0))))/(Geometria!$L$52/100^3)-((Geometria!$N$416)/(Geometria!$L$52/100^3))-((Geometria!$N$427)/(Geometria!$M$52))-((Geometria!$L$76*Geometria!$N$438)/(Geometria!$M$52)) -> -1801.6677 | AI104: =(IF(Z104="Sim",IF(X104="Sim",IF(Y104<Geometria!$L$1405/100,Geometria!$L$1435,Geometria!$L$1476),IF(Y104<Geometria!$L$1409/100,Geometria!$L$1442,Geometria!$L$1460)),IF(X104="Sim",IF(Y104<Geometria!$L$1405/100,Geometria!$L$1444,Geometria!$L$1462),Geometria!$L$298)))*AE127+Geometria!$P$1429*AE104 -> 579.47396 | AJ104: =(IF(Z104="Sim",IF(X104="Sim",IF(Y104<Geometria!$L$1405/100,Geometria!$L$1435,Geometria!$L$1476),IF(Y104<Geometria!$L$1409/100,Geometria!$L$1442,Geometria!$L$1460)),IF(X104="Sim",IF(Y104<Geometria!$L$1405/100,Geometria!$L$1444,Geometria!$L$1462),Geometria!$L$298)))*AE127*(IF(Z104="Sim",IF(X104="Sim",IF(Y104<Geometria!$L$1405/100,Geometria!$L$1436,Geometria!$L$1484),IF(Y104<Geometria!$L$1409/100,Geometria!$L$1443,Geometria!$L$1461)),IF(X104="Sim",IF(Y104<Geometria!$L$1405/100,Geometria!$L$1445,Geometria!$L$1463),Geometria!$L$299)))/100-Geometria!$P$1429*AE104*Geometria!$L$1438/100 -> 165.15008 | AL104: =(IF(Z104="Sim",IF(X104="Sim",$AB$93,ER104),IF(X104="Sim",ET104,Geometria!$L$373))) -> 621.77981 | AM104: =(IF(Z104="Sim",IF(X104="Sim",$AB$94,ES104),IF(X104="Sim",EU104,Geometria!$L$374))) -> 177.20725 | AO104: σi,4 | AP104: =AC104 -> -1801.6677 | AQ104: kN/m² | AR104: =AP104/1000 -> -1.8016677 | AS104: MPa | AT104: =AT103 -> 0 | AU104: =IF(OR(AND(AV104<Geometria!$L$1405/100,Geometria!$K$1405>0),AND((Geometria!$L$29/100-AV104)<Geometria!$R$1405/100,Geometria!$Q$1405>0)),"Sim","Não") -> Sim | AV104: =Geometria!$N$415 -> 1.1775 | AW104: =IF(OR(AND(AV104<Geometria!$L$1409/100,OR(Geometria!$K$1409>0,Geometria!$K$1407>0)),AND((Geometria!$L$29/100-AV104)<Geometria!$R$1409/100,OR(Geometria!$Q$1409>0,Geometria!$Q$1407>0))),"Sim","Não") -> Não | AX104: σi,4 | AY104: =IF(Geometria!$N$437<Geometria!$N$1307/100,"Reduzir","OK") -> OK | AZ104: =IF(AY104="Reduzir",BA104,BC104) -> -1801.6626 | BA104: =-(BF104/(Geometria!$L$48/100^2))+(BG104/(Geometria!$L$52/100^3))-((Geometria!$N$416)/(Geometria!$L$52/100^3))-((Geometria!$N$427)/(Geometria!$M$52))-((Geometria!$L$76*Geometria!$N$438)/(Geometria!$M$52)) -> -2236.4779 | BB104: =((Geometria!$N$369*(Geometria!$N$897*100))/Geometria!$N$1307) -> 124.16252 | BC104: =-((Geometria!$L$373-(Geometria!$L$373-ER104)*(1-(MIN(MIN(1,MAX(0,(AV104-Geometria!$L$1409/100)/(Geometria!$N$1307/100))),MIN(1,MAX(0,((Geometria!$L$29/100-AV104)-Geometria!$R$1409/100)/(Geometria!$N$1307/100))))))*(IF(OR(Geometria!$K$1409>0,Geometria!$K$1407>0,Geometria!$Q$1409>0,Geometria!$Q$1407>0),1,0))-(Geometria!$L$373-ET104)*(1-(MIN(MIN(1,MAX(0,(AV104-Geometria!$L$1405/100)/(Geometria!$N$1307/100))),MIN(1,MAX(0,((Geometria!$L$29/100-AV104)-Geometria!$R$1405/100)/(Geometria!$N$1307/100))))))*(IF(OR(Geometria!$K$1405>0,Geometria!$K$1403>0,Geometria!$Q$1405>0,Geometria!$Q$1403>0),1,0))))/(Geometria!$L$48/100^2)+((Geometria!$L$374-(Geometria!$L$374-ES104)*(1-(MIN(MIN(1,MAX(0,(AV104-Geometria!$L$1409/100)/(Geometria!$N$1307/100))),MIN(1,MAX(0,((Geometria!$L$29/100-AV104)-Geometria!$R$1409/100)/(Geometria!$N$1307/100))))))*(IF(OR(Geometria!$K$1409>0,Geometria!$K$1407>0,Geometria!$Q$1409>0,Geometria!$Q$1407>0),1,0))-(Geometria!$L$374-EU104)*(1-(MIN(MIN(1,MAX(0,(AV104-Geometria!$L$1405/100)/(Geometria!$N$1307/100))),MIN(1,MAX(0,((Geometria!$L$29/100-AV104)-Geometria!$R$1405/100)/(Geometria!$N$1307/100))))))*(IF(OR(Geometria!$K$1405>0,Geometria!$K$1403>0,Geometria!$Q$1405>0,Geometria!$Q$1403>0),1,0))))/(Geometria!$L$52/100^3)-((Geometria!$N$416)/(Geometria!$L$52/100^3))-((Geometria!$N$427)/(Geometria!$M$52)) -> -1801.6626 | BF104: =(Geometria!$L$298-(Geometria!$L$298-IF(AV104<Geometria!$L$1409/100,Geometria!$L$1442,Geometria!$L$1460))*(1-(MIN(MIN(1,MAX(0,(AV104-Geometria!$L$1409/100)/(Geometria!$N$1307/100))),MIN(1,MAX(0,((Geometria!$L$29/100-AV104)-Geometria!$R$1409/100)/(Geometria!$N$1307/100))))))*(IF(OR(Geometria!$K$1409>0,Geometria!$K$1407>0,Geometria!$Q$1409>0,Geometria!$Q$1407>0),1,0))-(Geometria!$L$298-IF(AV104<Geometria!$L$1405/100,Geometria!$L$1444,Geometria!$L$1462))*(1-(MIN(MIN(1,MAX(0,(AV104-Geometria!$L$1405/100)/(Geometria!$N$1307/100))),MIN(1,MAX(0,((Geometria!$L$29/100-AV104)-Geometria!$R$1405/100)/(Geometria!$N$1307/100))))))*(IF(OR(Geometria!$K$1405>0,Geometria!$K$1403>0,Geometria!$Q$1405>0,Geometria!$Q$1403>0),1,0)))*BB127+Geometria!$P$1429*BB104 -> 579.47396 | BG104: =(Geometria!$L$298-(Geometria!$L$298-IF(AV104<Geometria!$L$1409/100,Geometria!$L$1442,Geometria!$L$1460))*(1-(MIN(MIN(1,MAX(0,(AV104-Geometria!$L$1409/100)/(Geometria!$N$1307/100))),MIN(1,MAX(0,((Geometria!$L$29/100-AV104)-Geometria!$R$1409/100)/(Geometria!$N$1307/100))))))*(IF(OR(Geometria!$K$1409>0,Geometria!$K$1407>0,Geometria!$Q$1409>0,Geometria!$Q$1407>0),1,0))-(Geometria!$L$298-IF(AV104<Geometria!$L$1405/100,Geometria!$L$1444,Geometria!$L$1462))*(1-(MIN(MIN(1,MAX(0,(AV104-Geometria!$L$1405/100)/(Geometria!$N$1307/100))),MIN(1,MAX(0,((Geometria!$L$29/100-AV104)-Geometria!$R$1405/100)/(Geometria!$N$1307/100))))))*(IF(OR(Geometria!$K$1405>0,Geometria!$K$1403>0,Geometria!$Q$1405>0,Geometria!$Q$1403>0),1,0)))*BB127*(Geometria!$L$299-(Geometria!$L$299-IF(AV104<Geometria!$L$1409/100,Geometria!$L$1443,Geometria!$L$1461))*(1-(MIN(MIN(1,MAX(0,(AV104-Geometria!$L$1409/100)/(Geometria!$N$1307/100))),MIN(1,MAX(0,((Geometria!$L$29/100-AV104)-Geometria!$R$1409/100)/(Geometria!$N$1307/100))))))*(IF(OR(Geometria!$K$1409>0,Geometria!$K$1407>0,Geometria!$Q$1409>0,Geometria!$Q$1407>0),1,0))-(Geometria!$L$299-IF(AV104<Geometria!$L$1405/100,Geometria!$L$1445,Geometria!$L$1463))*(1-(MIN(MIN(1,MAX(0,(AV104-Geometria!$L$1405/100)/(Geometria!$N$1307/100))),MIN(1,MAX(0,((Geometria!$L$29/100-AV104)-Geometria!$R$1405/100)/(Geometria!$N$1307/100))))))*(IF(OR(Geometria!$K$1405>0,Geometria!$K$1403>0,Geometria!$Q$1405>0,Geometria!$Q$1403>0),1,0)))/100-Geometria!$P$1429*BB104*Geometria!$L$1438/100 -> 165.15008 | BI104: =(IF(AW104="Sim",IF(AU104="Sim",$AB$93,ER104),IF(AU104="Sim",ET104,Geometria!$L$373))) -> 621.77981 | BJ104: =(IF(AW104="Sim",IF(AU104="Sim",$AB$94,ES104),IF(AU104="Sim",EU104,Geometria!$L$374))) -> 177.20725 | BL104: σi,4 | BM104: =AZ104 -> -1801.6626 | BN104: kN/m² | BO104: =BM104/1000 -> -1.8016626 | BP104: MPa | BQ104: =BQ103 -> 0 | BR104: =IF(OR(AND(BS104<Geometria!$L$1405/100,Geometria!$K$1405>0),AND((Geometria!$L$29/100-BS104)<Geometria!$R$1405/100,Geometria!$Q$1405>0)),"Sim","Não") -> Sim | BS104: =Geometria!$N$415 -> 1.1775 | BT104: =IF(OR(AND(BS104<Geometria!$L$1409/100,OR(Geometria!$K$1409>0,Geometria!$K$1407>0)),AND((Geometria!$L$29/100-BS104)<Geometria!$R$1409/100,OR(Geometria!$Q$1409>0,Geometria!$Q$1407>0))),"Sim","Não") -> Não | BU104: σi,4 | BV104: =IF(Geometria!$N$437<Geometria!$N$1307/100,"Reduzir","OK") -> OK | BW104: =IF(BV104="Reduzir",BX104,BZ104) -> -1801.666 | BX104: =-(CC104/(Geometria!$L$48/100^2))+(CD104/(Geometria!$L$52/100^3))-((Geometria!$N$416)/(Geometria!$L$52/100^3))-((Geometria!$N$427)/(Geometria!$M$52))-((Geometria!$L$76*Geometria!$N$438)/(Geometria!$M$52)) -> -2236.4779 | BY104: =((Geometria!$N$369*(Geometria!$N$897*100))/Geometria!$N$1307) -> 124.16252 | BZ104: =-((Geometria!$L$373-(Geometria!$L$373-ER104)*(1-(MIN(MIN(1,MAX(0,(BS104-Geometria!$L$1409/100)/(Geometria!$N$1307/100))),MIN(1,MAX(0,((Geometria!$L$29/100-BS104)-Geometria!$R$1409/100)/(Geometria!$N$1307/100))))))*(IF(OR(Geometria!$K$1409>0,Geometria!$K$1407>0,Geometria!$Q$1409>0,Geometria!$Q$1407>0),1,0))-(Geometria!$L$373-ET104)*(1-(MIN(MIN(1,MAX(0,(BS104-Geometria!$L$1405/100)/(Geometria!$N$1307/100))),MIN(1,MAX(0,((Geometria!$L$29/100-BS104)-Geometria!$R$1405/100)/(Geometria!$N$1307/100))))))*(IF(OR(Geometria!$K$1405>0,Geometria!$K$1403>0,Geometria!$Q$1405>0,Geometria!$Q$1403>0),1,0))))/(Geometria!$L$48/100^2)+((Geometria!$L$374-(Geometria!$L$374-ES104)*(1-(MIN(MIN(1,MAX(0,(BS104-Geometria!$L$1409/100)/(Geometria!$N$1307/100))),MIN(1,MAX(0,((Geometria!$L$29/100-BS104)-Geometria!$R$1409/100)/(Geometria!$N$1307/100))))))*(IF(OR(Geometria!$K$1409>0,Geometria!$K$1407>0,Geometria!$Q$1409>0,Geometria!$Q$1407>0),1,0))-(Geometria!$L$374-EU104)*(1-(MIN(MIN(1,MAX(0,(BS104-Geometria!$L$1405/100)/(Geometria!$N$1307/100))),MIN(1,MAX(0,((Geometria!$L$29/100-BS104)-Geometria!$R$1405/100)/(Geometria!$N$1307/100))))))*(IF(OR(Geometria!$K$1405>0,Geometria!$K$1403>0,Geometria!$Q$1405>0,Geometria!$Q$1403>0),1,0))))/(Geometria!$L$52/100^3)-((Geometria!$N$673)/(Geometria!$L$52/100^3))-((Geometria!$N$684)/(Geometria!$M$52))-((Geometria!$L$77*Geometria!$N$695)/(Geometria!$M$52)) -> -1801.666 | CC104: =(Geometria!$L$298-(Geometria!$L$298-IF(BS104<Geometria!$L$1409/100,Geometria!$L$1442,Geometria!$L$1460))*(1-(MIN(MIN(1,MAX(0,(BS104-Geometria!$L$1409/100)/(Geometria!$N$1307/100))),MIN(1,MAX(0,((Geometria!$L$29/100-BS104)-Geometria!$R$1409/100)/(Geometria!$N$1307/100))))))*(IF(OR(Geometria!$K$1409>0,Geometria!$K$1407>0,Geometria!$Q$1409>0,Geometria!$Q$1407>0),1,0))-(Geometria!$L$298-IF(BS104<Geometria!$L$1405/100,Geometria!$L$1444,Geometria!$L$1462))*(1-(MIN(MIN(1,MAX(0,(BS104-Geometria!$L$1405/100)/(Geometria!$N$1307/100))),MIN(1,MAX(0,((Geometria!$L$29/100-BS104)-Geometria!$R$1405/100)/(Geometria!$N$1307/100))))))*(IF(OR(Geometria!$K$1405>0,Geometria!$K$1403>0,Geometria!$Q$1405>0,Geometria!$Q$1403>0),1,0)))*BY127+Geometria!$P$1429*BY104 -> 579.47396 | CD104: =(Geometria!$L$298-(Geometria!$L$298-IF(BS104<Geometria!$L$1409/100,Geometria!$L$1442,Geometria!$L$1460))*(1-(MIN(MIN(1,MAX(0,(BS104-Geometria!$L$1409/100)/(Geometria!$N$1307/100))),MIN(1,MAX(0,((Geometria!$L$29/100-BS104)-Geometria!$R$1409/100)/(Geometria!$N$1307/100))))))*(IF(OR(Geometria!$K$1409>0,Geometria!$K$1407>0,Geometria!$Q$1409>0,Geometria!$Q$1407>0),1,0))-(Geometria!$L$298-IF(BS104<Geometria!$L$1405/100,Geometria!$L$1444,Geometria!$L$1462))*(1-(MIN(MIN(1,MAX(0,(BS104-Geometria!$L$1405/100)/(Geometria!$N$1307/100))),MIN(1,MAX(0,((Geometria!$L$29/100-BS104)-Geometria!$R$1405/100)/(Geometria!$N$1307/100))))))*(IF(OR(Geometria!$K$1405>0,Geometria!$K$1403>0,Geometria!$Q$1405>0,Geometria!$Q$1403>0),1,0)))*BY127*(Geometria!$L$299-(Geometria!$L$299-IF(BS104<Geometria!$L$1409/100,Geometria!$L$1443,Geometria!$L$1461))*(1-(MIN(MIN(1,MAX(0,(BS104-Geometria!$L$1409/100)/(Geometria!$N$1307/100))),MIN(1,MAX(0,((Geometria!$L$29/100-BS104)-Geometria!$R$1409/100)/(Geometria!$N$1307/100))))))*(IF(OR(Geometria!$K$1409>0,Geometria!$K$1407>0,Geometria!$Q$1409>0,Geometria!$Q$1407>0),1,0))-(Geometria!$L$299-IF(BS104<Geometria!$L$1405/100,Geometria!$L$1445,Geometria!$L$1463))*(1-(MIN(MIN(1,MAX(0,(BS104-Geometria!$L$1405/100)/(Geometria!$N$1307/100))),MIN(1,MAX(0,((Geometria!$L$29/100-BS104)-Geometria!$R$1405/100)/(Geometria!$N$1307/100))))))*(IF(OR(Geometria!$K$1405>0,Geometria!$K$1403>0,Geometria!$Q$1405>0,Geometria!$Q$1403>0),1,0)))/100-Geometria!$P$1429*BY104*Geometria!$L$1438/100 -> 165.15008 | CF104: =(IF(BT104="Sim",IF(BR104="Sim",$AB$93,ER104),IF(BR104="Sim",ET104,Geometria!$L$373))) -> 621.77981 | CG104: =(IF(BT104="Sim",IF(BR104="Sim",$AB$94,ES104),IF(BR104="Sim",EU104,Geometria!$L$374))) -> 177.20725 | CI104: σi,4 | CJ104: =BW104 -> -1801.666 | CK104: kN/m² | CL104: =CJ104/1000 -> -1.801666 | CM104: MPa | CN104: =CN103 -> 0 | CO104: =IF(OR(AND(CP104<Geometria!$L$1405/100,Geometria!$K$1405>0),AND((Geometria!$L$29/100-CP104)<Geometria!$R$1405/100,Geometria!$Q$1405>0)),"Sim","Não") -> Sim | CP104: =Geometria!$N$415 -> 1.1775 | CQ104: =IF(OR(AND(CP104<Geometria!$L$1409/100,OR(Geometria!$K$1409>0,Geometria!$K$1407>0)),AND((Geometria!$L$29/100-CP104)<Geometria!$R$1409/100,OR(Geometria!$Q$1409>0,Geometria!$Q$1407>0))),"Sim","Não") -> Não | CR104: σi,4 | CS104: =IF(Geometria!$N$437<Geometria!$N$1307/100,"Reduzir","OK") -> OK | CT104: =IF(CS104="Reduzir",CU104,CW104) -> -1801.6626 | CU104: =-(CZ104/(Geometria!$L$48/100^2))+(DA104/(Geometria!$L$52/100^3))-((Geometria!$N$416)/(Geometria!$L$52/100^3))-((Geometria!$N$427)/(Geometria!$M$52))-((Geometria!$L$76*Geometria!$N$438)/(Geometria!$M$52)) -> -2236.4779 | CV104: =((Geometria!$N$369*(Geometria!$N$897*100))/Geometria!$N$1307) -> 124.16252 | CW104: =-((Geometria!$L$373-(Geometria!$L$373-ER104)*(1-(MIN(MIN(1,MAX(0,(CP104-Geometria!$L$1409/100)/(Geometria!$N$1307/100))),MIN(1,MAX(0,((Geometria!$L$29/100-CP104)-Geometria!$R$1409/100)/(Geometria!$N$1307/100))))))*(IF(OR(Geometria!$K$1409>0,Geometria!$K$1407>0,Geometria!$Q$1409>0,Geometria!$Q$1407>0),1,0))-(Geometria!$L$373-ET104)*(1-(MIN(MIN(1,MAX(0,(CP104-Geometria!$L$1405/100)/(Geometria!$N$1307/100))),MIN(1,MAX(0,((Geometria!$L$29/100-CP104)-Geometria!$R$1405/100)/(Geometria!$N$1307/100))))))*(IF(OR(Geometria!$K$1405>0,Geometria!$K$1403>0,Geometria!$Q$1405>0,Geometria!$Q$1403>0),1,0))))/(Geometria!$L$48/100^2)+((Geometria!$L$374-(Geometria!$L$374-ES104)*(1-(MIN(MIN(1,MAX(0,(CP104-Geometria!$L$1409/100)/(Geometria!$N$1307/100))),MIN(1,MAX(0,((Geometria!$L$29/100-CP104)-Geometria!$R$1409/100)/(Geometria!$N$1307/100))))))*(IF(OR(Geometria!$K$1409>0,Geometria!$K$1407>0,Geometria!$Q$1409>0,Geometria!$Q$1407>0),1,0))-(Geometria!$L$374-EU104)*(1-(MIN(MIN(1,MAX(0,(CP104-Geometria!$L$1405/100)/(Geometria!$N$1307/100))),MIN(1,MAX(0,((Geometria!$L$29/100-CP104)-Geometria!$R$1405/100)/(Geometria!$N$1307/100))))))*(IF(OR(Geometria!$K$1405>0,Geometria!$K$1403>0,Geometria!$Q$1405>0,Geometria!$Q$1403>0),1,0))))/(Geometria!$L$52/100^3)-((Geometria!$N$673)/(Geometria!$L$52/100^3))-((Geometria!$N$684)/(Geometria!$M$52)) -> -1801.6626 | CZ104: =(IF(CQ104="Sim",IF(CO104="Sim",IF(CP104<Geometria!$L$1405/100,Geometria!$L$1435,Geometria!$L$1476),IF(CP104<Geometria!$L$1409/100,Geometria!$L$1442,Geometria!$L$1460)),IF(CO104="Sim",IF(CP104<Geometria!$L$1405/100,Geometria!$L$1444,Geometria!$L$1462),Geometria!$L$298)))*CV127+Geometria!$P$1429*CV104 -> 579.47396 | DA104: =(IF(CQ104="Sim",IF(CO104="Sim",IF(CP104<Geometria!$L$1405/100,Geometria!$L$1435,Geometria!$L$1476),IF(CP104<Geometria!$L$1409/100,Geometria!$L$1442,Geometria!$L$1460)),IF(CO104="Sim",IF(CP104<Geometria!$L$1405/100,Geometria!$L$1444,Geometria!$L$1462),Geometria!$L$298)))*CV127*(IF(CQ104="Sim",IF(CO104="Sim",IF(CP104<Geometria!$L$1405/100,Geometria!$L$1436,Geometria!$L$1484),IF(CP104<Geometria!$L$1409/100,Geometria!$L$1443,Geometria!$L$1461)),IF(CO104="Sim",IF(CP104<Geometria!$L$1405/100,Geometria!$L$1445,Geometria!$L$1463),Geometria!$L$299)))/100-Geometria!$P$1429*CV104*Geometria!$L$1438/100 -> 165.15008 | DC104: =(IF(CQ104="Sim",IF(CO104="Sim",$AB$93,ER104),IF(CO104="Sim",ET104,Geometria!$L$373))) -> 621.77981 | DD104: =(IF(CQ104="Sim",IF(CO104="Sim",$AB$94,ES104),IF(CO104="Sim",EU104,Geometria!$L$374))) -> 177.20725 | DF104: σi,4 | DG104: =CT104 -> -1801.6626 | DH104: kN/m² | DI104: =DG104/1000 -> -1.8016626 | DJ104: MPa | DK104: =DK103 -> 0 | EA104: =-L104/('Aberturas na Alma'!$M$112/100^2)+M104/('Aberturas na Alma'!$M$119/100^3)-Geometria!$L$898/('Aberturas na Alma'!$M$119/100^3) -> 5811.0866 | EB104: =-(IF(C104="Sim",IF(A104="Sim",$E$93,EX104),IF(A104="Sim",EZ104,Geometria!$L$906)))/('Aberturas na Alma'!$M$112/100^2)+(IF(C104="Sim",IF(A104="Sim",$E$94,EY104),IF(A104="Sim",FA104,Geometria!$L$907)))/('Aberturas na Alma'!$M$119/100^3)-Geometria!$N$898/('Aberturas na Alma'!$M$119/100^3) -> 5618.7399 | EC104: =IF(AND('Aberturas na Alma'!$M$18="NÃO DISPENSADO — furo deve ser verificado (cálculo abaixo)",OR(AND(B104>=('Aberturas na Alma'!$M$4-'Aberturas na Alma'!$M$7/2)/100,B104<=('Aberturas na Alma'!$M$4+'Aberturas na Alma'!$M$7/2)/100),ABS(B104-'Aberturas na Alma'!$M$4/100)<=Geometria!$L$29/4000)),IF(E104="Reduzir",EA104,EB104),F104) -> 6545.1725 | ED104: =-(AI104/('Aberturas na Alma'!$M$112/100^2))+(AJ104/('Aberturas na Alma'!$M$119/100^3))-((Geometria!$N$416)/('Aberturas na Alma'!$M$119/100^3))-((Geometria!$N$427)/('Aberturas na Alma'!$M$119/100^3))-((Geometria!$L$76*Geometria!$N$438)/('Aberturas na Alma'!$M$119/100^3)) -> -24531.103 | EE104: =-((IF(Z104="Sim",IF(X104="Sim",$AB$93,ER104),IF(X104="Sim",ET104,Geometria!$L$373)))/('Aberturas na Alma'!$M$112/100^2))+((IF(Z104="Sim",IF(X104="Sim",$AB$94,ES104),IF(X104="Sim",EU104,Geometria!$L$374)))/('Aberturas na Alma'!$M$119/100^3))-((Geometria!$N$416)/('Aberturas na Alma'!$M$119/100^3))-((Geometria!$N$427)/('Aberturas na Alma'!$M$119/100^3))-((Geometria!$L$76*Geometria!$N$438)/('Aberturas na Alma'!$M$119/100^3)) -> -24145.728 | EF104: =IF(AND('Aberturas na Alma'!$M$18="NÃO DISPENSADO — furo deve ser verificado (cálculo abaixo)",OR(AND(B104>=('Aberturas na Alma'!$M$4-'Aberturas na Alma'!$M$7/2)/100,B104<=('Aberturas na Alma'!$M$4+'Aberturas na Alma'!$M$7/2)/100),ABS(B104-'Aberturas na Alma'!$M$4/100)<=Geometria!$L$29/4000)),IF(AB104="Reduzir",ED104,EE104),AC104) -> -1801.6677 | EG104: =-(BF104/('Aberturas na Alma'!$M$112/100^2))+(BG104/('Aberturas na Alma'!$M$119/100^3))-((Geometria!$N$416)/('Aberturas na Alma'!$M$119/100^3))-((Geometria!$N$427)/('Aberturas na Alma'!$M$119/100^3))-((Geometria!$L$76*Geometria!$N$438)/('Aberturas na Alma'!$M$119/100^3)) -> -24531.103 | EH104: =-((IF(AW104="Sim",IF(AU104="Sim",$AB$93,ER104),IF(AU104="Sim",ET104,Geometria!$L$373)))/('Aberturas na Alma'!$M$112/100^2))+((IF(AW104="Sim",IF(AU104="Sim",$AB$94,ES104),IF(AU104="Sim",EU104,Geometria!$L$374)))/('Aberturas na Alma'!$M$119/100^3))-((Geometria!$N$416)/('Aberturas na Alma'!$M$119/100^3))-((Geometria!$N$427)/('Aberturas na Alma'!$M$119/100^3)) -> -4210.7774 | EI104: =IF(AND('Aberturas na Alma'!$M$18="NÃO DISPENSADO — furo deve ser verificado (cálculo abaixo)",OR(AND(B104>=('Aberturas na Alma'!$M$4-'Aberturas na Alma'!$M$7/2)/100,B104<=('Aberturas na Alma'!$M$4+'Aberturas na Alma'!$M$7/2)/100),ABS(B104-'Aberturas na Alma'!$M$4/100)<=Geometria!$L$29/4000)),IF(AY104="Reduzir",EG104,EH104),AZ104) -> -1801.6626 | EJ104: =-(CC104/('Aberturas na Alma'!$M$112/100^2))+(CD104/('Aberturas na Alma'!$M$119/100^3))-((Geometria!$N$416)/('Aberturas na Alma'!$M$119/100^3))-((Geometria!$N$427)/('Aberturas na Alma'!$M$119/100^3))-((Geometria!$L$76*Geometria!$N$438)/('Aberturas na Alma'!$M$119/100^3)) -> -24531.103 | EK104: =-((IF(BT104="Sim",IF(BR104="Sim",$AB$93,ER104),IF(BR104="Sim",ET104,Geometria!$L$373)))/('Aberturas na Alma'!$M$112/100^2))+((IF(BT104="Sim",IF(BR104="Sim",$AB$94,ES104),IF(BR104="Sim",EU104,Geometria!$L$374)))/('Aberturas na Alma'!$M$119/100^3))-((Geometria!$N$673)/('Aberturas na Alma'!$M$119/100^3))-((Geometria!$N$684)/('Aberturas na Alma'!$M$119/100^3))-((Geometria!$L$77*Geometria!$N$695)/('Aberturas na Alma'!$M$119/100^3)) -> -17500.745 | EL104: =IF(AND('Aberturas na Alma'!$M$18="NÃO DISPENSADO — furo deve ser verificado (cálculo abaixo)",OR(AND(B104>=('Aberturas na Alma'!$M$4-'Aberturas na Alma'!$M$7/2)/100,B104<=('Aberturas na Alma'!$M$4+'Aberturas na Alma'!$M$7/2)/100),ABS(B104-'Aberturas na Alma'!$M$4/100)<=Geometria!$L$29/4000)),IF(BV104="Reduzir",EJ104,EK104),BW104) -> -1801.666 | EM104: =-(CZ104/('Aberturas na Alma'!$M$112/100^2))+(DA104/('Aberturas na Alma'!$M$119/100^3))-((Geometria!$N$416)/('Aberturas na Alma'!$M$119/100^3))-((Geometria!$N$427)/('Aberturas na Alma'!$M$119/100^3))-((Geometria!$L$76*Geometria!$N$438)/('Aberturas na Alma'!$M$119/100^3)) -> -24531.103 | EN104: =-((IF(CQ104="Sim",IF(CO104="Sim",$AB$93,ER104),IF(CO104="Sim",ET104,Geometria!$L$373)))/('Aberturas na Alma'!$M$112/100^2))+((IF(CQ104="Sim",IF(CO104="Sim",$AB$94,ES104),IF(CO104="Sim",EU104,Geometria!$L$374)))/('Aberturas na Alma'!$M$119/100^3))-((Geometria!$N$673)/('Aberturas na Alma'!$M$119/100^3))-((Geometria!$N$684)/('Aberturas na Alma'!$M$119/100^3)) -> -4210.7774 | EO104: =IF(AND('Aberturas na Alma'!$M$18="NÃO DISPENSADO — furo deve ser verificado (cálculo abaixo)",OR(AND(B104>=('Aberturas na Alma'!$M$4-'Aberturas na Alma'!$M$7/2)/100,B104<=('Aberturas na Alma'!$M$4+'Aberturas na Alma'!$M$7/2)/100),ABS(B104-'Aberturas na Alma'!$M$4/100)<=Geometria!$L$29/4000)),IF(CS104="Reduzir",EM104,EN104),CT104) -> -1801.6626 | EP104: =IF(AND(Y104<Geometria!$L$1409/100,OR(Geometria!$K$1409>0,Geometria!$K$1407>0)),"ESQ",IF(AND((Geometria!$L$29/100-Y104)<Geometria!$R$1409/100,OR(Geometria!$Q$1409>0,Geometria!$Q$1407>0)),"DIR","N/A")) -> N/A | EQ104: =IF(AND(Y104<Geometria!$L$1405/100,Geometria!$K$1405>0),"ESQ",IF(AND((Geometria!$L$29/100-Y104)<Geometria!$R$1405/100,Geometria!$Q$1405>0),"DIR","N/A")) -> ESQ | ER104: =IF(EP104="DIR",Geometria!$L$1470,Geometria!$L$1452) -> 1243.5596 | ES104: =IF(EP104="DIR",Geometria!$L$1471,Geometria!$L$1453) -> 233.16743 | ET104: =IF(EQ104="DIR",Geometria!$L$1472,Geometria!$L$1454) -> 621.77981 | EU104: =IF(EQ104="DIR",Geometria!$L$1473,Geometria!$L$1455) -> 177.20725 | EV104: =IF(AND(B104<Geometria!$L$1409/100,OR(Geometria!$K$1409>0,Geometria!$K$1407>0)),"ESQ",IF(AND((Geometria!$L$29/100-B104)<Geometria!$R$1409/100,OR(Geometria!$Q$1409>0,Geometria!$Q$1407>0)),"DIR","N/A")) -> N/A | EW104: =IF(AND(B104<Geometria!$L$1405/100,Geometria!$K$1405>0),"ESQ",IF(AND((Geometria!$L$29/100-B104)<Geometria!$R$1405/100,Geometria!$Q$1405>0),"DIR","N/A")) -> ESQ | EX104: =IF(EV104="DIR",Geometria!$L$1465,Geometria!$L$1447) -> 1499.8056 | EY104: =IF(EV104="DIR",Geometria!$L$1466,Geometria!$L$1448) -> 281.21355 | EZ104: =IF(EW104="DIR",Geometria!$L$1467,Geometria!$L$1449) -> 749.9028 | FA104: =IF(EW104="DIR",Geometria!$L$1468,Geometria!$L$1450) -> 213.7223
A105: =IF(OR(AND(B105<Geometria!$L$1405/100,Geometria!$K$1405>0),AND((Geometria!$L$29/100-B105)<Geometria!$R$1405/100,Geometria!$Q$1405>0)),"Sim","Não") -> Sim | B105: =Tensões!$F$63 -> 1.57 | C105: =IF(OR(AND(B105<Geometria!$L$1409/100,OR(Geometria!$K$1409>0,Geometria!$K$1407>0)),AND((Geometria!$L$29/100-B105)<Geometria!$R$1409/100,OR(Geometria!$Q$1409>0,Geometria!$Q$1407>0))),"Sim","Não") -> Não | D105: σi,5 | E105: =IF(Geometria!$O$437<Geometria!$N$1307/100,"Reduzir","OK") -> OK | F105: =IF(E105="Reduzir",G105,I105) -> 6248.9352 | G105: =-L105/(Geometria!$L$48/100^2)+M105/(Geometria!$L$52/100^3)-Geometria!$L$898/(Geometria!$L$52/100^3) -> 8988.514 | H105: =((Geometria!$L$326*(Geometria!$O$897*100))/Geometria!$N$1307) -> 195.91675 | I105: =-(Geometria!$L$906-(Geometria!$L$906-EX105)*(1-(MIN(MIN(1,MAX(0,(B105-Geometria!$L$1409/100)/(Geometria!$N$1307/100))),MIN(1,MAX(0,((Geometria!$L$29/100-B105)-Geometria!$R$1409/100)/(Geometria!$N$1307/100))))))*(IF(OR(Geometria!$K$1409>0,Geometria!$K$1407>0,Geometria!$Q$1409>0,Geometria!$Q$1407>0),1,0))-(Geometria!$L$906-EZ105)*(1-(MIN(MIN(1,MAX(0,(B105-Geometria!$L$1405/100)/(Geometria!$N$1307/100))),MIN(1,MAX(0,((Geometria!$L$29/100-B105)-Geometria!$R$1405/100)/(Geometria!$N$1307/100))))))*(IF(OR(Geometria!$K$1405>0,Geometria!$K$1403>0,Geometria!$Q$1405>0,Geometria!$Q$1403>0),1,0)))/(Geometria!$L$48/100^2)+(Geometria!$L$907-(Geometria!$L$907-EY105)*(1-(MIN(MIN(1,MAX(0,(B105-Geometria!$L$1409/100)/(Geometria!$N$1307/100))),MIN(1,MAX(0,((Geometria!$L$29/100-B105)-Geometria!$R$1409/100)/(Geometria!$N$1307/100))))))*(IF(OR(Geometria!$K$1409>0,Geometria!$K$1407>0,Geometria!$Q$1409>0,Geometria!$Q$1407>0),1,0))-(Geometria!$L$907-FA105)*(1-(MIN(MIN(1,MAX(0,(B105-Geometria!$L$1405/100)/(Geometria!$N$1307/100))),MIN(1,MAX(0,((Geometria!$L$29/100-B105)-Geometria!$R$1405/100)/(Geometria!$N$1307/100))))))*(IF(OR(Geometria!$K$1405>0,Geometria!$K$1403>0,Geometria!$Q$1405>0,Geometria!$Q$1403>0),1,0)))/(Geometria!$L$52/100^3)-Geometria!$O$898/(Geometria!$L$52/100^3) -> 6248.9352 | L105: =(Geometria!$L$298-(Geometria!$L$298-IF(B105<Geometria!$L$1409/100,Geometria!$L$1442,Geometria!$L$1460))*(1-(MIN(MIN(1,MAX(0,(B105-Geometria!$L$1409/100)/(Geometria!$N$1307/100))),MIN(1,MAX(0,((Geometria!$L$29/100-B105)-Geometria!$R$1409/100)/(Geometria!$N$1307/100))))))*(IF(OR(Geometria!$K$1409>0,Geometria!$K$1407>0,Geometria!$Q$1409>0,Geometria!$Q$1407>0),1,0))-(Geometria!$L$298-IF(B105<Geometria!$L$1405/100,Geometria!$L$1444,Geometria!$L$1462))*(1-(MIN(MIN(1,MAX(0,(B105-Geometria!$L$1405/100)/(Geometria!$N$1307/100))),MIN(1,MAX(0,((Geometria!$L$29/100-B105)-Geometria!$R$1405/100)/(Geometria!$N$1307/100))))))*(IF(OR(Geometria!$K$1405>0,Geometria!$K$1403>0,Geometria!$Q$1405>0,Geometria!$Q$1403>0),1,0)))*H128+Geometria!$P$1429*H105 -> 916.68418 | M105: =(Geometria!$L$298-(Geometria!$L$298-IF(B105<Geometria!$L$1409/100,Geometria!$L$1442,Geometria!$L$1460))*(1-(MIN(MIN(1,MAX(0,(B105-Geometria!$L$1409/100)/(Geometria!$N$1307/100))),MIN(1,MAX(0,((Geometria!$L$29/100-B105)-Geometria!$R$1409/100)/(Geometria!$N$1307/100))))))*(IF(OR(Geometria!$K$1409>0,Geometria!$K$1407>0,Geometria!$Q$1409>0,Geometria!$Q$1407>0),1,0))-(Geometria!$L$298-IF(B105<Geometria!$L$1405/100,Geometria!$L$1444,Geometria!$L$1462))*(1-(MIN(MIN(1,MAX(0,(B105-Geometria!$L$1405/100)/(Geometria!$N$1307/100))),MIN(1,MAX(0,((Geometria!$L$29/100-B105)-Geometria!$R$1405/100)/(Geometria!$N$1307/100))))))*(IF(OR(Geometria!$K$1405>0,Geometria!$K$1403>0,Geometria!$Q$1405>0,Geometria!$Q$1403>0),1,0)))*H128*(Geometria!$L$299-(Geometria!$L$299-IF(B105<Geometria!$L$1409/100,Geometria!$L$1443,Geometria!$L$1461))*(1-(MIN(MIN(1,MAX(0,(B105-Geometria!$L$1409/100)/(Geometria!$N$1307/100))),MIN(1,MAX(0,((Geometria!$L$29/100-B105)-Geometria!$R$1409/100)/(Geometria!$N$1307/100))))))*(IF(OR(Geometria!$K$1409>0,Geometria!$K$1407>0,Geometria!$Q$1409>0,Geometria!$Q$1407>0),1,0))-(Geometria!$L$299-IF(B105<Geometria!$L$1405/100,Geometria!$L$1445,Geometria!$L$1463))*(1-(MIN(MIN(1,MAX(0,(B105-Geometria!$L$1405/100)/(Geometria!$N$1307/100))),MIN(1,MAX(0,((Geometria!$L$29/100-B105)-Geometria!$R$1405/100)/(Geometria!$N$1307/100))))))*(IF(OR(Geometria!$K$1405>0,Geometria!$K$1403>0,Geometria!$Q$1405>0,Geometria!$Q$1403>0),1,0)))/100-Geometria!$P$1429*H105*Geometria!$L$1438/100 -> 261.25499 | O105: =(IF(C105="Sim",IF(A105="Sim",$E$93,EX105),IF(A105="Sim",EZ105,Geometria!$L$906))) -> 749.9028 | P105: =(IF(C105="Sim",IF(A105="Sim",$E$94,EY105),IF(A105="Sim",FA105,Geometria!$L$907))) -> 213.7223 | R105: σi,5 | S105: =F105 -> 6248.9352 | T105: kN/m² | U105: =S105/1000 -> 6.2489352 | V105: MPa | W105: =W104 -> 0 | X105: =IF(OR(AND(Y105<Geometria!$L$1405/100,Geometria!$K$1405>0),AND((Geometria!$L$29/100-Y105)<Geometria!$R$1405/100,Geometria!$Q$1405>0)),"Sim","Não") -> Sim | Y105: =Geometria!$O$415 -> 1.57 | Z105: =IF(OR(AND(Y105<Geometria!$L$1409/100,OR(Geometria!$K$1409>0,Geometria!$K$1407>0)),AND((Geometria!$L$29/100-Y105)<Geometria!$R$1409/100,OR(Geometria!$Q$1409>0,Geometria!$Q$1407>0))),"Sim","Não") -> Não | AA105: σi,5 | AB105: =IF(Geometria!$O$437<Geometria!$N$1307/100,"Reduzir","OK") -> OK | AC105: =IF(AB105="Reduzir",AD105,AF105) -> -3889.8711 | AD105: =-(AI105/(Geometria!$L$48/100^2))+(AJ105/(Geometria!$L$52/100^3))-((Geometria!$O$416)/(Geometria!$L$52/100^3))-((Geometria!$O$427)/(Geometria!$M$52))-((Geometria!$L$76*Geometria!$O$438)/(Geometria!$M$52)) -> -3889.8711 | AE105: =((Geometria!$N$369*(Geometria!$O$897*100))/Geometria!$N$1307) -> 165.55003 | AF105: =-((Geometria!$L$373-(Geometria!$L$373-ER105)*(1-(MIN(MIN(1,MAX(0,(Y105-Geometria!$L$1409/100)/(Geometria!$N$1307/100))),MIN(1,MAX(0,((Geometria!$L$29/100-Y105)-Geometria!$R$1409/100)/(Geometria!$N$1307/100))))))*(IF(OR(Geometria!$K$1409>0,Geometria!$K$1407>0,Geometria!$Q$1409>0,Geometria!$Q$1407>0),1,0))-(Geometria!$L$373-ET105)*(1-(MIN(MIN(1,MAX(0,(Y105-Geometria!$L$1405/100)/(Geometria!$N$1307/100))),MIN(1,MAX(0,((Geometria!$L$29/100-Y105)-Geometria!$R$1405/100)/(Geometria!$N$1307/100))))))*(IF(OR(Geometria!$K$1405>0,Geometria!$K$1403>0,Geometria!$Q$1405>0,Geometria!$Q$1403>0),1,0))))/(Geometria!$L$48/100^2)+((Geometria!$L$374-(Geometria!$L$374-ES105)*(1-(MIN(MIN(1,MAX(0,(Y105-Geometria!$L$1409/100)/(Geometria!$N$1307/100))),MIN(1,MAX(0,((Geometria!$L$29/100-Y105)-Geometria!$R$1409/100)/(Geometria!$N$1307/100))))))*(IF(OR(Geometria!$K$1409>0,Geometria!$K$1407>0,Geometria!$Q$1409>0,Geometria!$Q$1407>0),1,0))-(Geometria!$L$374-EU105)*(1-(MIN(MIN(1,MAX(0,(Y105-Geometria!$L$1405/100)/(Geometria!$N$1307/100))),MIN(1,MAX(0,((Geometria!$L$29/100-Y105)-Geometria!$R$1405/100)/(Geometria!$N$1307/100))))))*(IF(OR(Geometria!$K$1405>0,Geometria!$K$1403>0,Geometria!$Q$1405>0,Geometria!$Q$1403>0),1,0))))/(Geometria!$L$52/100^3)-((Geometria!$O$416)/(Geometria!$L$52/100^3))-((Geometria!$O$427)/(Geometria!$M$52))-((Geometria!$L$76*Geometria!$O$438)/(Geometria!$M$52)) -> -3889.8711 | AI105: =(IF(Z105="Sim",IF(X105="Sim",IF(Y105<Geometria!$L$1405/100,Geometria!$L$1435,Geometria!$L$1476),IF(Y105<Geometria!$L$1409/100,Geometria!$L$1442,Geometria!$L$1460)),IF(X105="Sim",IF(Y105<Geometria!$L$1405/100,Geometria!$L$1444,Geometria!$L$1462),Geometria!$L$298)))*AE128+Geometria!$P$1429*AE105 -> 621.77981 | AJ105: =(IF(Z105="Sim",IF(X105="Sim",IF(Y105<Geometria!$L$1405/100,Geometria!$L$1435,Geometria!$L$1476),IF(Y105<Geometria!$L$1409/100,Geometria!$L$1442,Geometria!$L$1460)),IF(X105="Sim",IF(Y105<Geometria!$L$1405/100,Geometria!$L$1444,Geometria!$L$1462),Geometria!$L$298)))*AE128*(IF(Z105="Sim",IF(X105="Sim",IF(Y105<Geometria!$L$1405/100,Geometria!$L$1436,Geometria!$L$1484),IF(Y105<Geometria!$L$1409/100,Geometria!$L$1443,Geometria!$L$1461)),IF(X105="Sim",IF(Y105<Geometria!$L$1405/100,Geometria!$L$1445,Geometria!$L$1463),Geometria!$L$299)))/100-Geometria!$P$1429*AE105*Geometria!$L$1438/100 -> 177.20725 | AL105: =(IF(Z105="Sim",IF(X105="Sim",$AB$93,ER105),IF(X105="Sim",ET105,Geometria!$L$373))) -> 621.77981 | AM105: =(IF(Z105="Sim",IF(X105="Sim",$AB$94,ES105),IF(X105="Sim",EU105,Geometria!$L$374))) -> 177.20725 | AO105: σi,5 | AP105: =AC105 -> -3889.8711 | AQ105: kN/m² | AR105: =AP105/1000 -> -3.8898711 | AS105: MPa | AT105: =AT104 -> 0 | AU105: =IF(OR(AND(AV105<Geometria!$L$1405/100,Geometria!$K$1405>0),AND((Geometria!$L$29/100-AV105)<Geometria!$R$1405/100,Geometria!$Q$1405>0)),"Sim","Não") -> Sim | AV105: =Geometria!$O$415 -> 1.57 | AW105: =IF(OR(AND(AV105<Geometria!$L$1409/100,OR(Geometria!$K$1409>0,Geometria!$K$1407>0)),AND((Geometria!$L$29/100-AV105)<Geometria!$R$1409/100,OR(Geometria!$Q$1409>0,Geometria!$Q$1407>0))),"Sim","Não") -> Não | AX105: σi,5 | AY105: =IF(Geometria!$O$437<Geometria!$N$1307/100,"Reduzir","OK") -> OK | AZ105: =IF(AY105="Reduzir",BA105,BC105) -> -3889.8647 | BA105: =-(BF105/(Geometria!$L$48/100^2))+(BG105/(Geometria!$L$52/100^3))-((Geometria!$O$416)/(Geometria!$L$52/100^3))-((Geometria!$O$427)/(Geometria!$M$52))-((Geometria!$L$76*Geometria!$O$438)/(Geometria!$M$52)) -> -3889.8711 | BB105: =((Geometria!$N$369*(Geometria!$O$897*100))/Geometria!$N$1307) -> 165.55003 | BC105: =-((Geometria!$L$373-(Geometria!$L$373-ER105)*(1-(MIN(MIN(1,MAX(0,(AV105-Geometria!$L$1409/100)/(Geometria!$N$1307/100))),MIN(1,MAX(0,((Geometria!$L$29/100-AV105)-Geometria!$R$1409/100)/(Geometria!$N$1307/100))))))*(IF(OR(Geometria!$K$1409>0,Geometria!$K$1407>0,Geometria!$Q$1409>0,Geometria!$Q$1407>0),1,0))-(Geometria!$L$373-ET105)*(1-(MIN(MIN(1,MAX(0,(AV105-Geometria!$L$1405/100)/(Geometria!$N$1307/100))),MIN(1,MAX(0,((Geometria!$L$29/100-AV105)-Geometria!$R$1405/100)/(Geometria!$N$1307/100))))))*(IF(OR(Geometria!$K$1405>0,Geometria!$K$1403>0,Geometria!$Q$1405>0,Geometria!$Q$1403>0),1,0))))/(Geometria!$L$48/100^2)+((Geometria!$L$374-(Geometria!$L$374-ES105)*(1-(MIN(MIN(1,MAX(0,(AV105-Geometria!$L$1409/100)/(Geometria!$N$1307/100))),MIN(1,MAX(0,((Geometria!$L$29/100-AV105)-Geometria!$R$1409/100)/(Geometria!$N$1307/100))))))*(IF(OR(Geometria!$K$1409>0,Geometria!$K$1407>0,Geometria!$Q$1409>0,Geometria!$Q$1407>0),1,0))-(Geometria!$L$374-EU105)*(1-(MIN(MIN(1,MAX(0,(AV105-Geometria!$L$1405/100)/(Geometria!$N$1307/100))),MIN(1,MAX(0,((Geometria!$L$29/100-AV105)-Geometria!$R$1405/100)/(Geometria!$N$1307/100))))))*(IF(OR(Geometria!$K$1405>0,Geometria!$K$1403>0,Geometria!$Q$1405>0,Geometria!$Q$1403>0),1,0))))/(Geometria!$L$52/100^3)-((Geometria!$O$416)/(Geometria!$L$52/100^3))-((Geometria!$O$427)/(Geometria!$M$52)) -> -3889.8647 | BF105: =(Geometria!$L$298-(Geometria!$L$298-IF(AV105<Geometria!$L$1409/100,Geometria!$L$1442,Geometria!$L$1460))*(1-(MIN(MIN(1,MAX(0,(AV105-Geometria!$L$1409/100)/(Geometria!$N$1307/100))),MIN(1,MAX(0,((Geometria!$L$29/100-AV105)-Geometria!$R$1409/100)/(Geometria!$N$1307/100))))))*(IF(OR(Geometria!$K$1409>0,Geometria!$K$1407>0,Geometria!$Q$1409>0,Geometria!$Q$1407>0),1,0))-(Geometria!$L$298-IF(AV105<Geometria!$L$1405/100,Geometria!$L$1444,Geometria!$L$1462))*(1-(MIN(MIN(1,MAX(0,(AV105-Geometria!$L$1405/100)/(Geometria!$N$1307/100))),MIN(1,MAX(0,((Geometria!$L$29/100-AV105)-Geometria!$R$1405/100)/(Geometria!$N$1307/100))))))*(IF(OR(Geometria!$K$1405>0,Geometria!$K$1403>0,Geometria!$Q$1405>0,Geometria!$Q$1403>0),1,0)))*BB128+Geometria!$P$1429*BB105 -> 621.77981 | BG105: =(Geometria!$L$298-(Geometria!$L$298-IF(AV105<Geometria!$L$1409/100,Geometria!$L$1442,Geometria!$L$1460))*(1-(MIN(MIN(1,MAX(0,(AV105-Geometria!$L$1409/100)/(Geometria!$N$1307/100))),MIN(1,MAX(0,((Geometria!$L$29/100-AV105)-Geometria!$R$1409/100)/(Geometria!$N$1307/100))))))*(IF(OR(Geometria!$K$1409>0,Geometria!$K$1407>0,Geometria!$Q$1409>0,Geometria!$Q$1407>0),1,0))-(Geometria!$L$298-IF(AV105<Geometria!$L$1405/100,Geometria!$L$1444,Geometria!$L$1462))*(1-(MIN(MIN(1,MAX(0,(AV105-Geometria!$L$1405/100)/(Geometria!$N$1307/100))),MIN(1,MAX(0,((Geometria!$L$29/100-AV105)-Geometria!$R$1405/100)/(Geometria!$N$1307/100))))))*(IF(OR(Geometria!$K$1405>0,Geometria!$K$1403>0,Geometria!$Q$1405>0,Geometria!$Q$1403>0),1,0)))*BB128*(Geometria!$L$299-(Geometria!$L$299-IF(AV105<Geometria!$L$1409/100,Geometria!$L$1443,Geometria!$L$1461))*(1-(MIN(MIN(1,MAX(0,(AV105-Geometria!$L$1409/100)/(Geometria!$N$1307/100))),MIN(1,MAX(0,((Geometria!$L$29/100-AV105)-Geometria!$R$1409/100)/(Geometria!$N$1307/100))))))*(IF(OR(Geometria!$K$1409>0,Geometria!$K$1407>0,Geometria!$Q$1409>0,Geometria!$Q$1407>0),1,0))-(Geometria!$L$299-IF(AV105<Geometria!$L$1405/100,Geometria!$L$1445,Geometria!$L$1463))*(1-(MIN(MIN(1,MAX(0,(AV105-Geometria!$L$1405/100)/(Geometria!$N$1307/100))),MIN(1,MAX(0,((Geometria!$L$29/100-AV105)-Geometria!$R$1405/100)/(Geometria!$N$1307/100))))))*(IF(OR(Geometria!$K$1405>0,Geometria!$K$1403>0,Geometria!$Q$1405>0,Geometria!$Q$1403>0),1,0)))/100-Geometria!$P$1429*BB105*Geometria!$L$1438/100 -> 177.20725 | BI105: =(IF(AW105="Sim",IF(AU105="Sim",$AB$93,ER105),IF(AU105="Sim",ET105,Geometria!$L$373))) -> 621.77981 | BJ105: =(IF(AW105="Sim",IF(AU105="Sim",$AB$94,ES105),IF(AU105="Sim",EU105,Geometria!$L$374))) -> 177.20725 | BL105: σi,5 | BM105: =AZ105 -> -3889.8647 | BN105: kN/m² | BO105: =BM105/1000 -> -3.8898647 | BP105: MPa | BQ105: =BQ104 -> 0 | BR105: =IF(OR(AND(BS105<Geometria!$L$1405/100,Geometria!$K$1405>0),AND((Geometria!$L$29/100-BS105)<Geometria!$R$1405/100,Geometria!$Q$1405>0)),"Sim","Não") -> Sim | BS105: =Geometria!$O$415 -> 1.57 | BT105: =IF(OR(AND(BS105<Geometria!$L$1409/100,OR(Geometria!$K$1409>0,Geometria!$K$1407>0)),AND((Geometria!$L$29/100-BS105)<Geometria!$R$1409/100,OR(Geometria!$Q$1409>0,Geometria!$Q$1407>0))),"Sim","Não") -> Não | BU105: σi,5 | BV105: =IF(Geometria!$O$437<Geometria!$N$1307/100,"Reduzir","OK") -> OK | BW105: =IF(BV105="Reduzir",BX105,BZ105) -> -3889.8689 | BX105: =-(CC105/(Geometria!$L$48/100^2))+(CD105/(Geometria!$L$52/100^3))-((Geometria!$O$416)/(Geometria!$L$52/100^3))-((Geometria!$O$427)/(Geometria!$M$52))-((Geometria!$L$76*Geometria!$O$438)/(Geometria!$M$52)) -> -3889.8711 | BY105: =((Geometria!$N$369*(Geometria!$O$897*100))/Geometria!$N$1307) -> 165.55003 | BZ105: =-((Geometria!$L$373-(Geometria!$L$373-ER105)*(1-(MIN(MIN(1,MAX(0,(BS105-Geometria!$L$1409/100)/(Geometria!$N$1307/100))),MIN(1,MAX(0,((Geometria!$L$29/100-BS105)-Geometria!$R$1409/100)/(Geometria!$N$1307/100))))))*(IF(OR(Geometria!$K$1409>0,Geometria!$K$1407>0,Geometria!$Q$1409>0,Geometria!$Q$1407>0),1,0))-(Geometria!$L$373-ET105)*(1-(MIN(MIN(1,MAX(0,(BS105-Geometria!$L$1405/100)/(Geometria!$N$1307/100))),MIN(1,MAX(0,((Geometria!$L$29/100-BS105)-Geometria!$R$1405/100)/(Geometria!$N$1307/100))))))*(IF(OR(Geometria!$K$1405>0,Geometria!$K$1403>0,Geometria!$Q$1405>0,Geometria!$Q$1403>0),1,0))))/(Geometria!$L$48/100^2)+((Geometria!$L$374-(Geometria!$L$374-ES105)*(1-(MIN(MIN(1,MAX(0,(BS105-Geometria!$L$1409/100)/(Geometria!$N$1307/100))),MIN(1,MAX(0,((Geometria!$L$29/100-BS105)-Geometria!$R$1409/100)/(Geometria!$N$1307/100))))))*(IF(OR(Geometria!$K$1409>0,Geometria!$K$1407>0,Geometria!$Q$1409>0,Geometria!$Q$1407>0),1,0))-(Geometria!$L$374-EU105)*(1-(MIN(MIN(1,MAX(0,(BS105-Geometria!$L$1405/100)/(Geometria!$N$1307/100))),MIN(1,MAX(0,((Geometria!$L$29/100-BS105)-Geometria!$R$1405/100)/(Geometria!$N$1307/100))))))*(IF(OR(Geometria!$K$1405>0,Geometria!$K$1403>0,Geometria!$Q$1405>0,Geometria!$Q$1403>0),1,0))))/(Geometria!$L$52/100^3)-((Geometria!$O$673)/(Geometria!$L$52/100^3))-((Geometria!$O$684)/(Geometria!$M$52))-((Geometria!$L$77*Geometria!$O$695)/(Geometria!$M$52)) -> -3889.8689 | CC105: =(Geometria!$L$298-(Geometria!$L$298-IF(BS105<Geometria!$L$1409/100,Geometria!$L$1442,Geometria!$L$1460))*(1-(MIN(MIN(1,MAX(0,(BS105-Geometria!$L$1409/100)/(Geometria!$N$1307/100))),MIN(1,MAX(0,((Geometria!$L$29/100-BS105)-Geometria!$R$1409/100)/(Geometria!$N$1307/100))))))*(IF(OR(Geometria!$K$1409>0,Geometria!$K$1407>0,Geometria!$Q$1409>0,Geometria!$Q$1407>0),1,0))-(Geometria!$L$298-IF(BS105<Geometria!$L$1405/100,Geometria!$L$1444,Geometria!$L$1462))*(1-(MIN(MIN(1,MAX(0,(BS105-Geometria!$L$1405/100)/(Geometria!$N$1307/100))),MIN(1,MAX(0,((Geometria!$L$29/100-BS105)-Geometria!$R$1405/100)/(Geometria!$N$1307/100))))))*(IF(OR(Geometria!$K$1405>0,Geometria!$K$1403>0,Geometria!$Q$1405>0,Geometria!$Q$1403>0),1,0)))*BY128+Geometria!$P$1429*BY105 -> 621.77981 | CD105: =(Geometria!$L$298-(Geometria!$L$298-IF(BS105<Geometria!$L$1409/100,Geometria!$L$1442,Geometria!$L$1460))*(1-(MIN(MIN(1,MAX(0,(BS105-Geometria!$L$1409/100)/(Geometria!$N$1307/100))),MIN(1,MAX(0,((Geometria!$L$29/100-BS105)-Geometria!$R$1409/100)/(Geometria!$N$1307/100))))))*(IF(OR(Geometria!$K$1409>0,Geometria!$K$1407>0,Geometria!$Q$1409>0,Geometria!$Q$1407>0),1,0))-(Geometria!$L$298-IF(BS105<Geometria!$L$1405/100,Geometria!$L$1444,Geometria!$L$1462))*(1-(MIN(MIN(1,MAX(0,(BS105-Geometria!$L$1405/100)/(Geometria!$N$1307/100))),MIN(1,MAX(0,((Geometria!$L$29/100-BS105)-Geometria!$R$1405/100)/(Geometria!$N$1307/100))))))*(IF(OR(Geometria!$K$1405>0,Geometria!$K$1403>0,Geometria!$Q$1405>0,Geometria!$Q$1403>0),1,0)))*BY128*(Geometria!$L$299-(Geometria!$L$299-IF(BS105<Geometria!$L$1409/100,Geometria!$L$1443,Geometria!$L$1461))*(1-(MIN(MIN(1,MAX(0,(BS105-Geometria!$L$1409/100)/(Geometria!$N$1307/100))),MIN(1,MAX(0,((Geometria!$L$29/100-BS105)-Geometria!$R$1409/100)/(Geometria!$N$1307/100))))))*(IF(OR(Geometria!$K$1409>0,Geometria!$K$1407>0,Geometria!$Q$1409>0,Geometria!$Q$1407>0),1,0))-(Geometria!$L$299-IF(BS105<Geometria!$L$1405/100,Geometria!$L$1445,Geometria!$L$1463))*(1-(MIN(MIN(1,MAX(0,(BS105-Geometria!$L$1405/100)/(Geometria!$N$1307/100))),MIN(1,MAX(0,((Geometria!$L$29/100-BS105)-Geometria!$R$1405/100)/(Geometria!$N$1307/100))))))*(IF(OR(Geometria!$K$1405>0,Geometria!$K$1403>0,Geometria!$Q$1405>0,Geometria!$Q$1403>0),1,0)))/100-Geometria!$P$1429*BY105*Geometria!$L$1438/100 -> 177.20725 | CF105: =(IF(BT105="Sim",IF(BR105="Sim",$AB$93,ER105),IF(BR105="Sim",ET105,Geometria!$L$373))) -> 621.77981 | CG105: =(IF(BT105="Sim",IF(BR105="Sim",$AB$94,ES105),IF(BR105="Sim",EU105,Geometria!$L$374))) -> 177.20725 | CI105: σi,5 | CJ105: =BW105 -> -3889.8689 | CK105: kN/m² | CL105: =CJ105/1000 -> -3.8898689 | CM105: MPa | CN105: =CN104 -> 0 | CO105: =IF(OR(AND(CP105<Geometria!$L$1405/100,Geometria!$K$1405>0),AND((Geometria!$L$29/100-CP105)<Geometria!$R$1405/100,Geometria!$Q$1405>0)),"Sim","Não") -> Sim | CP105: =Geometria!$O$415 -> 1.57 | CQ105: =IF(OR(AND(CP105<Geometria!$L$1409/100,OR(Geometria!$K$1409>0,Geometria!$K$1407>0)),AND((Geometria!$L$29/100-CP105)<Geometria!$R$1409/100,OR(Geometria!$Q$1409>0,Geometria!$Q$1407>0))),"Sim","Não") -> Não | CR105: σi,5 | CS105: =IF(Geometria!$O$437<Geometria!$N$1307/100,"Reduzir","OK") -> OK | CT105: =IF(CS105="Reduzir",CU105,CW105) -> -3889.8647 | CU105: =-(CZ105/(Geometria!$L$48/100^2))+(DA105/(Geometria!$L$52/100^3))-((Geometria!$O$416)/(Geometria!$L$52/100^3))-((Geometria!$O$427)/(Geometria!$M$52))-((Geometria!$L$76*Geometria!$O$438)/(Geometria!$M$52)) -> -3889.8711 | CV105: =((Geometria!$N$369*(Geometria!$O$897*100))/Geometria!$N$1307) -> 165.55003 | CW105: =-((Geometria!$L$373-(Geometria!$L$373-ER105)*(1-(MIN(MIN(1,MAX(0,(CP105-Geometria!$L$1409/100)/(Geometria!$N$1307/100))),MIN(1,MAX(0,((Geometria!$L$29/100-CP105)-Geometria!$R$1409/100)/(Geometria!$N$1307/100))))))*(IF(OR(Geometria!$K$1409>0,Geometria!$K$1407>0,Geometria!$Q$1409>0,Geometria!$Q$1407>0),1,0))-(Geometria!$L$373-ET105)*(1-(MIN(MIN(1,MAX(0,(CP105-Geometria!$L$1405/100)/(Geometria!$N$1307/100))),MIN(1,MAX(0,((Geometria!$L$29/100-CP105)-Geometria!$R$1405/100)/(Geometria!$N$1307/100))))))*(IF(OR(Geometria!$K$1405>0,Geometria!$K$1403>0,Geometria!$Q$1405>0,Geometria!$Q$1403>0),1,0))))/(Geometria!$L$48/100^2)+((Geometria!$L$374-(Geometria!$L$374-ES105)*(1-(MIN(MIN(1,MAX(0,(CP105-Geometria!$L$1409/100)/(Geometria!$N$1307/100))),MIN(1,MAX(0,((Geometria!$L$29/100-CP105)-Geometria!$R$1409/100)/(Geometria!$N$1307/100))))))*(IF(OR(Geometria!$K$1409>0,Geometria!$K$1407>0,Geometria!$Q$1409>0,Geometria!$Q$1407>0),1,0))-(Geometria!$L$374-EU105)*(1-(MIN(MIN(1,MAX(0,(CP105-Geometria!$L$1405/100)/(Geometria!$N$1307/100))),MIN(1,MAX(0,((Geometria!$L$29/100-CP105)-Geometria!$R$1405/100)/(Geometria!$N$1307/100))))))*(IF(OR(Geometria!$K$1405>0,Geometria!$K$1403>0,Geometria!$Q$1405>0,Geometria!$Q$1403>0),1,0))))/(Geometria!$L$52/100^3)-((Geometria!$O$673)/(Geometria!$L$52/100^3))-((Geometria!$O$684)/(Geometria!$M$52)) -> -3889.8647 | CZ105: =(IF(CQ105="Sim",IF(CO105="Sim",IF(CP105<Geometria!$L$1405/100,Geometria!$L$1435,Geometria!$L$1476),IF(CP105<Geometria!$L$1409/100,Geometria!$L$1442,Geometria!$L$1460)),IF(CO105="Sim",IF(CP105<Geometria!$L$1405/100,Geometria!$L$1444,Geometria!$L$1462),Geometria!$L$298)))*CV128+Geometria!$P$1429*CV105 -> 621.77981 | DA105: =(IF(CQ105="Sim",IF(CO105="Sim",IF(CP105<Geometria!$L$1405/100,Geometria!$L$1435,Geometria!$L$1476),IF(CP105<Geometria!$L$1409/100,Geometria!$L$1442,Geometria!$L$1460)),IF(CO105="Sim",IF(CP105<Geometria!$L$1405/100,Geometria!$L$1444,Geometria!$L$1462),Geometria!$L$298)))*CV128*(IF(CQ105="Sim",IF(CO105="Sim",IF(CP105<Geometria!$L$1405/100,Geometria!$L$1436,Geometria!$L$1484),IF(CP105<Geometria!$L$1409/100,Geometria!$L$1443,Geometria!$L$1461)),IF(CO105="Sim",IF(CP105<Geometria!$L$1405/100,Geometria!$L$1445,Geometria!$L$1463),Geometria!$L$299)))/100-Geometria!$P$1429*CV105*Geometria!$L$1438/100 -> 177.20725 | DC105: =(IF(CQ105="Sim",IF(CO105="Sim",$AB$93,ER105),IF(CO105="Sim",ET105,Geometria!$L$373))) -> 621.77981 | DD105: =(IF(CQ105="Sim",IF(CO105="Sim",$AB$94,ES105),IF(CO105="Sim",EU105,Geometria!$L$374))) -> 177.20725 | DF105: σi,5 | DG105: =CT105 -> -3889.8647 | DH105: kN/m² | DI105: =DG105/1000 -> -3.8898647 | DJ105: MPa | DK105: =DK104 -> 0 | EA105: =-L105/('Aberturas na Alma'!$M$112/100^2)+M105/('Aberturas na Alma'!$M$119/100^3)-Geometria!$L$898/('Aberturas na Alma'!$M$119/100^3) -> 7898.6648 | EB105: =-(IF(C105="Sim",IF(A105="Sim",$E$93,EX105),IF(A105="Sim",EZ105,Geometria!$L$906)))/('Aberturas na Alma'!$M$112/100^2)+(IF(C105="Sim",IF(A105="Sim",$E$94,EY105),IF(A105="Sim",FA105,Geometria!$L$907)))/('Aberturas na Alma'!$M$119/100^3)-Geometria!$O$898/('Aberturas na Alma'!$M$119/100^3) -> 5309.7176 | EC105: =IF(AND('Aberturas na Alma'!$M$18="NÃO DISPENSADO — furo deve ser verificado (cálculo abaixo)",OR(AND(B105>=('Aberturas na Alma'!$M$4-'Aberturas na Alma'!$M$7/2)/100,B105<=('Aberturas na Alma'!$M$4+'Aberturas na Alma'!$M$7/2)/100),ABS(B105-'Aberturas na Alma'!$M$4/100)<=Geometria!$L$29/4000)),IF(E105="Reduzir",EA105,EB105),F105) -> 6248.9352 | ED105: =-(AI105/('Aberturas na Alma'!$M$112/100^2))+(AJ105/('Aberturas na Alma'!$M$119/100^3))-((Geometria!$O$416)/('Aberturas na Alma'!$M$119/100^3))-((Geometria!$O$427)/('Aberturas na Alma'!$M$119/100^3))-((Geometria!$L$76*Geometria!$O$438)/('Aberturas na Alma'!$M$119/100^3)) -> -31744.274 | EE105: =-((IF(Z105="Sim",IF(X105="Sim",$AB$93,ER105),IF(X105="Sim",ET105,Geometria!$L$373)))/('Aberturas na Alma'!$M$112/100^2))+((IF(Z105="Sim",IF(X105="Sim",$AB$94,ES105),IF(X105="Sim",EU105,Geometria!$L$374)))/('Aberturas na Alma'!$M$119/100^3))-((Geometria!$O$416)/('Aberturas na Alma'!$M$119/100^3))-((Geometria!$O$427)/('Aberturas na Alma'!$M$119/100^3))-((Geometria!$L$76*Geometria!$O$438)/('Aberturas na Alma'!$M$119/100^3)) -> -31744.274 | EF105: =IF(AND('Aberturas na Alma'!$M$18="NÃO DISPENSADO — furo deve ser verificado (cálculo abaixo)",OR(AND(B105>=('Aberturas na Alma'!$M$4-'Aberturas na Alma'!$M$7/2)/100,B105<=('Aberturas na Alma'!$M$4+'Aberturas na Alma'!$M$7/2)/100),ABS(B105-'Aberturas na Alma'!$M$4/100)<=Geometria!$L$29/4000)),IF(AB105="Reduzir",ED105,EE105),AC105) -> -3889.8711 | EG105: =-(BF105/('Aberturas na Alma'!$M$112/100^2))+(BG105/('Aberturas na Alma'!$M$119/100^3))-((Geometria!$O$416)/('Aberturas na Alma'!$M$119/100^3))-((Geometria!$O$427)/('Aberturas na Alma'!$M$119/100^3))-((Geometria!$L$76*Geometria!$O$438)/('Aberturas na Alma'!$M$119/100^3)) -> -31744.274 | EH105: =-((IF(AW105="Sim",IF(AU105="Sim",$AB$93,ER105),IF(AU105="Sim",ET105,Geometria!$L$373)))/('Aberturas na Alma'!$M$112/100^2))+((IF(AW105="Sim",IF(AU105="Sim",$AB$94,ES105),IF(AU105="Sim",EU105,Geometria!$L$374)))/('Aberturas na Alma'!$M$119/100^3))-((Geometria!$O$416)/('Aberturas na Alma'!$M$119/100^3))-((Geometria!$O$427)/('Aberturas na Alma'!$M$119/100^3)) -> -6727.8655 | EI105: =IF(AND('Aberturas na Alma'!$M$18="NÃO DISPENSADO — furo deve ser verificado (cálculo abaixo)",OR(AND(B105>=('Aberturas na Alma'!$M$4-'Aberturas na Alma'!$M$7/2)/100,B105<=('Aberturas na Alma'!$M$4+'Aberturas na Alma'!$M$7/2)/100),ABS(B105-'Aberturas na Alma'!$M$4/100)<=Geometria!$L$29/4000)),IF(AY105="Reduzir",EG105,EH105),AZ105) -> -3889.8647 | EJ105: =-(CC105/('Aberturas na Alma'!$M$112/100^2))+(CD105/('Aberturas na Alma'!$M$119/100^3))-((Geometria!$O$416)/('Aberturas na Alma'!$M$119/100^3))-((Geometria!$O$427)/('Aberturas na Alma'!$M$119/100^3))-((Geometria!$L$76*Geometria!$O$438)/('Aberturas na Alma'!$M$119/100^3)) -> -31744.274 | EK105: =-((IF(BT105="Sim",IF(BR105="Sim",$AB$93,ER105),IF(BR105="Sim",ET105,Geometria!$L$373)))/('Aberturas na Alma'!$M$112/100^2))+((IF(BT105="Sim",IF(BR105="Sim",$AB$94,ES105),IF(BR105="Sim",EU105,Geometria!$L$374)))/('Aberturas na Alma'!$M$119/100^3))-((Geometria!$O$673)/('Aberturas na Alma'!$M$119/100^3))-((Geometria!$O$684)/('Aberturas na Alma'!$M$119/100^3))-((Geometria!$L$77*Geometria!$O$695)/('Aberturas na Alma'!$M$119/100^3)) -> -23405.471 | EL105: =IF(AND('Aberturas na Alma'!$M$18="NÃO DISPENSADO — furo deve ser verificado (cálculo abaixo)",OR(AND(B105>=('Aberturas na Alma'!$M$4-'Aberturas na Alma'!$M$7/2)/100,B105<=('Aberturas na Alma'!$M$4+'Aberturas na Alma'!$M$7/2)/100),ABS(B105-'Aberturas na Alma'!$M$4/100)<=Geometria!$L$29/4000)),IF(BV105="Reduzir",EJ105,EK105),BW105) -> -3889.8689 | EM105: =-(CZ105/('Aberturas na Alma'!$M$112/100^2))+(DA105/('Aberturas na Alma'!$M$119/100^3))-((Geometria!$O$416)/('Aberturas na Alma'!$M$119/100^3))-((Geometria!$O$427)/('Aberturas na Alma'!$M$119/100^3))-((Geometria!$L$76*Geometria!$O$438)/('Aberturas na Alma'!$M$119/100^3)) -> -31744.274 | EN105: =-((IF(CQ105="Sim",IF(CO105="Sim",$AB$93,ER105),IF(CO105="Sim",ET105,Geometria!$L$373)))/('Aberturas na Alma'!$M$112/100^2))+((IF(CQ105="Sim",IF(CO105="Sim",$AB$94,ES105),IF(CO105="Sim",EU105,Geometria!$L$374)))/('Aberturas na Alma'!$M$119/100^3))-((Geometria!$O$673)/('Aberturas na Alma'!$M$119/100^3))-((Geometria!$O$684)/('Aberturas na Alma'!$M$119/100^3)) -> -6727.8655 | EO105: =IF(AND('Aberturas na Alma'!$M$18="NÃO DISPENSADO — furo deve ser verificado (cálculo abaixo)",OR(AND(B105>=('Aberturas na Alma'!$M$4-'Aberturas na Alma'!$M$7/2)/100,B105<=('Aberturas na Alma'!$M$4+'Aberturas na Alma'!$M$7/2)/100),ABS(B105-'Aberturas na Alma'!$M$4/100)<=Geometria!$L$29/4000)),IF(CS105="Reduzir",EM105,EN105),CT105) -> -3889.8647 | EP105: =IF(AND(Y105<Geometria!$L$1409/100,OR(Geometria!$K$1409>0,Geometria!$K$1407>0)),"ESQ",IF(AND((Geometria!$L$29/100-Y105)<Geometria!$R$1409/100,OR(Geometria!$Q$1409>0,Geometria!$Q$1407>0)),"DIR","N/A")) -> N/A | EQ105: =IF(AND(Y105<Geometria!$L$1405/100,Geometria!$K$1405>0),"ESQ",IF(AND((Geometria!$L$29/100-Y105)<Geometria!$R$1405/100,Geometria!$Q$1405>0),"DIR","N/A")) -> ESQ | ER105: =IF(EP105="DIR",Geometria!$L$1470,Geometria!$L$1452) -> 1243.5596 | ES105: =IF(EP105="DIR",Geometria!$L$1471,Geometria!$L$1453) -> 233.16743 | ET105: =IF(EQ105="DIR",Geometria!$L$1472,Geometria!$L$1454) -> 621.77981 | EU105: =IF(EQ105="DIR",Geometria!$L$1473,Geometria!$L$1455) -> 177.20725 | EV105: =IF(AND(B105<Geometria!$L$1409/100,OR(Geometria!$K$1409>0,Geometria!$K$1407>0)),"ESQ",IF(AND((Geometria!$L$29/100-B105)<Geometria!$R$1409/100,OR(Geometria!$Q$1409>0,Geometria!$Q$1407>0)),"DIR","N/A")) -> N/A | EW105: =IF(AND(B105<Geometria!$L$1405/100,Geometria!$K$1405>0),"ESQ",IF(AND((Geometria!$L$29/100-B105)<Geometria!$R$1405/100,Geometria!$Q$1405>0),"DIR","N/A")) -> ESQ | EX105: =IF(EV105="DIR",Geometria!$L$1465,Geometria!$L$1447) -> 1499.8056 | EY105: =IF(EV105="DIR",Geometria!$L$1466,Geometria!$L$1448) -> 281.21355 | EZ105: =IF(EW105="DIR",Geometria!$L$1467,Geometria!$L$1449) -> 749.9028 | FA105: =IF(EW105="DIR",Geometria!$L$1468,Geometria!$L$1450) -> 213.7223
